Workbook

Sheet Foglio1
M4: servizi singoli | N4: servizi di gruppo
M6: =GETPIVOTDATA("Ore",$A$4,"Addetto","CROCE MARIA GRAZIA")*27 -> 1296 | O6: croce 120
M8: =GETPIVOTDATA("Ore",$A$4,"Addetto","FALCONE SERENA")*25 -> 9037.5 | N8: =71*35 -> 2485 | O8: falcone 71
M10: =GETPIVOTDATA("Ore",$A$4,"Addetto","LA MANTIA DANILO")*25 -> #REF!
M11: =GETPIVOTDATA("Ore",$A$4,"Addetto","MAINERO CLAUDIA")*25 -> 14475 | N11: =52*35 -> 1820 | O11: mainero 52
M20: =SUM(M6:M19) -> #REF!

Sheet exp_SILP
A1: CF su Proforma | B1: Servizio PROFORMA | C1: COMMESSA | D1: Dalle | E1: Alle | F1: Ore | G1: Codice Fiscale Docente | H1: Codice Voce di Spesa | I1: BackOffice (S,N) | J1: Codice Sede | K1: N | L1: VALORE CM | M1: VALORE COMMESSE | N1: PROGETTO | O1: RICAVI | P1: Sesso (M,F) | Q1: Data | R1: Orario | S1: Servizio | T1: Ambito | U1: Progetto2 | V1: Soggetto | W1: Codice fiscale | X1: Data di nascita | Y1: Addetto | Z1: Esito | AA1: Ente | AB1: Tipologia | AC1: Luogo | AD1: Altro luogo | AE1: Motivazione | AF1: Note | AG1: Durata | AH1: Data esito | AI1: Utente inserimento | AJ1: CF CM
A2: =IFERROR(VLOOKUP(exp_SILP!$W2,exp_utenti_P!D:D,1,FALSE),"_DA INSERIRE") -> BNMKLD71A18Z330T | B2: =IF(AND(exp_SILP!$S2="A.3 ORIENTAMENTO PROFESSIONALE",exp_SILP!$AD2="4.2"),"A.3 ORIENTAMENTO PROFESSIONALE (CARCERE)", IF(AND(exp_SILP!$S2="A.3 ORIENTAMENTO PROFESSIONALE",exp_SILP!$AD2="."),"A.3 ORIENTAMENTO PROFESSIONALE (CARCERE)", IF(AND(exp_SILP!$S2="A.4 CONSULENZA ORIENTATIVA",exp_SILP!$AD2="4.2"),"A.4 CONSULENZA ORIENTATIVA (CARCERE)", IF(AND(exp_SILP!$S2="A.4 CONSULENZA ORIENTATIVA",exp_SILP!$AD2="."),"A.4 CONSULENZA ORIENTATIVA (CARCERE)", IF(AND(exp_SILP!$S2="A.5 - LEP F1 - ACCOMPAGNAMENTO AL LAVORO",exp_SILP!$AD2="4.2"),"A.5 - LEP F1 - ACCOMPAGNAMENTO AL LAVORO (CARCERE)", IF(AND(exp_SILP!$S2="A.5 - LEP F1 - ACCOMPAGNAMENTO AL LAVORO",exp_SILP!$AD2="."),"A.5 - LEP F1 - ACCOMPAGNAMENTO AL LAVORO (CARCERE)", IF(AND(exp_SILP!$S2="A.5.2a - TUTORAGGIO TIROCINI",exp_SILP!$AD2="4.2"),"A.5.2a - TUTORAGGIO TIROCINI (CARCERE)", exp_SILP!$S2))))))) -> A.5 - LEP F1 - ACCOMPAGNAMENTO AL LAVORO | C2: =CONCATENATE(VLOOKUP(exp_SILP!$B2,'DATI COMMESSE'!$A$2:$F$25,4,FALSE)," - ", VLOOKUP(exp_SILP!$B2,'DATI COMMESSE'!$A$2:$F$25,2,FALSE)," - ",VLOOKUP(exp_SILP!$B2,'DATI COMMESSE'!$A$2:$F$25,3,FALSE)) -> GOL - 22-02-5000 - 22-12-5003 | D2: =LEFT(exp_SILP!$R2,5) -> 14:00 | E2: =RIGHT(exp_SILP!$R2,5) -> 15:00 | F2: =IF(exp_SILP!$AG2>=60,exp_SILP!$AG2/60,exp_SILP!$AG2) -> 1 | G2: =VLOOKUP(exp_SILP!$Y2,'DATI CM'!$A$2:$F$28,2,FALSE) -> PNFMRT85H50A859E | H2: =VLOOKUP(exp_SILP!$Y2,'DATI CM'!$A$2:$F$28,3,FALSE) -> A011 | I2: =IF(A2>0,"N","N") -> N | J2: =VLOOKUP(exp_SILP!$Y2,'DATI CM'!$A$2:$F$28,4,FALSE) -> BIELLA | K2: =VLOOKUP(exp_SILP!$B2,'DATI COMMESSE'!$A$2:$F$25,5,FALSE) -> 39.94 | L2: =IF(exp_SILP!$B2="A4.10 - LEP E - ORIENTAMENTO SPECIALISTICO SKILL GAP ANALYSIS - GRUPPO 3P",0,VLOOKUP(exp_SILP!$Y2,'DATI CM'!$A$2:$F$28,6,FALSE)) -> 25 | M2: =IFERROR(VLOOKUP(exp_SILP!$B2,'DATI CM'!$H$2:$I$16,2,FALSE)*exp_SILP!$F2,0) -> 0 | N2: =VLOOKUP(exp_SILP!$B2,'DATI COMMESSE'!$A$2:$F$25,4,FALSE) -> GOL | O2: =VLOOKUP(exp_SILP!$B2,'DATI COMMESSE'!$A$2:$F$25,5,FALSE)*exp_SILP!$F2 -> 39.94 | P2: =IF(MID(exp_SILP!$W2,10,2)>"40","F","M") -> M | Q2: 01/02/2023 | R2: 14:00-15:00 | S2: A.5 - LEP F1 - ACCOMPAGNAMENTO AL LAVORO | T2: Progetti per accreditati | V2: BENAIM KHALID | W2: BNMKLD71A18Z330T | X2: 18/01/1971 | Y2: PIANOFORTE MARTA | Z2: Erogato | AA2: INFORCOOP ECIPA PIEMONTE | AB2: Incontro MDL | AC2: INFORCOOP ECIPA PIEMONTE STRADA CAMPAGNE' 7 - BIELLA | AG2: 60 | AH2: 01/02/2023 | AI2: PNFMRT85H50A859E | AJ2: =VLOOKUP(exp_SILP!$Y2,'DATI CM'!$A$2:$F$28,2,FALSE) -> PNFMRT85H50A859E
A3: =IFERROR(VLOOKUP(exp_SILP!$W3,exp_utenti_P!D:D,1,FALSE),"_DA INSERIRE") -> GLLGLC68P10L219E | B3: =IF(AND(exp_SILP!$S3="A.3 ORIENTAMENTO PROFESSIONALE",exp_SILP!$AD3="4.2"),"A.3 ORIENTAMENTO PROFESSIONALE (CARCERE)", IF(AND(exp_SILP!$S3="A.3 ORIENTAMENTO PROFESSIONALE",exp_SILP!$AD3="."),"A.3 ORIENTAMENTO PROFESSIONALE (CARCERE)", IF(AND(exp_SILP!$S3="A.4 CONSULENZA ORIENTATIVA",exp_SILP!$AD3="4.2"),"A.4 CONSULENZA ORIENTATIVA (CARCERE)", IF(AND(exp_SILP!$S3="A.4 CONSULENZA ORIENTATIVA",exp_SILP!$AD3="."),"A.4 CONSULENZA ORIENTATIVA (CARCERE)", IF(AND(exp_SILP!$S3="A.5 - LEP F1 - ACCOMPAGNAMENTO AL LAVORO",exp_SILP!$AD3="4.2"),"A.5 - LEP F1 - ACCOMPAGNAMENTO AL LAVORO (CARCERE)", IF(AND(exp_SILP!$S3="A.5 - LEP F1 - ACCOMPAGNAMENTO AL LAVORO",exp_SILP!$AD3="."),"A.5 - LEP F1 - ACCOMPAGNAMENTO AL LAVORO (CARCERE)", IF(AND(exp_SILP!$S3="A.5.2a - TUTORAGGIO TIROCINI",exp_SILP!$AD3="4.2"),"A.5.2a - TUTORAGGIO TIROCINI (CARCERE)", exp_SILP!$S3))))))) -> A4.10 - LEP E - ORIENTAMENTO SPECIALISTICO SKILL GAP ANALYSIS | C3: =CONCATENATE(VLOOKUP(exp_SILP!$B3,'DATI COMMESSE'!$A$2:$F$25,4,FALSE)," - ", VLOOKUP(exp_SILP!$B3,'DATI COMMESSE'!$A$2:$F$25,2,FALSE)," - ",VLOOKUP(exp_SILP!$B3,'DATI COMMESSE'!$A$2:$F$25,3,FALSE)) -> GOL - 22-02-5000 - 22-12-5003 | D3: =LEFT(exp_SILP!$R3,5) -> 14:00 | E3: =RIGHT(exp_SILP!$R3,5) -> 16:00 | F3: =IF(exp_SILP!$AG3>=60,exp_SILP!$AG3/60,exp_SILP!$AG3) -> 2 | G3: =VLOOKUP(exp_SILP!$Y3,'DATI CM'!$A$2:$F$28,2,FALSE) -> FLCSRN79S42L219X | H3: =VLOOKUP(exp_SILP!$Y3,'DATI CM'!$A$2:$F$28,3,FALSE) -> A011 | I3: =IF(A3>0,"N","N") -> N | J3: =VLOOKUP(exp_SILP!$Y3,'DATI CM'!$A$2:$F$28,4,FALSE) -> TORINO | K3: =VLOOKUP(exp_SILP!$B3,'DATI COMMESSE'!$A$2:$F$25,5,FALSE) -> 39.94 | L3: =IF(exp_SILP!$B3="A4.10 - LEP E - ORIENTAMENTO SPECIALISTICO SKILL GAP ANALYSIS - GRUPPO 3P",0,VLOOKUP(exp_SILP!$Y3,'DATI CM'!$A$2:$F$28,6,FALSE)) -> 25 | M3: =IFERROR(VLOOKUP(exp_SILP!$B3,'DATI CM'!$H$2:$I$16,2,FALSE)*exp_SILP!$F3,0) -> 0 | N3: =VLOOKUP(exp_SILP!$B3,'DATI COMMESSE'!$A$2:$F$25,4,FALSE) -> GOL | O3: =VLOOKUP(exp_SILP!$B3,'DATI COMMESSE'!$A$2:$F$25,5,FALSE)*exp_SILP!$F3 -> 79.88 | P3: =IF(MID(exp_SILP!$W3,10,2)>"40","F","M") -> M | Q3: 01/02/2023 | R3: 14:00-16:00 | S3: A4.10 - LEP E - ORIENTAMENTO SPECIALISTICO SKILL GAP ANALYSIS | T3: Progetti per accreditati | V3: UGLIOLA GIANLUCA | W3: GLLGLC68P10L219E | X3: 10/09/1968 | Y3: FALCONE SERENA | Z3: Erogato | AA3: INFORCOOP ECIPA PIEMONTE | AB3: Incontro MDLpresentato | AC3: INFORCOOP ECIPA PIEMONTE VIA LIVORNO 53/b - TORINO | AG3: 120 | AH3: 01/02/2023 | AI3: FLCSRN79S42L219X | AJ3: =VLOOKUP(exp_SILP!$Y3,'DATI CM'!$A$2:$F$28,2,FALSE) -> FLCSRN79S42L219X
A4: =IFERROR(VLOOKUP(exp_SILP!$W4,exp_utenti_P!D:D,1,FALSE),"_DA INSERIRE") -> CLMCRN71T70B019R | B4: =IF(AND(exp_SILP!$S4="A.3 ORIENTAMENTO PROFESSIONALE",exp_SILP!$AD4="4.2"),"A.3 ORIENTAMENTO PROFESSIONALE (CARCERE)", IF(AND(exp_SILP!$S4="A.3 ORIENTAMENTO PROFESSIONALE",exp_SILP!$AD4="."),"A.3 ORIENTAMENTO PROFESSIONALE (CARCERE)", IF(AND(exp_SILP!$S4="A.4 CONSULENZA ORIENTATIVA",exp_SILP!$AD4="4.2"),"A.4 CONSULENZA ORIENTATIVA (CARCERE)", IF(AND(exp_SILP!$S4="A.4 CONSULENZA ORIENTATIVA",exp_SILP!$AD4="."),"A.4 CONSULENZA ORIENTATIVA (CARCERE)", IF(AND(exp_SILP!$S4="A.5 - LEP F1 - ACCOMPAGNAMENTO AL LAVORO",exp_SILP!$AD4="4.2"),"A.5 - LEP F1 - ACCOMPAGNAMENTO AL LAVORO (CARCERE)", IF(AND(exp_SILP!$S4="A.5 - LEP F1 - ACCOMPAGNAMENTO AL LAVORO",exp_SILP!$AD4="."),"A.5 - LEP F1 - ACCOMPAGNAMENTO AL LAVORO (CARCERE)", IF(AND(exp_SILP!$S4="A.5.2a - TUTORAGGIO TIROCINI",exp_SILP!$AD4="4.2"),"A.5.2a - TUTORAGGIO TIROCINI (CARCERE)", exp_SILP!$S4))))))) -> A4.10 - LEP E - ORIENTAMENTO SPECIALISTICO SKILL GAP ANALYSIS | C4: =CONCATENATE(VLOOKUP(exp_SILP!$B4,'DATI COMMESSE'!$A$2:$F$25,4,FALSE)," - ", VLOOKUP(exp_SILP!$B4,'DATI COMMESSE'!$A$2:$F$25,2,FALSE)," - ",VLOOKUP(exp_SILP!$B4,'DATI COMMESSE'!$A$2:$F$25,3,FALSE)) -> GOL - 22-02-5000 - 22-12-5003 | D4: =LEFT(exp_SILP!$R4,5) -> 09:30 | E4: =RIGHT(exp_SILP!$R4,5) -> 11:30 | F4: =IF(exp_SILP!$AG4>=60,exp_SILP!$AG4/60,exp_SILP!$AG4) -> 2 | G4: =VLOOKUP(exp_SILP!$Y4,'DATI CM'!$A$2:$F$28,2,FALSE) -> TRZCST69B41F952V | H4: =VLOOKUP(exp_SILP!$Y4,'DATI CM'!$A$2:$F$28,3,FALSE) | I4: =IF(A4>0,"N","N") -> N | J4: =VLOOKUP(exp_SILP!$Y4,'DATI CM'!$A$2:$F$28,4,FALSE) | K4: =VLOOKUP(exp_SILP!$B4,'DATI COMMESSE'!$A$2:$F$25,5,FALSE) -> 39.94 | L4: =IF(exp_SILP!$B4="A4.10 - LEP E - ORIENTAMENTO SPECIALISTICO SKILL GAP ANALYSIS - GRUPPO 3P",0,VLOOKUP(exp_SILP!$Y4,'DATI CM'!$A$2:$F$28,6,FALSE)) | M4: =IFERROR(VLOOKUP(exp_SILP!$B4,'DATI CM'!$H$2:$I$16,2,FALSE)*exp_SILP!$F4,0) -> 0 | N4: =VLOOKUP(exp_SILP!$B4,'DATI COMMESSE'!$A$2:$F$25,4,FALSE) -> GOL | O4: =VLOOKUP(exp_SILP!$B4,'DATI COMMESSE'!$A$2:$F$25,5,FALSE)*exp_SILP!$F4 -> 79.88 | P4: =IF(MID(exp_SILP!$W4,10,2)>"40","F","M") -> F | Q4: 01/02/2023 | R4: 09:30-11:30 | S4: A4.10 - LEP E - ORIENTAMENTO SPECIALISTICO SKILL GAP ANALYSIS | T4: Progetti per accreditati | V4: COLOMBO CATERINA | W4: CLMCRN71T70B019R | X4: 30/12/1971 | Y4: TERZERA CRISTINA | Z4: Erogato | AA4: INFORCOOP ECIPA PIEMONTE | AB4: Incontro MDL | AC4: INFORCOOP ECIPA PIEMONTE VIA UGO PORZIO GIOVANOLA 7 - NOVARA | AG4: 120 | AH4: 01/02/2023 | AI4: TRZCST69B41F952V | AJ4: =VLOOKUP(exp_SILP!$Y4,'DATI CM'!$A$2:$F$28,2,FALSE) -> TRZCST69B41F952V
A5: =IFERROR(VLOOKUP(exp_SILP!$W5,exp_utenti_P!D:D,1,FALSE),"_DA INSERIRE") -> MNTSRH76E27Z138U | B5: =IF(AND(exp_SILP!$S5="A.3 ORIENTAMENTO PROFESSIONALE",exp_SILP!$AD5="4.2"),"A.3 ORIENTAMENTO PROFESSIONALE (CARCERE)", IF(AND(exp_SILP!$S5="A.3 ORIENTAMENTO PROFESSIONALE",exp_SILP!$AD5="."),"A.3 ORIENTAMENTO PROFESSIONALE (CARCERE)", IF(AND(exp_SILP!$S5="A.4 CONSULENZA ORIENTATIVA",exp_SILP!$AD5="4.2"),"A.4 CONSULENZA ORIENTATIVA (CARCERE)", IF(AND(exp_SILP!$S5="A.4 CONSULENZA ORIENTATIVA",exp_SILP!$AD5="."),"A.4 CONSULENZA ORIENTATIVA (CARCERE)", IF(AND(exp_SILP!$S5="A.5 - LEP F1 - ACCOMPAGNAMENTO AL LAVORO",exp_SILP!$AD5="4.2"),"A.5 - LEP F1 - ACCOMPAGNAMENTO AL LAVORO (CARCERE)", IF(AND(exp_SILP!$S5="A.5 - LEP F1 - ACCOMPAGNAMENTO AL LAVORO",exp_SILP!$AD5="."),"A.5 - LEP F1 - ACCOMPAGNAMENTO AL LAVORO (CARCERE)", IF(AND(exp_SILP!$S5="A.5.2a - TUTORAGGIO TIROCINI",exp_SILP!$AD5="4.2"),"A.5.2a - TUTORAGGIO TIROCINI (CARCERE)", exp_SILP!$S5))))))) -> A4.10 - LEP E - ORIENTAMENTO SPECIALISTICO SKILL GAP ANALYSIS | C5: =CONCATENATE(VLOOKUP(exp_SILP!$B5,'DATI COMMESSE'!$A$2:$F$25,4,FALSE)," - ", VLOOKUP(exp_SILP!$B5,'DATI COMMESSE'!$A$2:$F$25,2,FALSE)," - ",VLOOKUP(exp_SILP!$B5,'DATI COMMESSE'!$A$2:$F$25,3,FALSE)) -> GOL - 22-02-5000 - 22-12-5003 | D5: =LEFT(exp_SILP!$R5,5) -> 12:00 | E5: =RIGHT(exp_SILP!$R5,5) -> 14:00 | F5: =IF(exp_SILP!$AG5>=60,exp_SILP!$AG5/60,exp_SILP!$AG5) -> 2 | G5: =VLOOKUP(exp_SILP!$Y5,'DATI CM'!$A$2:$F$28,2,FALSE) -> PNFMRT85H50A859E | H5: =VLOOKUP(exp_SILP!$Y5,'DATI CM'!$A$2:$F$28,3,FALSE) -> A011 | I5: =IF(A5>0,"N","N") -> N | J5: =VLOOKUP(exp_SILP!$Y5,'DATI CM'!$A$2:$F$28,4,FALSE) -> BIELLA | K5: =VLOOKUP(exp_SILP!$B5,'DATI COMMESSE'!$A$2:$F$25,5,FALSE) -> 39.94 | L5: =IF(exp_SILP!$B5="A4.10 - LEP E - ORIENTAMENTO SPECIALISTICO SKILL GAP ANALYSIS - GRUPPO 3P",0,VLOOKUP(exp_SILP!$Y5,'DATI CM'!$A$2:$F$28,6,FALSE)) -> 25 | M5: =IFERROR(VLOOKUP(exp_SILP!$B5,'DATI CM'!$H$2:$I$16,2,FALSE)*exp_SILP!$F5,0) -> 0 | N5: =VLOOKUP(exp_SILP!$B5,'DATI COMMESSE'!$A$2:$F$25,4,FALSE) -> GOL | O5: =VLOOKUP(exp_SILP!$B5,'DATI COMMESSE'!$A$2:$F$25,5,FALSE)*exp_SILP!$F5 -> 79.88 | P5: =IF(MID(exp_SILP!$W5,10,2)>"40","F","M") -> M | Q5: 01/02/2023 | R5: 12:00-14:00 | S5: A4.10 - LEP E - ORIENTAMENTO SPECIALISTICO SKILL GAP ANALYSIS | T5: Progetti per accreditati | V5: MINTENKU SERHII | W5: MNTSRH76E27Z138U | X5: 27/05/1976 | Y5: PIANOFORTE MARTA | Z5: Erogato | AA5: INFORCOOP ECIPA PIEMONTE | AB5: Incontro MDL | AC5: INFORCOOP ECIPA PIEMONTE STRADA CAMPAGNE' 7 - BIELLA | AG5: 120 | AH5: 01/02/2023 | AI5: PNFMRT85H50A859E | AJ5: =VLOOKUP(exp_SILP!$Y5,'DATI CM'!$A$2:$F$28,2,FALSE) -> PNFMRT85H50A859E
A6: =IFERROR(VLOOKUP(exp_SILP!$W6,exp_utenti_P!D:D,1,FALSE),"_DA INSERIRE") -> RSNMRA72A46D872J | B6: =IF(AND(exp_SILP!$S6="A.3 ORIENTAMENTO PROFESSIONALE",exp_SILP!$AD6="4.2"),"A.3 ORIENTAMENTO PROFESSIONALE (CARCERE)", IF(AND(exp_SILP!$S6="A.3 ORIENTAMENTO PROFESSIONALE",exp_SILP!$AD6="."),"A.3 ORIENTAMENTO PROFESSIONALE (CARCERE)", IF(AND(exp_SILP!$S6="A.4 CONSULENZA ORIENTATIVA",exp_SILP!$AD6="4.2"),"A.4 CONSULENZA ORIENTATIVA (CARCERE)", IF(AND(exp_SILP!$S6="A.4 CONSULENZA ORIENTATIVA",exp_SILP!$AD6="."),"A.4 CONSULENZA ORIENTATIVA (CARCERE)", IF(AND(exp_SILP!$S6="A.5 - LEP F1 - ACCOMPAGNAMENTO AL LAVORO",exp_SILP!$AD6="4.2"),"A.5 - LEP F1 - ACCOMPAGNAMENTO AL LAVORO (CARCERE)", IF(AND(exp_SILP!$S6="A.5 - LEP F1 - ACCOMPAGNAMENTO AL LAVORO",exp_SILP!$AD6="."),"A.5 - LEP F1 - ACCOMPAGNAMENTO AL LAVORO (CARCERE)", IF(AND(exp_SILP!$S6="A.5.2a - TUTORAGGIO TIROCINI",exp_SILP!$AD6="4.2"),"A.5.2a - TUTORAGGIO TIROCINI (CARCERE)", exp_SILP!$S6))))))) -> A4.10 - LEP E - ORIENTAMENTO SPECIALISTICO SKILL GAP ANALYSIS | C6: =CONCATENATE(VLOOKUP(exp_SILP!$B6,'DATI COMMESSE'!$A$2:$F$25,4,FALSE)," - ", VLOOKUP(exp_SILP!$B6,'DATI COMMESSE'!$A$2:$F$25,2,FALSE)," - ",VLOOKUP(exp_SILP!$B6,'DATI COMMESSE'!$A$2:$F$25,3,FALSE)) -> GOL - 22-02-5000 - 22-12-5003 | D6: =LEFT(exp_SILP!$R6,5) -> 11:30 | E6: =RIGHT(exp_SILP!$R6,5) -> 13:30 | F6: =IF(exp_SILP!$AG6>=60,exp_SILP!$AG6/60,exp_SILP!$AG6) -> 2 | G6: =VLOOKUP(exp_SILP!$Y6,'DATI CM'!$A$2:$F$28,2,FALSE) -> TRZCST69B41F952V | H6: =VLOOKUP(exp_SILP!$Y6,'DATI CM'!$A$2:$F$28,3,FALSE) | I6: =IF(A6>0,"N","N") -> N | J6: =VLOOKUP(exp_SILP!$Y6,'DATI CM'!$A$2:$F$28,4,FALSE) | K6: =VLOOKUP(exp_SILP!$B6,'DATI COMMESSE'!$A$2:$F$25,5,FALSE) -> 39.94 | L6: =IF(exp_SILP!$B6="A4.10 - LEP E - ORIENTAMENTO SPECIALISTICO SKILL GAP ANALYSIS - GRUPPO 3P",0,VLOOKUP(exp_SILP!$Y6,'DATI CM'!$A$2:$F$28,6,FALSE)) | M6: =IFERROR(VLOOKUP(exp_SILP!$B6,'DATI CM'!$H$2:$I$16,2,FALSE)*exp_SILP!$F6,0) -> 0 | N6: =VLOOKUP(exp_SILP!$B6,'DATI COMMESSE'!$A$2:$F$25,4,FALSE) -> GOL | O6: =VLOOKUP(exp_SILP!$B6,'DATI COMMESSE'!$A$2:$F$25,5,FALSE)*exp_SILP!$F6 -> 79.88 | P6: =IF(MID(exp_SILP!$W6,10,2)>"40","F","M") -> F | Q6: 01/02/2023 | R6: 11:30-13:30 | S6: A4.10 - LEP E - ORIENTAMENTO SPECIALISTICO SKILL GAP ANALYSIS | T6: Progetti per accreditati | V6: ORSINA MARA | W6: RSNMRA72A46D872J | X6: 06/01/1972 | Y6: TERZERA CRISTINA | Z6: Erogato | AA6: INFORCOOP ECIPA PIEMONTE | AB6: Incontro MDL | AC6: INFORCOOP ECIPA PIEMONTE VIA UGO PORZIO GIOVANOLA 7 - NOVARA | AG6: 120 | AH6: 01/02/2023 | AI6: TRZCST69B41F952V | AJ6: =VLOOKUP(exp_SILP!$Y6,'DATI CM'!$A$2:$F$28,2,FALSE) -> TRZCST69B41F952V
A7: =IFERROR(VLOOKUP(exp_SILP!$W7,exp_utenti_P!D:D,1,FALSE),"_DA INSERIRE") -> MTAGRG64C06Z129P | B7: =IF(AND(exp_SILP!$S7="A.3 ORIENTAMENTO PROFESSIONALE",exp_SILP!$AD7="4.2"),"A.3 ORIENTAMENTO PROFESSIONALE (CARCERE)", IF(AND(exp_SILP!$S7="A.3 ORIENTAMENTO PROFESSIONALE",exp_SILP!$AD7="."),"A.3 ORIENTAMENTO PROFESSIONALE (CARCERE)", IF(AND(exp_SILP!$S7="A.4 CONSULENZA ORIENTATIVA",exp_SILP!$AD7="4.2"),"A.4 CONSULENZA ORIENTATIVA (CARCERE)", IF(AND(exp_SILP!$S7="A.4 CONSULENZA ORIENTATIVA",exp_SILP!$AD7="."),"A.4 CONSULENZA ORIENTATIVA (CARCERE)", IF(AND(exp_SILP!$S7="A.5 - LEP F1 - ACCOMPAGNAMENTO AL LAVORO",exp_SILP!$AD7="4.2"),"A.5 - LEP F1 - ACCOMPAGNAMENTO AL LAVORO (CARCERE)", IF(AND(exp_SILP!$S7="A.5 - LEP F1 - ACCOMPAGNAMENTO AL LAVORO",exp_SILP!$AD7="."),"A.5 - LEP F1 - ACCOMPAGNAMENTO AL LAVORO (CARCERE)", IF(AND(exp_SILP!$S7="A.5.2a - TUTORAGGIO TIROCINI",exp_SILP!$AD7="4.2"),"A.5.2a - TUTORAGGIO TIROCINI (CARCERE)", exp_SILP!$S7))))))) -> A.4 CONSULENZA ORIENTATIVA (1-C) | C7: =CONCATENATE(VLOOKUP(exp_SILP!$B7,'DATI COMMESSE'!$A$2:$F$25,4,FALSE)," - ", VLOOKUP(exp_SILP!$B7,'DATI COMMESSE'!$A$2:$F$25,2,FALSE)," - ",VLOOKUP(exp_SILP!$B7,'DATI COMMESSE'!$A$2:$F$25,3,FALSE)) -> FRD - 22-02-5000 - 22-12-5002 | D7: =LEFT(exp_SILP!$R7,5) -> 17:00 | E7: =RIGHT(exp_SILP!$R7,5) -> 18:00 | F7: =IF(exp_SILP!$AG7>=60,exp_SILP!$AG7/60,exp_SILP!$AG7) -> 1 | G7: =VLOOKUP(exp_SILP!$Y7,'DATI CM'!$A$2:$F$28,2,FALSE) -> FLCSRN79S42L219X | H7: =VLOOKUP(exp_SILP!$Y7,'DATI CM'!$A$2:$F$28,3,FALSE) -> A011 | I7: =IF(A7>0,"N","N") -> N | J7: =VLOOKUP(exp_SILP!$Y7,'DATI CM'!$A$2:$F$28,4,FALSE) -> TORINO | K7: =VLOOKUP(exp_SILP!$B7,'DATI COMMESSE'!$A$2:$F$25,5,FALSE) -> 35.5 | L7: =IF(exp_SILP!$B7="A4.10 - LEP E - ORIENTAMENTO SPECIALISTICO SKILL GAP ANALYSIS - GRUPPO 3P",0,VLOOKUP(exp_SILP!$Y7,'DATI CM'!$A$2:$F$28,6,FALSE)) -> 25 | M7: =IFERROR(VLOOKUP(exp_SILP!$B7,'DATI CM'!$H$2:$I$16,2,FALSE)*exp_SILP!$F7,0) -> 0 | N7: =VLOOKUP(exp_SILP!$B7,'DATI COMMESSE'!$A$2:$F$25,4,FALSE) -> FRD | O7: =VLOOKUP(exp_SILP!$B7,'DATI COMMESSE'!$A$2:$F$25,5,FALSE)*exp_SILP!$F7 -> 35.5 | P7: =IF(MID(exp_SILP!$W7,10,2)>"40","F","M") -> M | Q7: 01/03/2023 | R7: 17:00-18:00 | S7: A.4 CONSULENZA ORIENTATIVA (1-C) | T7: Progetti per accreditati | V7: MATEI GHEORGHE | W7: MTAGRG64C06Z129P | X7: 06/03/1964 | Y7: FALCONE SERENA | Z7: Erogato | AA7: INFORCOOP ECIPA PIEMONTE | AB7: Incontro MDL | AC7: INFORCOOP ECIPA PIEMONTE VIA LIVORNO 53/b - TORINO | AF7: BACK OFFICE | AG7: 60 | AH7: 03/03/2023 | AI7: FLCSRN79S42L219X | AJ7: =VLOOKUP(exp_SILP!$Y7,'DATI CM'!$A$2:$F$28,2,FALSE) -> FLCSRN79S42L219X
A8: =IFERROR(VLOOKUP(exp_SILP!$W8,exp_utenti_P!D:D,1,FALSE),"_DA INSERIRE") -> MTAGRG64C06Z129P | B8: =IF(AND(exp_SILP!$S8="A.3 ORIENTAMENTO PROFESSIONALE",exp_SILP!$AD8="4.2"),"A.3 ORIENTAMENTO PROFESSIONALE (CARCERE)", IF(AND(exp_SILP!$S8="A.3 ORIENTAMENTO PROFESSIONALE",exp_SILP!$AD8="."),"A.3 ORIENTAMENTO PROFESSIONALE (CARCERE)", IF(AND(exp_SILP!$S8="A.4 CONSULENZA ORIENTATIVA",exp_SILP!$AD8="4.2"),"A.4 CONSULENZA ORIENTATIVA (CARCERE)", IF(AND(exp_SILP!$S8="A.4 CONSULENZA ORIENTATIVA",exp_SILP!$AD8="."),"A.4 CONSULENZA ORIENTATIVA (CARCERE)", IF(AND(exp_SILP!$S8="A.5 - LEP F1 - ACCOMPAGNAMENTO AL LAVORO",exp_SILP!$AD8="4.2"),"A.5 - LEP F1 - ACCOMPAGNAMENTO AL LAVORO (CARCERE)", IF(AND(exp_SILP!$S8="A.5 - LEP F1 - ACCOMPAGNAMENTO AL LAVORO",exp_SILP!$AD8="."),"A.5 - LEP F1 - ACCOMPAGNAMENTO AL LAVORO (CARCERE)", IF(AND(exp_SILP!$S8="A.5.2a - TUTORAGGIO TIROCINI",exp_SILP!$AD8="4.2"),"A.5.2a - TUTORAGGIO TIROCINI (CARCERE)", exp_SILP!$S8))))))) -> A.4 CONSULENZA ORIENTATIVA (1-C) | C8: =CONCATENATE(VLOOKUP(exp_SILP!$B8,'DATI COMMESSE'!$A$2:$F$25,4,FALSE)," - ", VLOOKUP(exp_SILP!$B8,'DATI COMMESSE'!$A$2:$F$25,2,FALSE)," - ",VLOOKUP(exp_SILP!$B8,'DATI COMMESSE'!$A$2:$F$25,3,FALSE)) -> FRD - 22-02-5000 - 22-12-5002 | D8: =LEFT(exp_SILP!$R8,5) -> 14:00 | E8: =RIGHT(exp_SILP!$R8,5) -> 17:00 | F8: =IF(exp_SILP!$AG8>=60,exp_SILP!$AG8/60,exp_SILP!$AG8) -> 3 | G8: =VLOOKUP(exp_SILP!$Y8,'DATI CM'!$A$2:$F$28,2,FALSE) -> FLCSRN79S42L219X | H8: =VLOOKUP(exp_SILP!$Y8,'DATI CM'!$A$2:$F$28,3,FALSE) -> A011 | I8: =IF(A8>0,"N","N") -> N | J8: =VLOOKUP(exp_SILP!$Y8,'DATI CM'!$A$2:$F$28,4,FALSE) -> TORINO | K8: =VLOOKUP(exp_SILP!$B8,'DATI COMMESSE'!$A$2:$F$25,5,FALSE) -> 35.5 | L8: =IF(exp_SILP!$B8="A4.10 - LEP E - ORIENTAMENTO SPECIALISTICO SKILL GAP ANALYSIS - GRUPPO 3P",0,VLOOKUP(exp_SILP!$Y8,'DATI CM'!$A$2:$F$28,6,FALSE)) -> 25 | M8: =IFERROR(VLOOKUP(exp_SILP!$B8,'DATI CM'!$H$2:$I$16,2,FALSE)*exp_SILP!$F8,0) -> 0 | N8: =VLOOKUP(exp_SILP!$B8,'DATI COMMESSE'!$A$2:$F$25,4,FALSE) -> FRD | O8: =VLOOKUP(exp_SILP!$B8,'DATI COMMESSE'!$A$2:$F$25,5,FALSE)*exp_SILP!$F8 -> 106.5 | P8: =IF(MID(exp_SILP!$W8,10,2)>"40","F","M") -> M | Q8: 01/03/2023 | R8: 14:00-17:00 | S8: A.4 CONSULENZA ORIENTATIVA (1-C) | T8: Progetti per accreditati | V8: MATEI GHEORGHE | W8: MTAGRG64C06Z129P | X8: 06/03/1964 | Y8: FALCONE SERENA | Z8: Erogato | AA8: INFORCOOP ECIPA PIEMONTE | AB8: Incontro MDLpresentato | AC8: INFORCOOP ECIPA PIEMONTE VIA LIVORNO 53/b - TORINO | AG8: 180 | AH8: 03/03/2023 | AI8: FLCSRN79S42L219X | AJ8: =VLOOKUP(exp_SILP!$Y8,'DATI CM'!$A$2:$F$28,2,FALSE) -> FLCSRN79S42L219X
A9: =IFERROR(VLOOKUP(exp_SILP!$W9,exp_utenti_P!D:D,1,FALSE),"_DA INSERIRE") -> BRTJNY00R63L219O | B9: =IF(AND(exp_SILP!$S9="A.3 ORIENTAMENTO PROFESSIONALE",exp_SILP!$AD9="4.2"),"A.3 ORIENTAMENTO PROFESSIONALE (CARCERE)", IF(AND(exp_SILP!$S9="A.3 ORIENTAMENTO PROFESSIONALE",exp_SILP!$AD9="."),"A.3 ORIENTAMENTO PROFESSIONALE (CARCERE)", IF(AND(exp_SILP!$S9="A.4 CONSULENZA ORIENTATIVA",exp_SILP!$AD9="4.2"),"A.4 CONSULENZA ORIENTATIVA (CARCERE)", IF(AND(exp_SILP!$S9="A.4 CONSULENZA ORIENTATIVA",exp_SILP!$AD9="."),"A.4 CONSULENZA ORIENTATIVA (CARCERE)", IF(AND(exp_SILP!$S9="A.5 - LEP F1 - ACCOMPAGNAMENTO AL LAVORO",exp_SILP!$AD9="4.2"),"A.5 - LEP F1 - ACCOMPAGNAMENTO AL LAVORO (CARCERE)", IF(AND(exp_SILP!$S9="A.5 - LEP F1 - ACCOMPAGNAMENTO AL LAVORO",exp_SILP!$AD9="."),"A.5 - LEP F1 - ACCOMPAGNAMENTO AL LAVORO (CARCERE)", IF(AND(exp_SILP!$S9="A.5.2a - TUTORAGGIO TIROCINI",exp_SILP!$AD9="4.2"),"A.5.2a - TUTORAGGIO TIROCINI (CARCERE)", exp_SILP!$S9))))))) -> A.4 CONSULENZA ORIENTATIVA (1-C) | C9: =CONCATENATE(VLOOKUP(exp_SILP!$B9,'DATI COMMESSE'!$A$2:$F$25,4,FALSE)," - ", VLOOKUP(exp_SILP!$B9,'DATI COMMESSE'!$A$2:$F$25,2,FALSE)," - ",VLOOKUP(exp_SILP!$B9,'DATI COMMESSE'!$A$2:$F$25,3,FALSE)) -> FRD - 22-02-5000 - 22-12-5002 | D9: =LEFT(exp_SILP!$R9,5) -> 12:00 | E9: =RIGHT(exp_SILP!$R9,5) -> 13:00 | F9: =IF(exp_SILP!$AG9>=60,exp_SILP!$AG9/60,exp_SILP!$AG9) -> 1 | G9: =VLOOKUP(exp_SILP!$Y9,'DATI CM'!$A$2:$F$28,2,FALSE) -> FLCSRN79S42L219X | H9: =VLOOKUP(exp_SILP!$Y9,'DATI CM'!$A$2:$F$28,3,FALSE) -> A011 | I9: =IF(A9>0,"N","N") -> N | J9: =VLOOKUP(exp_SILP!$Y9,'DATI CM'!$A$2:$F$28,4,FALSE) -> TORINO | K9: =VLOOKUP(exp_SILP!$B9,'DATI COMMESSE'!$A$2:$F$25,5,FALSE) -> 35.5 | L9: =IF(exp_SILP!$B9="A4.10 - LEP E - ORIENTAMENTO SPECIALISTICO SKILL GAP ANALYSIS - GRUPPO 3P",0,VLOOKUP(exp_SILP!$Y9,'DATI CM'!$A$2:$F$28,6,FALSE)) -> 25 | M9: =IFERROR(VLOOKUP(exp_SILP!$B9,'DATI CM'!$H$2:$I$16,2,FALSE)*exp_SILP!$F9,0) -> 0 | N9: =VLOOKUP(exp_SILP!$B9,'DATI COMMESSE'!$A$2:$F$25,4,FALSE) -> FRD | O9: =VLOOKUP(exp_SILP!$B9,'DATI COMMESSE'!$A$2:$F$25,5,FALSE)*exp_SILP!$F9 -> 35.5 | P9: =IF(MID(exp_SILP!$W9,10,2)>"40","F","M") -> F | Q9: 01/03/2023 | R9: 12:00-13:00 | S9: A.4 CONSULENZA ORIENTATIVA (1-C) | T9: Progetti per accreditati | V9: BERTAGGIA JENNY | W9: BRTJNY00R63L219O | X9: 23/10/2000 | Y9: FALCONE SERENA | Z9: Erogato | AA9: INFORCOOP ECIPA PIEMONTE | AB9: Incontro MDLpresentato | AC9: INFORCOOP ECIPA PIEMONTE VIA LIVORNO 53/b - TORINO | AG9: 60 | AH9: 01/03/2023 | AI9: FLCSRN79S42L219X | AJ9: =VLOOKUP(exp_SILP!$Y9,'DATI CM'!$A$2:$F$28,2,FALSE) -> FLCSRN79S42L219X
A10: =IFERROR(VLOOKUP(exp_SILP!$W10,exp_utenti_P!D:D,1,FALSE),"_DA INSERIRE") -> STRGRY71L08C627Y | B10: =IF(AND(exp_SILP!$S10="A.3 ORIENTAMENTO PROFESSIONALE",exp_SILP!$AD10="4.2"),"A.3 ORIENTAMENTO PROFESSIONALE (CARCERE)", IF(AND(exp_SILP!$S10="A.3 ORIENTAMENTO PROFESSIONALE",exp_SILP!$AD10="."),"A.3 ORIENTAMENTO PROFESSIONALE (CARCERE)", IF(AND(exp_SILP!$S10="A.4 CONSULENZA ORIENTATIVA",exp_SILP!$AD10="4.2"),"A.4 CONSULENZA ORIENTATIVA (CARCERE)", IF(AND(exp_SILP!$S10="A.4 CONSULENZA ORIENTATIVA",exp_SILP!$AD10="."),"A.4 CONSULENZA ORIENTATIVA (CARCERE)", IF(AND(exp_SILP!$S10="A.5 - LEP F1 - ACCOMPAGNAMENTO AL LAVORO",exp_SILP!$AD10="4.2"),"A.5 - LEP F1 - ACCOMPAGNAMENTO AL LAVORO (CARCERE)", IF(AND(exp_SILP!$S10="A.5 - LEP F1 - ACCOMPAGNAMENTO AL LAVORO",exp_SILP!$AD10="."),"A.5 - LEP F1 - ACCOMPAGNAMENTO AL LAVORO (CARCERE)", IF(AND(exp_SILP!$S10="A.5.2a - TUTORAGGIO TIROCINI",exp_SILP!$AD10="4.2"),"A.5.2a - TUTORAGGIO TIROCINI (CARCERE)", exp_SILP!$S10))))))) -> A4.10 - LEP E - ORIENTAMENTO SPECIALISTICO SKILL GAP ANALYSIS | C10: =CONCATENATE(VLOOKUP(exp_SILP!$B10,'DATI COMMESSE'!$A$2:$F$25,4,FALSE)," - ", VLOOKUP(exp_SILP!$B10,'DATI COMMESSE'!$A$2:$F$25,2,FALSE)," - ",VLOOKUP(exp_SILP!$B10,'DATI COMMESSE'!$A$2:$F$25,3,FALSE)) -> GOL - 22-02-5000 - 22-12-5003 | D10: =LEFT(exp_SILP!$R10,5) -> 09:00 | E10: =RIGHT(exp_SILP!$R10,5) -> 12:00 | F10: =IF(exp_SILP!$AG10>=60,exp_SILP!$AG10/60,exp_SILP!$AG10) -> 3 | G10: =VLOOKUP(exp_SILP!$Y10,'DATI CM'!$A$2:$F$28,2,FALSE) -> FLCSRN79S42L219X | H10: =VLOOKUP(exp_SILP!$Y10,'DATI CM'!$A$2:$F$28,3,FALSE) -> A011 | I10: =IF(A10>0,"N","N") -> N | J10: =VLOOKUP(exp_SILP!$Y10,'DATI CM'!$A$2:$F$28,4,FALSE) -> TORINO | K10: =VLOOKUP(exp_SILP!$B10,'DATI COMMESSE'!$A$2:$F$25,5,FALSE) -> 39.94 | L10: =IF(exp_SILP!$B10="A4.10 - LEP E - ORIENTAMENTO SPECIALISTICO SKILL GAP ANALYSIS - GRUPPO 3P",0,VLOOKUP(exp_SILP!$Y10,'DATI CM'!$A$2:$F$28,6,FALSE)) -> 25 | M10: =IFERROR(VLOOKUP(exp_SILP!$B10,'DATI CM'!$H$2:$I$16,2,FALSE)*exp_SILP!$F10,0) -> 0 | N10: =VLOOKUP(exp_SILP!$B10,'DATI COMMESSE'!$A$2:$F$25,4,FALSE) -> GOL | O10: =VLOOKUP(exp_SILP!$B10,'DATI COMMESSE'!$A$2:$F$25,5,FALSE)*exp_SILP!$F10 -> 119.82 | P10: =IF(MID(exp_SILP!$W10,10,2)>"40","F","M") -> M | Q10: 01/03/2023 | R10: 09:00-12:00 | S10: A4.10 - LEP E - ORIENTAMENTO SPECIALISTICO SKILL GAP ANALYSIS | T10: Progetti per accreditati | V10: STRIANO GERRY | W10: STRGRY71L08C627Y | X10: 08/07/1971 | Y10: FALCONE SERENA | Z10: Erogato | AA10: INFORCOOP ECIPA PIEMONTE | AB10: Incontro MDLpresentato | AC10: INFORCOOP ECIPA PIEMONTE VIA LIVORNO 53/b - TORINO | AG10: 180 | AH10: 01/03/2023 | AI10: FLCSRN79S42L219X | AJ10: =VLOOKUP(exp_SILP!$Y10,'DATI CM'!$A$2:$F$28,2,FALSE) -> FLCSRN79S42L219X
A11: =IFERROR(VLOOKUP(exp_SILP!$W11,exp_utenti_P!D:D,1,FALSE),"_DA INSERIRE") -> DMAGPP68A02C352O | B11: =IF(AND(exp_SILP!$S11="A.3 ORIENTAMENTO PROFESSIONALE",exp_SILP!$AD11="4.2"),"A.3 ORIENTAMENTO PROFESSIONALE (CARCERE)", IF(AND(exp_SILP!$S11="A.3 ORIENTAMENTO PROFESSIONALE",exp_SILP!$AD11="."),"A.3 ORIENTAMENTO PROFESSIONALE (CARCERE)", IF(AND(exp_SILP!$S11="A.4 CONSULENZA ORIENTATIVA",exp_SILP!$AD11="4.2"),"A.4 CONSULENZA ORIENTATIVA (CARCERE)", IF(AND(exp_SILP!$S11="A.4 CONSULENZA ORIENTATIVA",exp_SILP!$AD11="."),"A.4 CONSULENZA ORIENTATIVA (CARCERE)", IF(AND(exp_SILP!$S11="A.5 - LEP F1 - ACCOMPAGNAMENTO AL LAVORO",exp_SILP!$AD11="4.2"),"A.5 - LEP F1 - ACCOMPAGNAMENTO AL LAVORO (CARCERE)", IF(AND(exp_SILP!$S11="A.5 - LEP F1 - ACCOMPAGNAMENTO AL LAVORO",exp_SILP!$AD11="."),"A.5 - LEP F1 - ACCOMPAGNAMENTO AL LAVORO (CARCERE)", IF(AND(exp_SILP!$S11="A.5.2a - TUTORAGGIO TIROCINI",exp_SILP!$AD11="4.2"),"A.5.2a - TUTORAGGIO TIROCINI (CARCERE)", exp_SILP!$S11))))))) -> A4.10 - LEP E - ORIENTAMENTO SPECIALISTICO SKILL GAP ANALYSIS | C11: =CONCATENATE(VLOOKUP(exp_SILP!$B11,'DATI COMMESSE'!$A$2:$F$25,4,FALSE)," - ", VLOOKUP(exp_SILP!$B11,'DATI COMMESSE'!$A$2:$F$25,2,FALSE)," - ",VLOOKUP(exp_SILP!$B11,'DATI COMMESSE'!$A$2:$F$25,3,FALSE)) -> GOL - 22-02-5000 - 22-12-5003 | D11: =LEFT(exp_SILP!$R11,5) -> 16:30 | E11: =RIGHT(exp_SILP!$R11,5) -> 17:30 | F11: =IF(exp_SILP!$AG11>=60,exp_SILP!$AG11/60,exp_SILP!$AG11) -> 1 | G11: =VLOOKUP(exp_SILP!$Y11,'DATI CM'!$A$2:$F$28,2,FALSE) -> TRZCST69B41F952V | H11: =VLOOKUP(exp_SILP!$Y11,'DATI CM'!$A$2:$F$28,3,FALSE) | I11: =IF(A11>0,"N","N") -> N | J11: =VLOOKUP(exp_SILP!$Y11,'DATI CM'!$A$2:$F$28,4,FALSE) | K11: =VLOOKUP(exp_SILP!$B11,'DATI COMMESSE'!$A$2:$F$25,5,FALSE) -> 39.94 | L11: =IF(exp_SILP!$B11="A4.10 - LEP E - ORIENTAMENTO SPECIALISTICO SKILL GAP ANALYSIS - GRUPPO 3P",0,VLOOKUP(exp_SILP!$Y11,'DATI CM'!$A$2:$F$28,6,FALSE)) | M11: =IFERROR(VLOOKUP(exp_SILP!$B11,'DATI CM'!$H$2:$I$16,2,FALSE)*exp_SILP!$F11,0) -> 0 | N11: =VLOOKUP(exp_SILP!$B11,'DATI COMMESSE'!$A$2:$F$25,4,FALSE) -> GOL | O11: =VLOOKUP(exp_SILP!$B11,'DATI COMMESSE'!$A$2:$F$25,5,FALSE)*exp_SILP!$F11 -> 39.94 | P11: =IF(MID(exp_SILP!$W11,10,2)>"40","F","M") -> M | Q11: 01/03/2023 | R11: 16:30-17:30 | S11: A4.10 - LEP E - ORIENTAMENTO SPECIALISTICO SKILL GAP ANALYSIS | T11: Progetti per accreditati | V11: ADAMO GIUSEPPE | W11: DMAGPP68A02C352O | X11: 02/01/1968 | Y11: TERZERA CRISTINA | Z11: Erogato | AA11: INFORCOOP ECIPA PIEMONTE | AB11: Incontro MDL | AC11: INFORCOOP ECIPA PIEMONTE VIA UGO PORZIO GIOVANOLA 7 - NOVARA | AF11: BACK OFFICE | AG11: 60 | AH11: 20/04/2023 | AI11: TRZCST69B41F952V | AJ11: =VLOOKUP(exp_SILP!$Y11,'DATI CM'!$A$2:$F$28,2,FALSE) -> TRZCST69B41F952V
A12: =IFERROR(VLOOKUP(exp_SILP!$W12,exp_utenti_P!D:D,1,FALSE),"_DA INSERIRE") -> RSSMSM71T04A010O | B12: =IF(AND(exp_SILP!$S12="A.3 ORIENTAMENTO PROFESSIONALE",exp_SILP!$AD12="4.2"),"A.3 ORIENTAMENTO PROFESSIONALE (CARCERE)", IF(AND(exp_SILP!$S12="A.3 ORIENTAMENTO PROFESSIONALE",exp_SILP!$AD12="."),"A.3 ORIENTAMENTO PROFESSIONALE (CARCERE)", IF(AND(exp_SILP!$S12="A.4 CONSULENZA ORIENTATIVA",exp_SILP!$AD12="4.2"),"A.4 CONSULENZA ORIENTATIVA (CARCERE)", IF(AND(exp_SILP!$S12="A.4 CONSULENZA ORIENTATIVA",exp_SILP!$AD12="."),"A.4 CONSULENZA ORIENTATIVA (CARCERE)", IF(AND(exp_SILP!$S12="A.5 - LEP F1 - ACCOMPAGNAMENTO AL LAVORO",exp_SILP!$AD12="4.2"),"A.5 - LEP F1 - ACCOMPAGNAMENTO AL LAVORO (CARCERE)", IF(AND(exp_SILP!$S12="A.5 - LEP F1 - ACCOMPAGNAMENTO AL LAVORO",exp_SILP!$AD12="."),"A.5 - LEP F1 - ACCOMPAGNAMENTO AL LAVORO (CARCERE)", IF(AND(exp_SILP!$S12="A.5.2a - TUTORAGGIO TIROCINI",exp_SILP!$AD12="4.2"),"A.5.2a - TUTORAGGIO TIROCINI (CARCERE)", exp_SILP!$S12))))))) -> A4.10 - LEP E - ORIENTAMENTO SPECIALISTICO SKILL GAP ANALYSIS | C12: =CONCATENATE(VLOOKUP(exp_SILP!$B12,'DATI COMMESSE'!$A$2:$F$25,4,FALSE)," - ", VLOOKUP(exp_SILP!$B12,'DATI COMMESSE'!$A$2:$F$25,2,FALSE)," - ",VLOOKUP(exp_SILP!$B12,'DATI COMMESSE'!$A$2:$F$25,3,FALSE)) -> GOL - 22-02-5000 - 22-12-5003 | D12: =LEFT(exp_SILP!$R12,5) -> 15:30 | E12: =RIGHT(exp_SILP!$R12,5) -> 16:30 | F12: =IF(exp_SILP!$AG12>=60,exp_SILP!$AG12/60,exp_SILP!$AG12) -> 1 | G12: =VLOOKUP(exp_SILP!$Y12,'DATI CM'!$A$2:$F$28,2,FALSE) -> TRZCST69B41F952V | H12: =VLOOKUP(exp_SILP!$Y12,'DATI CM'!$A$2:$F$28,3,FALSE) | I12: =IF(A12>0,"N","N") -> N | J12: =VLOOKUP(exp_SILP!$Y12,'DATI CM'!$A$2:$F$28,4,FALSE) | K12: =VLOOKUP(exp_SILP!$B12,'DATI COMMESSE'!$A$2:$F$25,5,FALSE) -> 39.94 | L12: =IF(exp_SILP!$B12="A4.10 - LEP E - ORIENTAMENTO SPECIALISTICO SKILL GAP ANALYSIS - GRUPPO 3P",0,VLOOKUP(exp_SILP!$Y12,'DATI CM'!$A$2:$F$28,6,FALSE)) | M12: =IFERROR(VLOOKUP(exp_SILP!$B12,'DATI CM'!$H$2:$I$16,2,FALSE)*exp_SILP!$F12,0) -> 0 | N12: =VLOOKUP(exp_SILP!$B12,'DATI COMMESSE'!$A$2:$F$25,4,FALSE) -> GOL | O12: =VLOOKUP(exp_SILP!$B12,'DATI COMMESSE'!$A$2:$F$25,5,FALSE)*exp_SILP!$F12 -> 39.94 | P12: =IF(MID(exp_SILP!$W12,10,2)>"40","F","M") -> M | Q12: 01/03/2023 | R12: 15:30-16:30 | S12: A4.10 - LEP E - ORIENTAMENTO SPECIALISTICO SKILL GAP ANALYSIS | T12: Progetti per accreditati | V12: RUSSO MASSIMO | W12: RSSMSM71T04A010O | X12: 04/12/1971 | Y12: TERZERA CRISTINA | Z12: Erogato | AA12: INFORCOOP ECIPA PIEMONTE | AB12: Incontro MDL | AC12: INFORCOOP ECIPA PIEMONTE VIA UGO PORZIO GIOVANOLA 7 - NOVARA | AG12: 60 | AH12: 10/03/2023 | AI12: TRZCST69B41F952V | AJ12: =VLOOKUP(exp_SILP!$Y12,'DATI CM'!$A$2:$F$28,2,FALSE) -> TRZCST69B41F952V
A13: =IFERROR(VLOOKUP(exp_SILP!$W13,exp_utenti_P!D:D,1,FALSE),"_DA INSERIRE") -> CLNNLS04L23F952V | B13: =IF(AND(exp_SILP!$S13="A.3 ORIENTAMENTO PROFESSIONALE",exp_SILP!$AD13="4.2"),"A.3 ORIENTAMENTO PROFESSIONALE (CARCERE)", IF(AND(exp_SILP!$S13="A.3 ORIENTAMENTO PROFESSIONALE",exp_SILP!$AD13="."),"A.3 ORIENTAMENTO PROFESSIONALE (CARCERE)", IF(AND(exp_SILP!$S13="A.4 CONSULENZA ORIENTATIVA",exp_SILP!$AD13="4.2"),"A.4 CONSULENZA ORIENTATIVA (CARCERE)", IF(AND(exp_SILP!$S13="A.4 CONSULENZA ORIENTATIVA",exp_SILP!$AD13="."),"A.4 CONSULENZA ORIENTATIVA (CARCERE)", IF(AND(exp_SILP!$S13="A.5 - LEP F1 - ACCOMPAGNAMENTO AL LAVORO",exp_SILP!$AD13="4.2"),"A.5 - LEP F1 - ACCOMPAGNAMENTO AL LAVORO (CARCERE)", IF(AND(exp_SILP!$S13="A.5 - LEP F1 - ACCOMPAGNAMENTO AL LAVORO",exp_SILP!$AD13="."),"A.5 - LEP F1 - ACCOMPAGNAMENTO AL LAVORO (CARCERE)", IF(AND(exp_SILP!$S13="A.5.2a - TUTORAGGIO TIROCINI",exp_SILP!$AD13="4.2"),"A.5.2a - TUTORAGGIO TIROCINI (CARCERE)", exp_SILP!$S13))))))) -> A4.10 - LEP E - ORIENTAMENTO SPECIALISTICO SKILL GAP ANALYSIS | C13: =CONCATENATE(VLOOKUP(exp_SILP!$B13,'DATI COMMESSE'!$A$2:$F$25,4,FALSE)," - ", VLOOKUP(exp_SILP!$B13,'DATI COMMESSE'!$A$2:$F$25,2,FALSE)," - ",VLOOKUP(exp_SILP!$B13,'DATI COMMESSE'!$A$2:$F$25,3,FALSE)) -> GOL - 22-02-5000 - 22-12-5003 | D13: =LEFT(exp_SILP!$R13,5) -> 14:30 | E13: =RIGHT(exp_SILP!$R13,5) -> 15:30 | F13: =IF(exp_SILP!$AG13>=60,exp_SILP!$AG13/60,exp_SILP!$AG13) -> 1 | G13: =VLOOKUP(exp_SILP!$Y13,'DATI CM'!$A$2:$F$28,2,FALSE) -> TRZCST69B41F952V | H13: =VLOOKUP(exp_SILP!$Y13,'DATI CM'!$A$2:$F$28,3,FALSE) | I13: =IF(A13>0,"N","N") -> N | J13: =VLOOKUP(exp_SILP!$Y13,'DATI CM'!$A$2:$F$28,4,FALSE) | K13: =VLOOKUP(exp_SILP!$B13,'DATI COMMESSE'!$A$2:$F$25,5,FALSE) -> 39.94 | L13: =IF(exp_SILP!$B13="A4.10 - LEP E - ORIENTAMENTO SPECIALISTICO SKILL GAP ANALYSIS - GRUPPO 3P",0,VLOOKUP(exp_SILP!$Y13,'DATI CM'!$A$2:$F$28,6,FALSE)) | M13: =IFERROR(VLOOKUP(exp_SILP!$B13,'DATI CM'!$H$2:$I$16,2,FALSE)*exp_SILP!$F13,0) -> 0 | N13: =VLOOKUP(exp_SILP!$B13,'DATI COMMESSE'!$A$2:$F$25,4,FALSE) -> GOL | O13: =VLOOKUP(exp_SILP!$B13,'DATI COMMESSE'!$A$2:$F$25,5,FALSE)*exp_SILP!$F13 -> 39.94 | P13: =IF(MID(exp_SILP!$W13,10,2)>"40","F","M") -> M | Q13: 01/03/2023 | R13: 14:30-15:30 | S13: A4.10 - LEP E - ORIENTAMENTO SPECIALISTICO SKILL GAP ANALYSIS | T13: Progetti per accreditati | V13: COLONNA NICOLAS | W13: CLNNLS04L23F952V | X13: 23/07/2004 | Y13: TERZERA CRISTINA | Z13: Erogato | AA13: INFORCOOP ECIPA PIEMONTE | AB13: Incontro MDL | AC13: INFORCOOP ECIPA PIEMONTE VIA UGO PORZIO GIOVANOLA 7 - NOVARA | AG13: 60 | AH13: 07/03/2023 | AI13: TRZCST69B41F952V | AJ13: =VLOOKUP(exp_SILP!$Y13,'DATI CM'!$A$2:$F$28,2,FALSE) -> TRZCST69B41F952V
A14: =IFERROR(VLOOKUP(exp_SILP!$W14,exp_utenti_P!D:D,1,FALSE),"_DA INSERIRE") -> CLNNLS04L23F952V | B14: =IF(AND(exp_SILP!$S14="A.3 ORIENTAMENTO PROFESSIONALE",exp_SILP!$AD14="4.2"),"A.3 ORIENTAMENTO PROFESSIONALE (CARCERE)", IF(AND(exp_SILP!$S14="A.3 ORIENTAMENTO PROFESSIONALE",exp_SILP!$AD14="."),"A.3 ORIENTAMENTO PROFESSIONALE (CARCERE)", IF(AND(exp_SILP!$S14="A.4 CONSULENZA ORIENTATIVA",exp_SILP!$AD14="4.2"),"A.4 CONSULENZA ORIENTATIVA (CARCERE)", IF(AND(exp_SILP!$S14="A.4 CONSULENZA ORIENTATIVA",exp_SILP!$AD14="."),"A.4 CONSULENZA ORIENTATIVA (CARCERE)", IF(AND(exp_SILP!$S14="A.5 - LEP F1 - ACCOMPAGNAMENTO AL LAVORO",exp_SILP!$AD14="4.2"),"A.5 - LEP F1 - ACCOMPAGNAMENTO AL LAVORO (CARCERE)", IF(AND(exp_SILP!$S14="A.5 - LEP F1 - ACCOMPAGNAMENTO AL LAVORO",exp_SILP!$AD14="."),"A.5 - LEP F1 - ACCOMPAGNAMENTO AL LAVORO (CARCERE)", IF(AND(exp_SILP!$S14="A.5.2a - TUTORAGGIO TIROCINI",exp_SILP!$AD14="4.2"),"A.5.2a - TUTORAGGIO TIROCINI (CARCERE)", exp_SILP!$S14))))))) -> A4.10 - LEP E - ORIENTAMENTO SPECIALISTICO SKILL GAP ANALYSIS | C14: =CONCATENATE(VLOOKUP(exp_SILP!$B14,'DATI COMMESSE'!$A$2:$F$25,4,FALSE)," - ", VLOOKUP(exp_SILP!$B14,'DATI COMMESSE'!$A$2:$F$25,2,FALSE)," - ",VLOOKUP(exp_SILP!$B14,'DATI COMMESSE'!$A$2:$F$25,3,FALSE)) -> GOL - 22-02-5000 - 22-12-5003 | D14: =LEFT(exp_SILP!$R14,5) -> 09:30 | E14: =RIGHT(exp_SILP!$R14,5) -> 12:30 | F14: =IF(exp_SILP!$AG14>=60,exp_SILP!$AG14/60,exp_SILP!$AG14) -> 3 | G14: =VLOOKUP(exp_SILP!$Y14,'DATI CM'!$A$2:$F$28,2,FALSE) -> TRZCST69B41F952V | H14: =VLOOKUP(exp_SILP!$Y14,'DATI CM'!$A$2:$F$28,3,FALSE) | I14: =IF(A14>0,"N","N") -> N | J14: =VLOOKUP(exp_SILP!$Y14,'DATI CM'!$A$2:$F$28,4,FALSE) | K14: =VLOOKUP(exp_SILP!$B14,'DATI COMMESSE'!$A$2:$F$25,5,FALSE) -> 39.94 | L14: =IF(exp_SILP!$B14="A4.10 - LEP E - ORIENTAMENTO SPECIALISTICO SKILL GAP ANALYSIS - GRUPPO 3P",0,VLOOKUP(exp_SILP!$Y14,'DATI CM'!$A$2:$F$28,6,FALSE)) | M14: =IFERROR(VLOOKUP(exp_SILP!$B14,'DATI CM'!$H$2:$I$16,2,FALSE)*exp_SILP!$F14,0) -> 0 | N14: =VLOOKUP(exp_SILP!$B14,'DATI COMMESSE'!$A$2:$F$25,4,FALSE) -> GOL | O14: =VLOOKUP(exp_SILP!$B14,'DATI COMMESSE'!$A$2:$F$25,5,FALSE)*exp_SILP!$F14 -> 119.82 | P14: =IF(MID(exp_SILP!$W14,10,2)>"40","F","M") -> M | Q14: 01/03/2023 | R14: 09:30-12:30 | S14: A4.10 - LEP E - ORIENTAMENTO SPECIALISTICO SKILL GAP ANALYSIS | T14: Progetti per accreditati | V14: COLONNA NICOLAS | W14: CLNNLS04L23F952V | X14: 23/07/2004 | Y14: TERZERA CRISTINA | Z14: Erogato | AA14: INFORCOOP ECIPA PIEMONTE | AB14: Incontro MDL | AC14: INFORCOOP ECIPA PIEMONTE VIA UGO PORZIO GIOVANOLA 7 - NOVARA | AG14: 180 | AH14: 01/03/2023 | AI14: TRZCST69B41F952V | AJ14: =VLOOKUP(exp_SILP!$Y14,'DATI CM'!$A$2:$F$28,2,FALSE) -> TRZCST69B41F952V
A15: =IFERROR(VLOOKUP(exp_SILP!$W15,exp_utenti_P!D:D,1,FALSE),"_DA INSERIRE") -> LEIGLC70M01F952G | B15: =IF(AND(exp_SILP!$S15="A.3 ORIENTAMENTO PROFESSIONALE",exp_SILP!$AD15="4.2"),"A.3 ORIENTAMENTO PROFESSIONALE (CARCERE)", IF(AND(exp_SILP!$S15="A.3 ORIENTAMENTO PROFESSIONALE",exp_SILP!$AD15="."),"A.3 ORIENTAMENTO PROFESSIONALE (CARCERE)", IF(AND(exp_SILP!$S15="A.4 CONSULENZA ORIENTATIVA",exp_SILP!$AD15="4.2"),"A.4 CONSULENZA ORIENTATIVA (CARCERE)", IF(AND(exp_SILP!$S15="A.4 CONSULENZA ORIENTATIVA",exp_SILP!$AD15="."),"A.4 CONSULENZA ORIENTATIVA (CARCERE)", IF(AND(exp_SILP!$S15="A.5 - LEP F1 - ACCOMPAGNAMENTO AL LAVORO",exp_SILP!$AD15="4.2"),"A.5 - LEP F1 - ACCOMPAGNAMENTO AL LAVORO (CARCERE)", IF(AND(exp_SILP!$S15="A.5 - LEP F1 - ACCOMPAGNAMENTO AL LAVORO",exp_SILP!$AD15="."),"A.5 - LEP F1 - ACCOMPAGNAMENTO AL LAVORO (CARCERE)", IF(AND(exp_SILP!$S15="A.5.2a - TUTORAGGIO TIROCINI",exp_SILP!$AD15="4.2"),"A.5.2a - TUTORAGGIO TIROCINI (CARCERE)", exp_SILP!$S15))))))) -> A4.10 - LEP E - ORIENTAMENTO SPECIALISTICO SKILL GAP ANALYSIS | C15: =CONCATENATE(VLOOKUP(exp_SILP!$B15,'DATI COMMESSE'!$A$2:$F$25,4,FALSE)," - ", VLOOKUP(exp_SILP!$B15,'DATI COMMESSE'!$A$2:$F$25,2,FALSE)," - ",VLOOKUP(exp_SILP!$B15,'DATI COMMESSE'!$A$2:$F$25,3,FALSE)) -> GOL - 22-02-5000 - 22-12-5003 | D15: =LEFT(exp_SILP!$R15,5) -> 12:30 | E15: =RIGHT(exp_SILP!$R15,5) -> 14:30 | F15: =IF(exp_SILP!$AG15>=60,exp_SILP!$AG15/60,exp_SILP!$AG15) -> 2 | G15: =VLOOKUP(exp_SILP!$Y15,'DATI CM'!$A$2:$F$28,2,FALSE) -> TRZCST69B41F952V | H15: =VLOOKUP(exp_SILP!$Y15,'DATI CM'!$A$2:$F$28,3,FALSE) | I15: =IF(A15>0,"N","N") -> N | J15: =VLOOKUP(exp_SILP!$Y15,'DATI CM'!$A$2:$F$28,4,FALSE) | K15: =VLOOKUP(exp_SILP!$B15,'DATI COMMESSE'!$A$2:$F$25,5,FALSE) -> 39.94 | L15: =IF(exp_SILP!$B15="A4.10 - LEP E - ORIENTAMENTO SPECIALISTICO SKILL GAP ANALYSIS - GRUPPO 3P",0,VLOOKUP(exp_SILP!$Y15,'DATI CM'!$A$2:$F$28,6,FALSE)) | M15: =IFERROR(VLOOKUP(exp_SILP!$B15,'DATI CM'!$H$2:$I$16,2,FALSE)*exp_SILP!$F15,0) -> 0 | N15: =VLOOKUP(exp_SILP!$B15,'DATI COMMESSE'!$A$2:$F$25,4,FALSE) -> GOL | O15: =VLOOKUP(exp_SILP!$B15,'DATI COMMESSE'!$A$2:$F$25,5,FALSE)*exp_SILP!$F15 -> 79.88 | P15: =IF(MID(exp_SILP!$W15,10,2)>"40","F","M") -> M | Q15: 01/03/2023 | R15: 12:30-14:30 | S15: A4.10 - LEP E - ORIENTAMENTO SPECIALISTICO SKILL GAP ANALYSIS | T15: Progetti per accreditati | V15: ELIA GIANLUCA | W15: LEIGLC70M01F952G | X15: 01/08/1970 | Y15: TERZERA CRISTINA | Z15: Erogato | AA15: INFORCOOP ECIPA PIEMONTE | AB15: Incontro MDL | AC15: INFORCOOP ECIPA PIEMONTE VIA UGO PORZIO GIOVANOLA 7 - NOVARA | AG15: 120 | AH15: 01/03/2023 | AI15: TRZCST69B41F952V | AJ15: =VLOOKUP(exp_SILP!$Y15,'DATI CM'!$A$2:$F$28,2,FALSE) -> TRZCST69B41F952V
A16: =IFERROR(VLOOKUP(exp_SILP!$W16,exp_utenti_P!D:D,1,FALSE),"_DA INSERIRE") -> SDRMLA83A50Z330A | B16: =IF(AND(exp_SILP!$S16="A.3 ORIENTAMENTO PROFESSIONALE",exp_SILP!$AD16="4.2"),"A.3 ORIENTAMENTO PROFESSIONALE (CARCERE)", IF(AND(exp_SILP!$S16="A.3 ORIENTAMENTO PROFESSIONALE",exp_SILP!$AD16="."),"A.3 ORIENTAMENTO PROFESSIONALE (CARCERE)", IF(AND(exp_SILP!$S16="A.4 CONSULENZA ORIENTATIVA",exp_SILP!$AD16="4.2"),"A.4 CONSULENZA ORIENTATIVA (CARCERE)", IF(AND(exp_SILP!$S16="A.4 CONSULENZA ORIENTATIVA",exp_SILP!$AD16="."),"A.4 CONSULENZA ORIENTATIVA (CARCERE)", IF(AND(exp_SILP!$S16="A.5 - LEP F1 - ACCOMPAGNAMENTO AL LAVORO",exp_SILP!$AD16="4.2"),"A.5 - LEP F1 - ACCOMPAGNAMENTO AL LAVORO (CARCERE)", IF(AND(exp_SILP!$S16="A.5 - LEP F1 - ACCOMPAGNAMENTO AL LAVORO",exp_SILP!$AD16="."),"A.5 - LEP F1 - ACCOMPAGNAMENTO AL LAVORO (CARCERE)", IF(AND(exp_SILP!$S16="A.5.2a - TUTORAGGIO TIROCINI",exp_SILP!$AD16="4.2"),"A.5.2a - TUTORAGGIO TIROCINI (CARCERE)", exp_SILP!$S16))))))) -> A4.10 - LEP E - ORIENTAMENTO SPECIALISTICO SKILL GAP ANALYSIS | C16: =CONCATENATE(VLOOKUP(exp_SILP!$B16,'DATI COMMESSE'!$A$2:$F$25,4,FALSE)," - ", VLOOKUP(exp_SILP!$B16,'DATI COMMESSE'!$A$2:$F$25,2,FALSE)," - ",VLOOKUP(exp_SILP!$B16,'DATI COMMESSE'!$A$2:$F$25,3,FALSE)) -> GOL - 22-02-5000 - 22-12-5003 | D16: =LEFT(exp_SILP!$R16,5) -> 14:00 | E16: =RIGHT(exp_SILP!$R16,5) -> 18:00 | F16: =IF(exp_SILP!$AG16>=60,exp_SILP!$AG16/60,exp_SILP!$AG16) -> 4 | G16: =VLOOKUP(exp_SILP!$Y16,'DATI CM'!$A$2:$F$28,2,FALSE) -> SPDPRZ67H55L219V | H16: =VLOOKUP(exp_SILP!$Y16,'DATI CM'!$A$2:$F$28,3,FALSE) -> A010 | I16: =IF(A16>0,"N","N") -> N | J16: =VLOOKUP(exp_SILP!$Y16,'DATI CM'!$A$2:$F$28,4,FALSE) -> TORINO | K16: =VLOOKUP(exp_SILP!$B16,'DATI COMMESSE'!$A$2:$F$25,5,FALSE) -> 39.94 | L16: =IF(exp_SILP!$B16="A4.10 - LEP E - ORIENTAMENTO SPECIALISTICO SKILL GAP ANALYSIS - GRUPPO 3P",0,VLOOKUP(exp_SILP!$Y16,'DATI CM'!$A$2:$F$28,6,FALSE)) | M16: =IFERROR(VLOOKUP(exp_SILP!$B16,'DATI CM'!$H$2:$I$16,2,FALSE)*exp_SILP!$F16,0) -> 0 | N16: =VLOOKUP(exp_SILP!$B16,'DATI COMMESSE'!$A$2:$F$25,4,FALSE) -> GOL | O16: =VLOOKUP(exp_SILP!$B16,'DATI COMMESSE'!$A$2:$F$25,5,FALSE)*exp_SILP!$F16 -> 159.76 | P16: =IF(MID(exp_SILP!$W16,10,2)>"40","F","M") -> F | Q16: 01/03/2023 | R16: 14:00-18:00 | S16: A4.10 - LEP E - ORIENTAMENTO SPECIALISTICO SKILL GAP ANALYSIS | T16: Progetti per accreditati | V16: SADRI AMAL | W16: SDRMLA83A50Z330A | X16: 10/01/1983 | Y16: SPADARO PATRIZIA | Z16: Erogato | AA16: INFORCOOP ECIPA PIEMONTE | AB16: Incontro MDL | AC16: INFORCOOP ECIPA PIEMONTE VIA TREVISO 12 - TORINO | AG16: 240 | AH16: 01/03/2023 | AI16: SPDPRZ67H55L219V | AJ16: =VLOOKUP(exp_SILP!$Y16,'DATI CM'!$A$2:$F$28,2,FALSE) -> SPDPRZ67H55L219V
A17: =IFERROR(VLOOKUP(exp_SILP!$W17,exp_utenti_P!D:D,1,FALSE),"_DA INSERIRE") -> BNCDLM80L07L219L | B17: =IF(AND(exp_SILP!$S17="A.3 ORIENTAMENTO PROFESSIONALE",exp_SILP!$AD17="4.2"),"A.3 ORIENTAMENTO PROFESSIONALE (CARCERE)", IF(AND(exp_SILP!$S17="A.3 ORIENTAMENTO PROFESSIONALE",exp_SILP!$AD17="."),"A.3 ORIENTAMENTO PROFESSIONALE (CARCERE)", IF(AND(exp_SILP!$S17="A.4 CONSULENZA ORIENTATIVA",exp_SILP!$AD17="4.2"),"A.4 CONSULENZA ORIENTATIVA (CARCERE)", IF(AND(exp_SILP!$S17="A.4 CONSULENZA ORIENTATIVA",exp_SILP!$AD17="."),"A.4 CONSULENZA ORIENTATIVA (CARCERE)", IF(AND(exp_SILP!$S17="A.5 - LEP F1 - ACCOMPAGNAMENTO AL LAVORO",exp_SILP!$AD17="4.2"),"A.5 - LEP F1 - ACCOMPAGNAMENTO AL LAVORO (CARCERE)", IF(AND(exp_SILP!$S17="A.5 - LEP F1 - ACCOMPAGNAMENTO AL LAVORO",exp_SILP!$AD17="."),"A.5 - LEP F1 - ACCOMPAGNAMENTO AL LAVORO (CARCERE)", IF(AND(exp_SILP!$S17="A.5.2a - TUTORAGGIO TIROCINI",exp_SILP!$AD17="4.2"),"A.5.2a - TUTORAGGIO TIROCINI (CARCERE)", exp_SILP!$S17))))))) -> A.5 - LEP F1 - ACCOMPAGNAMENTO AL LAVORO | C17: =CONCATENATE(VLOOKUP(exp_SILP!$B17,'DATI COMMESSE'!$A$2:$F$25,4,FALSE)," - ", VLOOKUP(exp_SILP!$B17,'DATI COMMESSE'!$A$2:$F$25,2,FALSE)," - ",VLOOKUP(exp_SILP!$B17,'DATI COMMESSE'!$A$2:$F$25,3,FALSE)) -> GOL - 22-02-5000 - 22-12-5003 | D17: =LEFT(exp_SILP!$R17,5) -> 10:00 | E17: =RIGHT(exp_SILP!$R17,5) -> 11:00 | F17: =IF(exp_SILP!$AG17>=60,exp_SILP!$AG17/60,exp_SILP!$AG17) -> 1 | G17: =VLOOKUP(exp_SILP!$Y17,'DATI CM'!$A$2:$F$28,2,FALSE) -> DNRSMN97E58L219U | H17: =VLOOKUP(exp_SILP!$Y17,'DATI CM'!$A$2:$F$28,3,FALSE) | I17: =IF(A17>0,"N","N") -> N | J17: =VLOOKUP(exp_SILP!$Y17,'DATI CM'!$A$2:$F$28,4,FALSE) | K17: =VLOOKUP(exp_SILP!$B17,'DATI COMMESSE'!$A$2:$F$25,5,FALSE) -> 39.94 | L17: =IF(exp_SILP!$B17="A4.10 - LEP E - ORIENTAMENTO SPECIALISTICO SKILL GAP ANALYSIS - GRUPPO 3P",0,VLOOKUP(exp_SILP!$Y17,'DATI CM'!$A$2:$F$28,6,FALSE)) | M17: =IFERROR(VLOOKUP(exp_SILP!$B17,'DATI CM'!$H$2:$I$16,2,FALSE)*exp_SILP!$F17,0) -> 0 | N17: =VLOOKUP(exp_SILP!$B17,'DATI COMMESSE'!$A$2:$F$25,4,FALSE) -> GOL | O17: =VLOOKUP(exp_SILP!$B17,'DATI COMMESSE'!$A$2:$F$25,5,FALSE)*exp_SILP!$F17 -> 39.94 | P17: =IF(MID(exp_SILP!$W17,10,2)>"40","F","M") -> M | Q17: 01/06/2023 | R17: 10:00-11:00 | S17: A.5 - LEP F1 - ACCOMPAGNAMENTO AL LAVORO | T17: Progetti per accreditati | V17: BIANCO DANIELE MARCO | W17: BNCDLM80L07L219L | X17: 07/07/1980 | Y17: DENARO SIMONA | Z17: Erogato | AA17: INFORCOOP ECIPA PIEMONTE | AB17: Incontro MDL | AC17: INFORCOOP ECIPA PIEMONTE VIA TREVISO 12 - TORINO | AG17: 60 | AH17: 01/06/2023 | AI17: DNRSMN97E58L219U | AJ17: =VLOOKUP(exp_SILP!$Y17,'DATI CM'!$A$2:$F$28,2,FALSE) -> DNRSMN97E58L219U
A18: =IFERROR(VLOOKUP(exp_SILP!$W18,exp_utenti_P!D:D,1,FALSE),"_DA INSERIRE") -> BLSRRT80A25L219K | B18: =IF(AND(exp_SILP!$S18="A.3 ORIENTAMENTO PROFESSIONALE",exp_SILP!$AD18="4.2"),"A.3 ORIENTAMENTO PROFESSIONALE (CARCERE)", IF(AND(exp_SILP!$S18="A.3 ORIENTAMENTO PROFESSIONALE",exp_SILP!$AD18="."),"A.3 ORIENTAMENTO PROFESSIONALE (CARCERE)", IF(AND(exp_SILP!$S18="A.4 CONSULENZA ORIENTATIVA",exp_SILP!$AD18="4.2"),"A.4 CONSULENZA ORIENTATIVA (CARCERE)", IF(AND(exp_SILP!$S18="A.4 CONSULENZA ORIENTATIVA",exp_SILP!$AD18="."),"A.4 CONSULENZA ORIENTATIVA (CARCERE)", IF(AND(exp_SILP!$S18="A.5 - LEP F1 - ACCOMPAGNAMENTO AL LAVORO",exp_SILP!$AD18="4.2"),"A.5 - LEP F1 - ACCOMPAGNAMENTO AL LAVORO (CARCERE)", IF(AND(exp_SILP!$S18="A.5 - LEP F1 - ACCOMPAGNAMENTO AL LAVORO",exp_SILP!$AD18="."),"A.5 - LEP F1 - ACCOMPAGNAMENTO AL LAVORO (CARCERE)", IF(AND(exp_SILP!$S18="A.5.2a - TUTORAGGIO TIROCINI",exp_SILP!$AD18="4.2"),"A.5.2a - TUTORAGGIO TIROCINI (CARCERE)", exp_SILP!$S18))))))) -> A.5 - LEP F1 - ACCOMPAGNAMENTO AL LAVORO | C18: =CONCATENATE(VLOOKUP(exp_SILP!$B18,'DATI COMMESSE'!$A$2:$F$25,4,FALSE)," - ", VLOOKUP(exp_SILP!$B18,'DATI COMMESSE'!$A$2:$F$25,2,FALSE)," - ",VLOOKUP(exp_SILP!$B18,'DATI COMMESSE'!$A$2:$F$25,3,FALSE)) -> GOL - 22-02-5000 - 22-12-5003 | D18: =LEFT(exp_SILP!$R18,5) -> 15:00 | E18: =RIGHT(exp_SILP!$R18,5) -> 17:00 | F18: =IF(exp_SILP!$AG18>=60,exp_SILP!$AG18/60,exp_SILP!$AG18) -> 2 | G18: =VLOOKUP(exp_SILP!$Y18,'DATI CM'!$A$2:$F$28,2,FALSE) -> DNRSMN97E58L219U | H18: =VLOOKUP(exp_SILP!$Y18,'DATI CM'!$A$2:$F$28,3,FALSE) | I18: =IF(A18>0,"N","N") -> N | J18: =VLOOKUP(exp_SILP!$Y18,'DATI CM'!$A$2:$F$28,4,FALSE) | K18: =VLOOKUP(exp_SILP!$B18,'DATI COMMESSE'!$A$2:$F$25,5,FALSE) -> 39.94 | L18: =IF(exp_SILP!$B18="A4.10 - LEP E - ORIENTAMENTO SPECIALISTICO SKILL GAP ANALYSIS - GRUPPO 3P",0,VLOOKUP(exp_SILP!$Y18,'DATI CM'!$A$2:$F$28,6,FALSE)) | M18: =IFERROR(VLOOKUP(exp_SILP!$B18,'DATI CM'!$H$2:$I$16,2,FALSE)*exp_SILP!$F18,0) -> 0 | N18: =VLOOKUP(exp_SILP!$B18,'DATI COMMESSE'!$A$2:$F$25,4,FALSE) -> GOL | O18: =VLOOKUP(exp_SILP!$B18,'DATI COMMESSE'!$A$2:$F$25,5,FALSE)*exp_SILP!$F18 -> 79.88 | P18: =IF(MID(exp_SILP!$W18,10,2)>"40","F","M") -> M | Q18: 01/06/2023 | R18: 15:00-17:00 | S18: A.5 - LEP F1 - ACCOMPAGNAMENTO AL LAVORO | T18: Progetti per accreditati | V18: BELSITO ROBERTO | W18: BLSRRT80A25L219K | X18: 25/01/1980 | Y18: DENARO SIMONA | Z18: Erogato | AA18: INFORCOOP ECIPA PIEMONTE | AB18: Incontro MDL | AC18: INFORCOOP ECIPA PIEMONTE VIA TREVISO 12 - TORINO | AG18: 120 | AH18: 01/06/2023 | AI18: DNRSMN97E58L219U | AJ18: =VLOOKUP(exp_SILP!$Y18,'DATI CM'!$A$2:$F$28,2,FALSE) -> DNRSMN97E58L219U
A19: =IFERROR(VLOOKUP(exp_SILP!$W19,exp_utenti_P!D:D,1,FALSE),"_DA INSERIRE") -> DRDZRC92C41L219G | B19: =IF(AND(exp_SILP!$S19="A.3 ORIENTAMENTO PROFESSIONALE",exp_SILP!$AD19="4.2"),"A.3 ORIENTAMENTO PROFESSIONALE (CARCERE)", IF(AND(exp_SILP!$S19="A.3 ORIENTAMENTO PROFESSIONALE",exp_SILP!$AD19="."),"A.3 ORIENTAMENTO PROFESSIONALE (CARCERE)", IF(AND(exp_SILP!$S19="A.4 CONSULENZA ORIENTATIVA",exp_SILP!$AD19="4.2"),"A.4 CONSULENZA ORIENTATIVA (CARCERE)", IF(AND(exp_SILP!$S19="A.4 CONSULENZA ORIENTATIVA",exp_SILP!$AD19="."),"A.4 CONSULENZA ORIENTATIVA (CARCERE)", IF(AND(exp_SILP!$S19="A.5 - LEP F1 - ACCOMPAGNAMENTO AL LAVORO",exp_SILP!$AD19="4.2"),"A.5 - LEP F1 - ACCOMPAGNAMENTO AL LAVORO (CARCERE)", IF(AND(exp_SILP!$S19="A.5 - LEP F1 - ACCOMPAGNAMENTO AL LAVORO",exp_SILP!$AD19="."),"A.5 - LEP F1 - ACCOMPAGNAMENTO AL LAVORO (CARCERE)", IF(AND(exp_SILP!$S19="A.5.2a - TUTORAGGIO TIROCINI",exp_SILP!$AD19="4.2"),"A.5.2a - TUTORAGGIO TIROCINI (CARCERE)", exp_SILP!$S19))))))) -> A.5 - LEP F1 - ACCOMPAGNAMENTO AL LAVORO | C19: =CONCATENATE(VLOOKUP(exp_SILP!$B19,'DATI COMMESSE'!$A$2:$F$25,4,FALSE)," - ", VLOOKUP(exp_SILP!$B19,'DATI COMMESSE'!$A$2:$F$25,2,FALSE)," - ",VLOOKUP(exp_SILP!$B19,'DATI COMMESSE'!$A$2:$F$25,3,FALSE)) -> GOL - 22-02-5000 - 22-12-5003 | D19: =LEFT(exp_SILP!$R19,5) -> 16:00 | E19: =RIGHT(exp_SILP!$R19,5) -> 18:00 | F19: =IF(exp_SILP!$AG19>=60,exp_SILP!$AG19/60,exp_SILP!$AG19) -> 2 | G19: =VLOOKUP(exp_SILP!$Y19,'DATI CM'!$A$2:$F$28,2,FALSE) -> SPDPRZ67H55L219V | H19: =VLOOKUP(exp_SILP!$Y19,'DATI CM'!$A$2:$F$28,3,FALSE) -> A010 | I19: =IF(A19>0,"N","N") -> N | J19: =VLOOKUP(exp_SILP!$Y19,'DATI CM'!$A$2:$F$28,4,FALSE) -> TORINO | K19: =VLOOKUP(exp_SILP!$B19,'DATI COMMESSE'!$A$2:$F$25,5,FALSE) -> 39.94 | L19: =IF(exp_SILP!$B19="A4.10 - LEP E - ORIENTAMENTO SPECIALISTICO SKILL GAP ANALYSIS - GRUPPO 3P",0,VLOOKUP(exp_SILP!$Y19,'DATI CM'!$A$2:$F$28,6,FALSE)) | M19: =IFERROR(VLOOKUP(exp_SILP!$B19,'DATI CM'!$H$2:$I$16,2,FALSE)*exp_SILP!$F19,0) -> 0 | N19: =VLOOKUP(exp_SILP!$B19,'DATI COMMESSE'!$A$2:$F$25,4,FALSE) -> GOL | O19: =VLOOKUP(exp_SILP!$B19,'DATI COMMESSE'!$A$2:$F$25,5,FALSE)*exp_SILP!$F19 -> 79.88 | P19: =IF(MID(exp_SILP!$W19,10,2)>"40","F","M") -> F | Q19: 01/06/2023 | R19: 16:00-18:00 | S19: A.5 - LEP F1 - ACCOMPAGNAMENTO AL LAVORO | T19: Progetti per accreditati | V19: DORDEVIC ZORICA | W19: DRDZRC92C41L219G | X19: 01/03/1992 | Y19: SPADARO PATRIZIA | Z19: Erogato | AA19: INFORCOOP ECIPA PIEMONTE | AB19: Incontro MDL | AC19: INFORCOOP ECIPA PIEMONTE VIA TREVISO 12 - TORINO | AG19: 120 | AH19: 01/06/2023 | AI19: SPDPRZ67H55L219V | AJ19: =VLOOKUP(exp_SILP!$Y19,'DATI CM'!$A$2:$F$28,2,FALSE) -> SPDPRZ67H55L219V
A20: =IFERROR(VLOOKUP(exp_SILP!$W20,exp_utenti_P!D:D,1,FALSE),"_DA INSERIRE") -> RSSDRH73A55C351F | B20: =IF(AND(exp_SILP!$S20="A.3 ORIENTAMENTO PROFESSIONALE",exp_SILP!$AD20="4.2"),"A.3 ORIENTAMENTO PROFESSIONALE (CARCERE)", IF(AND(exp_SILP!$S20="A.3 ORIENTAMENTO PROFESSIONALE",exp_SILP!$AD20="."),"A.3 ORIENTAMENTO PROFESSIONALE (CARCERE)", IF(AND(exp_SILP!$S20="A.4 CONSULENZA ORIENTATIVA",exp_SILP!$AD20="4.2"),"A.4 CONSULENZA ORIENTATIVA (CARCERE)", IF(AND(exp_SILP!$S20="A.4 CONSULENZA ORIENTATIVA",exp_SILP!$AD20="."),"A.4 CONSULENZA ORIENTATIVA (CARCERE)", IF(AND(exp_SILP!$S20="A.5 - LEP F1 - ACCOMPAGNAMENTO AL LAVORO",exp_SILP!$AD20="4.2"),"A.5 - LEP F1 - ACCOMPAGNAMENTO AL LAVORO (CARCERE)", IF(AND(exp_SILP!$S20="A.5 - LEP F1 - ACCOMPAGNAMENTO AL LAVORO",exp_SILP!$AD20="."),"A.5 - LEP F1 - ACCOMPAGNAMENTO AL LAVORO (CARCERE)", IF(AND(exp_SILP!$S20="A.5.2a - TUTORAGGIO TIROCINI",exp_SILP!$AD20="4.2"),"A.5.2a - TUTORAGGIO TIROCINI (CARCERE)", exp_SILP!$S20))))))) -> A.5 - LEP F1 - ACCOMPAGNAMENTO AL LAVORO | C20: =CONCATENATE(VLOOKUP(exp_SILP!$B20,'DATI COMMESSE'!$A$2:$F$25,4,FALSE)," - ", VLOOKUP(exp_SILP!$B20,'DATI COMMESSE'!$A$2:$F$25,2,FALSE)," - ",VLOOKUP(exp_SILP!$B20,'DATI COMMESSE'!$A$2:$F$25,3,FALSE)) -> GOL - 22-02-5000 - 22-12-5003 | D20: =LEFT(exp_SILP!$R20,5) -> 16:00 | E20: =RIGHT(exp_SILP!$R20,5) -> 17:00 | F20: =IF(exp_SILP!$AG20>=60,exp_SILP!$AG20/60,exp_SILP!$AG20) -> 1 | G20: =VLOOKUP(exp_SILP!$Y20,'DATI CM'!$A$2:$F$28,2,FALSE) -> MNRCLD73B46G674U | H20: =VLOOKUP(exp_SILP!$Y20,'DATI CM'!$A$2:$F$28,3,FALSE) -> A011 | I20: =IF(A20>0,"N","N") -> N | J20: =VLOOKUP(exp_SILP!$Y20,'DATI CM'!$A$2:$F$28,4,FALSE) -> TORINO | K20: =VLOOKUP(exp_SILP!$B20,'DATI COMMESSE'!$A$2:$F$25,5,FALSE) -> 39.94 | L20: =IF(exp_SILP!$B20="A4.10 - LEP E - ORIENTAMENTO SPECIALISTICO SKILL GAP ANALYSIS - GRUPPO 3P",0,VLOOKUP(exp_SILP!$Y20,'DATI CM'!$A$2:$F$28,6,FALSE)) -> 25 | M20: =IFERROR(VLOOKUP(exp_SILP!$B20,'DATI CM'!$H$2:$I$16,2,FALSE)*exp_SILP!$F20,0) -> 0 | N20: =VLOOKUP(exp_SILP!$B20,'DATI COMMESSE'!$A$2:$F$25,4,FALSE) -> GOL | O20: =VLOOKUP(exp_SILP!$B20,'DATI COMMESSE'!$A$2:$F$25,5,FALSE)*exp_SILP!$F20 -> 39.94 | P20: =IF(MID(exp_SILP!$W20,10,2)>"40","F","M") -> F | Q20: 01/06/2023 | R20: 16:00-17:00 | S20: A.5 - LEP F1 - ACCOMPAGNAMENTO AL LAVORO | T20: Progetti per accreditati | V20: ROSSI DEBORAH | W20: RSSDRH73A55C351F | X20: 15/01/1973 | Y20: MAINERO CLAUDIA | Z20: Erogato | AA20: INFORCOOP ECIPA PIEMONTE | AB20: Incontro MDL | AC20: INFORCOOP ECIPA PIEMONTE VIA TREVISO 12 - TORINO | AF20: B.O. | AG20: 60 | AH20: 07/06/2023 | AI20: MNRCLD73B46G674U | AJ20: =VLOOKUP(exp_SILP!$Y20,'DATI CM'!$A$2:$F$28,2,FALSE) -> MNRCLD73B46G674U
A21: =IFERROR(VLOOKUP(exp_SILP!$W21,exp_utenti_P!D:D,1,FALSE),"_DA INSERIRE") -> TTNSFN74L68L219D | B21: =IF(AND(exp_SILP!$S21="A.3 ORIENTAMENTO PROFESSIONALE",exp_SILP!$AD21="4.2"),"A.3 ORIENTAMENTO PROFESSIONALE (CARCERE)", IF(AND(exp_SILP!$S21="A.3 ORIENTAMENTO PROFESSIONALE",exp_SILP!$AD21="."),"A.3 ORIENTAMENTO PROFESSIONALE (CARCERE)", IF(AND(exp_SILP!$S21="A.4 CONSULENZA ORIENTATIVA",exp_SILP!$AD21="4.2"),"A.4 CONSULENZA ORIENTATIVA (CARCERE)", IF(AND(exp_SILP!$S21="A.4 CONSULENZA ORIENTATIVA",exp_SILP!$AD21="."),"A.4 CONSULENZA ORIENTATIVA (CARCERE)", IF(AND(exp_SILP!$S21="A.5 - LEP F1 - ACCOMPAGNAMENTO AL LAVORO",exp_SILP!$AD21="4.2"),"A.5 - LEP F1 - ACCOMPAGNAMENTO AL LAVORO (CARCERE)", IF(AND(exp_SILP!$S21="A.5 - LEP F1 - ACCOMPAGNAMENTO AL LAVORO",exp_SILP!$AD21="."),"A.5 - LEP F1 - ACCOMPAGNAMENTO AL LAVORO (CARCERE)", IF(AND(exp_SILP!$S21="A.5.2a - TUTORAGGIO TIROCINI",exp_SILP!$AD21="4.2"),"A.5.2a - TUTORAGGIO TIROCINI (CARCERE)", exp_SILP!$S21))))))) -> A.5.1 ATTIVAZIONE E RICERCA OPPORTUNITA' (1-C) | C21: =CONCATENATE(VLOOKUP(exp_SILP!$B21,'DATI COMMESSE'!$A$2:$F$25,4,FALSE)," - ", VLOOKUP(exp_SILP!$B21,'DATI COMMESSE'!$A$2:$F$25,2,FALSE)," - ",VLOOKUP(exp_SILP!$B21,'DATI COMMESSE'!$A$2:$F$25,3,FALSE)) -> FRD - 22-02-5000 - 22-12-5002 | D21: =LEFT(exp_SILP!$R21,5) -> 13:00 | E21: =RIGHT(exp_SILP!$R21,5) -> 14:00 | F21: =IF(exp_SILP!$AG21>=60,exp_SILP!$AG21/60,exp_SILP!$AG21) -> 1 | G21: =VLOOKUP(exp_SILP!$Y21,'DATI CM'!$A$2:$F$28,2,FALSE) -> MNRCLD73B46G674U | H21: =VLOOKUP(exp_SILP!$Y21,'DATI CM'!$A$2:$F$28,3,FALSE) -> A011 | I21: =IF(A21>0,"N","N") -> N | J21: =VLOOKUP(exp_SILP!$Y21,'DATI CM'!$A$2:$F$28,4,FALSE) -> TORINO | K21: =VLOOKUP(exp_SILP!$B21,'DATI COMMESSE'!$A$2:$F$25,5,FALSE) -> 35.5 | L21: =IF(exp_SILP!$B21="A4.10 - LEP E - ORIENTAMENTO SPECIALISTICO SKILL GAP ANALYSIS - GRUPPO 3P",0,VLOOKUP(exp_SILP!$Y21,'DATI CM'!$A$2:$F$28,6,FALSE)) -> 25 | M21: =IFERROR(VLOOKUP(exp_SILP!$B21,'DATI CM'!$H$2:$I$16,2,FALSE)*exp_SILP!$F21,0) -> 0 | N21: =VLOOKUP(exp_SILP!$B21,'DATI COMMESSE'!$A$2:$F$25,4,FALSE) -> FRD | O21: =VLOOKUP(exp_SILP!$B21,'DATI COMMESSE'!$A$2:$F$25,5,FALSE)*exp_SILP!$F21 -> 35.5 | P21: =IF(MID(exp_SILP!$W21,10,2)>"40","F","M") -> F | Q21: 01/06/2023 | R21: 13:00-14:00 | S21: A.5.1 ATTIVAZIONE E RICERCA OPPORTUNITA' (1-C) | T21: Progetti per accreditati | V21: TITONE STEFANIA | W21: TTNSFN74L68L219D | X21: 28/07/1974 | Y21: MAINERO CLAUDIA | Z21: Erogato | AA21: INFORCOOP ECIPA PIEMONTE | AB21: Incontro MDL | AC21: INFORCOOP ECIPA PIEMONTE VIA TREVISO 12 - TORINO | AF21: B.O. | AG21: 60 | AH21: 07/06/2023 | AI21: MNRCLD73B46G674U | AJ21: =VLOOKUP(exp_SILP!$Y21,'DATI CM'!$A$2:$F$28,2,FALSE) -> MNRCLD73B46G674U
A22: =IFERROR(VLOOKUP(exp_SILP!$W22,exp_utenti_P!D:D,1,FALSE),"_DA INSERIRE") -> TTNSFN74L68L219D | B22: =IF(AND(exp_SILP!$S22="A.3 ORIENTAMENTO PROFESSIONALE",exp_SILP!$AD22="4.2"),"A.3 ORIENTAMENTO PROFESSIONALE (CARCERE)", IF(AND(exp_SILP!$S22="A.3 ORIENTAMENTO PROFESSIONALE",exp_SILP!$AD22="."),"A.3 ORIENTAMENTO PROFESSIONALE (CARCERE)", IF(AND(exp_SILP!$S22="A.4 CONSULENZA ORIENTATIVA",exp_SILP!$AD22="4.2"),"A.4 CONSULENZA ORIENTATIVA (CARCERE)", IF(AND(exp_SILP!$S22="A.4 CONSULENZA ORIENTATIVA",exp_SILP!$AD22="."),"A.4 CONSULENZA ORIENTATIVA (CARCERE)", IF(AND(exp_SILP!$S22="A.5 - LEP F1 - ACCOMPAGNAMENTO AL LAVORO",exp_SILP!$AD22="4.2"),"A.5 - LEP F1 - ACCOMPAGNAMENTO AL LAVORO (CARCERE)", IF(AND(exp_SILP!$S22="A.5 - LEP F1 - ACCOMPAGNAMENTO AL LAVORO",exp_SILP!$AD22="."),"A.5 - LEP F1 - ACCOMPAGNAMENTO AL LAVORO (CARCERE)", IF(AND(exp_SILP!$S22="A.5.2a - TUTORAGGIO TIROCINI",exp_SILP!$AD22="4.2"),"A.5.2a - TUTORAGGIO TIROCINI (CARCERE)", exp_SILP!$S22))))))) -> A.5.1 ATTIVAZIONE E RICERCA OPPORTUNITA' (1-C) | C22: =CONCATENATE(VLOOKUP(exp_SILP!$B22,'DATI COMMESSE'!$A$2:$F$25,4,FALSE)," - ", VLOOKUP(exp_SILP!$B22,'DATI COMMESSE'!$A$2:$F$25,2,FALSE)," - ",VLOOKUP(exp_SILP!$B22,'DATI COMMESSE'!$A$2:$F$25,3,FALSE)) -> FRD - 22-02-5000 - 22-12-5002 | D22: =LEFT(exp_SILP!$R22,5) -> 10:00 | E22: =RIGHT(exp_SILP!$R22,5) -> 13:00 | F22: =IF(exp_SILP!$AG22>=60,exp_SILP!$AG22/60,exp_SILP!$AG22) -> 3 | G22: =VLOOKUP(exp_SILP!$Y22,'DATI CM'!$A$2:$F$28,2,FALSE) -> MNRCLD73B46G674U | H22: =VLOOKUP(exp_SILP!$Y22,'DATI CM'!$A$2:$F$28,3,FALSE) -> A011 | I22: =IF(A22>0,"N","N") -> N | J22: =VLOOKUP(exp_SILP!$Y22,'DATI CM'!$A$2:$F$28,4,FALSE) -> TORINO | K22: =VLOOKUP(exp_SILP!$B22,'DATI COMMESSE'!$A$2:$F$25,5,FALSE) -> 35.5 | L22: =IF(exp_SILP!$B22="A4.10 - LEP E - ORIENTAMENTO SPECIALISTICO SKILL GAP ANALYSIS - GRUPPO 3P",0,VLOOKUP(exp_SILP!$Y22,'DATI CM'!$A$2:$F$28,6,FALSE)) -> 25 | M22: =IFERROR(VLOOKUP(exp_SILP!$B22,'DATI CM'!$H$2:$I$16,2,FALSE)*exp_SILP!$F22,0) -> 0 | N22: =VLOOKUP(exp_SILP!$B22,'DATI COMMESSE'!$A$2:$F$25,4,FALSE) -> FRD | O22: =VLOOKUP(exp_SILP!$B22,'DATI COMMESSE'!$A$2:$F$25,5,FALSE)*exp_SILP!$F22 -> 106.5 | P22: =IF(MID(exp_SILP!$W22,10,2)>"40","F","M") -> F | Q22: 01/06/2023 | R22: 10:00-13:00 | S22: A.5.1 ATTIVAZIONE E RICERCA OPPORTUNITA' (1-C) | T22: Progetti per accreditati | V22: TITONE STEFANIA | W22: TTNSFN74L68L219D | X22: 28/07/1974 | Y22: MAINERO CLAUDIA | Z22: Erogato | AA22: INFORCOOP ECIPA PIEMONTE | AB22: Incontro MDLpresentato | AC22: INFORCOOP ECIPA PIEMONTE VIA TREVISO 12 - TORINO | AG22: 180 | AH22: 07/06/2023 | AI22: MNRCLD73B46G674U | AJ22: =VLOOKUP(exp_SILP!$Y22,'DATI CM'!$A$2:$F$28,2,FALSE) -> MNRCLD73B46G674U
A23: =IFERROR(VLOOKUP(exp_SILP!$W23,exp_utenti_P!D:D,1,FALSE),"_DA INSERIRE") -> MNFLNZ03E12C722P | B23: =IF(AND(exp_SILP!$S23="A.3 ORIENTAMENTO PROFESSIONALE",exp_SILP!$AD23="4.2"),"A.3 ORIENTAMENTO PROFESSIONALE (CARCERE)", IF(AND(exp_SILP!$S23="A.3 ORIENTAMENTO PROFESSIONALE",exp_SILP!$AD23="."),"A.3 ORIENTAMENTO PROFESSIONALE (CARCERE)", IF(AND(exp_SILP!$S23="A.4 CONSULENZA ORIENTATIVA",exp_SILP!$AD23="4.2"),"A.4 CONSULENZA ORIENTATIVA (CARCERE)", IF(AND(exp_SILP!$S23="A.4 CONSULENZA ORIENTATIVA",exp_SILP!$AD23="."),"A.4 CONSULENZA ORIENTATIVA (CARCERE)", IF(AND(exp_SILP!$S23="A.5 - LEP F1 - ACCOMPAGNAMENTO AL LAVORO",exp_SILP!$AD23="4.2"),"A.5 - LEP F1 - ACCOMPAGNAMENTO AL LAVORO (CARCERE)", IF(AND(exp_SILP!$S23="A.5 - LEP F1 - ACCOMPAGNAMENTO AL LAVORO",exp_SILP!$AD23="."),"A.5 - LEP F1 - ACCOMPAGNAMENTO AL LAVORO (CARCERE)", IF(AND(exp_SILP!$S23="A.5.2a - TUTORAGGIO TIROCINI",exp_SILP!$AD23="4.2"),"A.5.2a - TUTORAGGIO TIROCINI (CARCERE)", exp_SILP!$S23))))))) -> A.5.2a - TUTORAGGIO TIROCINI | C23: =CONCATENATE(VLOOKUP(exp_SILP!$B23,'DATI COMMESSE'!$A$2:$F$25,4,FALSE)," - ", VLOOKUP(exp_SILP!$B23,'DATI COMMESSE'!$A$2:$F$25,2,FALSE)," - ",VLOOKUP(exp_SILP!$B23,'DATI COMMESSE'!$A$2:$F$25,3,FALSE)) -> FRD - 22-02-5000 - 22-12-5002 | D23: =LEFT(exp_SILP!$R23,5) -> 08:00 | E23: =RIGHT(exp_SILP!$R23,5) -> 09:00 | F23: =IF(exp_SILP!$AG23>=60,exp_SILP!$AG23/60,exp_SILP!$AG23) -> 1 | G23: =VLOOKUP(exp_SILP!$Y23,'DATI CM'!$A$2:$F$28,2,FALSE) -> MNRCLD73B46G674U | H23: =VLOOKUP(exp_SILP!$Y23,'DATI CM'!$A$2:$F$28,3,FALSE) -> A011 | I23: =IF(A23>0,"N","N") -> N | J23: =VLOOKUP(exp_SILP!$Y23,'DATI CM'!$A$2:$F$28,4,FALSE) -> TORINO | K23: =VLOOKUP(exp_SILP!$B23,'DATI COMMESSE'!$A$2:$F$25,5,FALSE) -> 35.5 | L23: =IF(exp_SILP!$B23="A4.10 - LEP E - ORIENTAMENTO SPECIALISTICO SKILL GAP ANALYSIS - GRUPPO 3P",0,VLOOKUP(exp_SILP!$Y23,'DATI CM'!$A$2:$F$28,6,FALSE)) -> 25 | M23: =IFERROR(VLOOKUP(exp_SILP!$B23,'DATI CM'!$H$2:$I$16,2,FALSE)*exp_SILP!$F23,0) -> 0 | N23: =VLOOKUP(exp_SILP!$B23,'DATI COMMESSE'!$A$2:$F$25,4,FALSE) -> FRD | O23: =VLOOKUP(exp_SILP!$B23,'DATI COMMESSE'!$A$2:$F$25,5,FALSE)*exp_SILP!$F23 -> 35.5 | P23: =IF(MID(exp_SILP!$W23,10,2)>"40","F","M") -> M | Q23: 01/06/2023 | R23: 08:00-09:00 | S23: A.5.2a - TUTORAGGIO TIROCINI | T23: Progetti per accreditati | V23: MANFREDI LORENZO | W23: MNFLNZ03E12C722P | X23: 12/05/2003 | Y23: MAINERO CLAUDIA | Z23: Erogato | AA23: INFORCOOP ECIPA PIEMONTE | AB23: Incontro MDLpresentato | AC23: INFORCOOP ECIPA PIEMONTE VIA TREVISO 12 - TORINO | AD23: TUTORAGGIO IN AZIENDA | AG23: 60 | AH23: 07/06/2023 | AI23: MNRCLD73B46G674U | AJ23: =VLOOKUP(exp_SILP!$Y23,'DATI CM'!$A$2:$F$28,2,FALSE) -> MNRCLD73B46G674U
A24: =IFERROR(VLOOKUP(exp_SILP!$W24,exp_utenti_P!D:D,1,FALSE),"_DA INSERIRE") -> BRTJNY00R63L219O | B24: =IF(AND(exp_SILP!$S24="A.3 ORIENTAMENTO PROFESSIONALE",exp_SILP!$AD24="4.2"),"A.3 ORIENTAMENTO PROFESSIONALE (CARCERE)", IF(AND(exp_SILP!$S24="A.3 ORIENTAMENTO PROFESSIONALE",exp_SILP!$AD24="."),"A.3 ORIENTAMENTO PROFESSIONALE (CARCERE)", IF(AND(exp_SILP!$S24="A.4 CONSULENZA ORIENTATIVA",exp_SILP!$AD24="4.2"),"A.4 CONSULENZA ORIENTATIVA (CARCERE)", IF(AND(exp_SILP!$S24="A.4 CONSULENZA ORIENTATIVA",exp_SILP!$AD24="."),"A.4 CONSULENZA ORIENTATIVA (CARCERE)", IF(AND(exp_SILP!$S24="A.5 - LEP F1 - ACCOMPAGNAMENTO AL LAVORO",exp_SILP!$AD24="4.2"),"A.5 - LEP F1 - ACCOMPAGNAMENTO AL LAVORO (CARCERE)", IF(AND(exp_SILP!$S24="A.5 - LEP F1 - ACCOMPAGNAMENTO AL LAVORO",exp_SILP!$AD24="."),"A.5 - LEP F1 - ACCOMPAGNAMENTO AL LAVORO (CARCERE)", IF(AND(exp_SILP!$S24="A.5.2a - TUTORAGGIO TIROCINI",exp_SILP!$AD24="4.2"),"A.5.2a - TUTORAGGIO TIROCINI (CARCERE)", exp_SILP!$S24))))))) -> A.5.2a - TUTORAGGIO TIROCINI | C24: =CONCATENATE(VLOOKUP(exp_SILP!$B24,'DATI COMMESSE'!$A$2:$F$25,4,FALSE)," - ", VLOOKUP(exp_SILP!$B24,'DATI COMMESSE'!$A$2:$F$25,2,FALSE)," - ",VLOOKUP(exp_SILP!$B24,'DATI COMMESSE'!$A$2:$F$25,3,FALSE)) -> FRD - 22-02-5000 - 22-12-5002 | D24: =LEFT(exp_SILP!$R24,5) -> 16:00 | E24: =RIGHT(exp_SILP!$R24,5) -> 18:00 | F24: =IF(exp_SILP!$AG24>=60,exp_SILP!$AG24/60,exp_SILP!$AG24) -> 2 | G24: =VLOOKUP(exp_SILP!$Y24,'DATI CM'!$A$2:$F$28,2,FALSE) -> FLCSRN79S42L219X | H24: =VLOOKUP(exp_SILP!$Y24,'DATI CM'!$A$2:$F$28,3,FALSE) -> A011 | I24: =IF(A24>0,"N","N") -> N | J24: =VLOOKUP(exp_SILP!$Y24,'DATI CM'!$A$2:$F$28,4,FALSE) -> TORINO | K24: =VLOOKUP(exp_SILP!$B24,'DATI COMMESSE'!$A$2:$F$25,5,FALSE) -> 35.5 | L24: =IF(exp_SILP!$B24="A4.10 - LEP E - ORIENTAMENTO SPECIALISTICO SKILL GAP ANALYSIS - GRUPPO 3P",0,VLOOKUP(exp_SILP!$Y24,'DATI CM'!$A$2:$F$28,6,FALSE)) -> 25 | M24: =IFERROR(VLOOKUP(exp_SILP!$B24,'DATI CM'!$H$2:$I$16,2,FALSE)*exp_SILP!$F24,0) -> 0 | N24: =VLOOKUP(exp_SILP!$B24,'DATI COMMESSE'!$A$2:$F$25,4,FALSE) -> FRD | O24: =VLOOKUP(exp_SILP!$B24,'DATI COMMESSE'!$A$2:$F$25,5,FALSE)*exp_SILP!$F24 -> 71 | P24: =IF(MID(exp_SILP!$W24,10,2)>"40","F","M") -> F | Q24: 01/06/2023 | R24: 16:00-18:00 | S24: A.5.2a - TUTORAGGIO TIROCINI | T24: Progetti per accreditati | V24: BERTAGGIA JENNY | W24: BRTJNY00R63L219O | X24: 23/10/2000 | Y24: FALCONE SERENA | Z24: Erogato | AA24: INFORCOOP ECIPA PIEMONTE | AB24: Incontro MDLpresentato | AC24: INFORCOOP ECIPA PIEMONTE VIA LIVORNO 53/b - TORINO | AG24: 120 | AH24: 29/06/2023 | AI24: FLCSRN79S42L219X | AJ24: =VLOOKUP(exp_SILP!$Y24,'DATI CM'!$A$2:$F$28,2,FALSE) -> FLCSRN79S42L219X
A25: =IFERROR(VLOOKUP(exp_SILP!$W25,exp_utenti_P!D:D,1,FALSE),"_DA INSERIRE") -> TPNJYD84D06Z611P | B25: =IF(AND(exp_SILP!$S25="A.3 ORIENTAMENTO PROFESSIONALE",exp_SILP!$AD25="4.2"),"A.3 ORIENTAMENTO PROFESSIONALE (CARCERE)", IF(AND(exp_SILP!$S25="A.3 ORIENTAMENTO PROFESSIONALE",exp_SILP!$AD25="."),"A.3 ORIENTAMENTO PROFESSIONALE (CARCERE)", IF(AND(exp_SILP!$S25="A.4 CONSULENZA ORIENTATIVA",exp_SILP!$AD25="4.2"),"A.4 CONSULENZA ORIENTATIVA (CARCERE)", IF(AND(exp_SILP!$S25="A.4 CONSULENZA ORIENTATIVA",exp_SILP!$AD25="."),"A.4 CONSULENZA ORIENTATIVA (CARCERE)", IF(AND(exp_SILP!$S25="A.5 - LEP F1 - ACCOMPAGNAMENTO AL LAVORO",exp_SILP!$AD25="4.2"),"A.5 - LEP F1 - ACCOMPAGNAMENTO AL LAVORO (CARCERE)", IF(AND(exp_SILP!$S25="A.5 - LEP F1 - ACCOMPAGNAMENTO AL LAVORO",exp_SILP!$AD25="."),"A.5 - LEP F1 - ACCOMPAGNAMENTO AL LAVORO (CARCERE)", IF(AND(exp_SILP!$S25="A.5.2a - TUTORAGGIO TIROCINI",exp_SILP!$AD25="4.2"),"A.5.2a - TUTORAGGIO TIROCINI (CARCERE)", exp_SILP!$S25))))))) -> A.5.6 - LEP F2 - TUTORAGGIO TIROCINI | C25: =CONCATENATE(VLOOKUP(exp_SILP!$B25,'DATI COMMESSE'!$A$2:$F$25,4,FALSE)," - ", VLOOKUP(exp_SILP!$B25,'DATI COMMESSE'!$A$2:$F$25,2,FALSE)," - ",VLOOKUP(exp_SILP!$B25,'DATI COMMESSE'!$A$2:$F$25,3,FALSE)) -> GOL - 22-02-5000 - 22-12-5003 | D25: =LEFT(exp_SILP!$R25,5) -> 13:30 | E25: =RIGHT(exp_SILP!$R25,5) -> 14:30 | F25: =IF(exp_SILP!$AG25>=60,exp_SILP!$AG25/60,exp_SILP!$AG25) -> 1 | G25: =VLOOKUP(exp_SILP!$Y25,'DATI CM'!$A$2:$F$28,2,FALSE) -> FLCSRN79S42L219X | H25: =VLOOKUP(exp_SILP!$Y25,'DATI CM'!$A$2:$F$28,3,FALSE) -> A011 | I25: =IF(A25>0,"N","N") -> N | J25: =VLOOKUP(exp_SILP!$Y25,'DATI CM'!$A$2:$F$28,4,FALSE) -> TORINO | K25: =VLOOKUP(exp_SILP!$B25,'DATI COMMESSE'!$A$2:$F$25,5,FALSE) -> 39.94 | L25: =IF(exp_SILP!$B25="A4.10 - LEP E - ORIENTAMENTO SPECIALISTICO SKILL GAP ANALYSIS - GRUPPO 3P",0,VLOOKUP(exp_SILP!$Y25,'DATI CM'!$A$2:$F$28,6,FALSE)) -> 25 | M25: =IFERROR(VLOOKUP(exp_SILP!$B25,'DATI CM'!$H$2:$I$16,2,FALSE)*exp_SILP!$F25,0) -> 0 | N25: =VLOOKUP(exp_SILP!$B25,'DATI COMMESSE'!$A$2:$F$25,4,FALSE) -> GOL | O25: =VLOOKUP(exp_SILP!$B25,'DATI COMMESSE'!$A$2:$F$25,5,FALSE)*exp_SILP!$F25 -> 39.94 | P25: =IF(MID(exp_SILP!$W25,10,2)>"40","F","M") -> M | Q25: 01/06/2023 | R25: 13:30-14:30 | S25: A.5.6 - LEP F2 - TUTORAGGIO TIROCINI | T25: Progetti per accreditati | V25: TAIPE NIQUITIN JIMY EDISON | W25: TPNJYD84D06Z611P | X25: 06/04/1984 | Y25: FALCONE SERENA | Z25: Erogato | AA25: INFORCOOP ECIPA PIEMONTE | AB25: Incontro MDLpresentato | AC25: INFORCOOP ECIPA PIEMONTE VIA LIVORNO 53/b - TORINO | AD25: IN IMPRESA | AF25: IN IMPRESA | AG25: 60 | AH25: 01/06/2023 | AI25: FLCSRN79S42L219X | AJ25: =VLOOKUP(exp_SILP!$Y25,'DATI CM'!$A$2:$F$28,2,FALSE) -> FLCSRN79S42L219X
A26: =IFERROR(VLOOKUP(exp_SILP!$W26,exp_utenti_P!D:D,1,FALSE),"_DA INSERIRE") -> NGYCRT99M41Z318B | B26: =IF(AND(exp_SILP!$S26="A.3 ORIENTAMENTO PROFESSIONALE",exp_SILP!$AD26="4.2"),"A.3 ORIENTAMENTO PROFESSIONALE (CARCERE)", IF(AND(exp_SILP!$S26="A.3 ORIENTAMENTO PROFESSIONALE",exp_SILP!$AD26="."),"A.3 ORIENTAMENTO PROFESSIONALE (CARCERE)", IF(AND(exp_SILP!$S26="A.4 CONSULENZA ORIENTATIVA",exp_SILP!$AD26="4.2"),"A.4 CONSULENZA ORIENTATIVA (CARCERE)", IF(AND(exp_SILP!$S26="A.4 CONSULENZA ORIENTATIVA",exp_SILP!$AD26="."),"A.4 CONSULENZA ORIENTATIVA (CARCERE)", IF(AND(exp_SILP!$S26="A.5 - LEP F1 - ACCOMPAGNAMENTO AL LAVORO",exp_SILP!$AD26="4.2"),"A.5 - LEP F1 - ACCOMPAGNAMENTO AL LAVORO (CARCERE)", IF(AND(exp_SILP!$S26="A.5 - LEP F1 - ACCOMPAGNAMENTO AL LAVORO",exp_SILP!$AD26="."),"A.5 - LEP F1 - ACCOMPAGNAMENTO AL LAVORO (CARCERE)", IF(AND(exp_SILP!$S26="A.5.2a - TUTORAGGIO TIROCINI",exp_SILP!$AD26="4.2"),"A.5.2a - TUTORAGGIO TIROCINI (CARCERE)", exp_SILP!$S26))))))) -> A4.10 - LEP E - ORIENTAMENTO SPECIALISTICO SKILL GAP ANALYSIS | C26: =CONCATENATE(VLOOKUP(exp_SILP!$B26,'DATI COMMESSE'!$A$2:$F$25,4,FALSE)," - ", VLOOKUP(exp_SILP!$B26,'DATI COMMESSE'!$A$2:$F$25,2,FALSE)," - ",VLOOKUP(exp_SILP!$B26,'DATI COMMESSE'!$A$2:$F$25,3,FALSE)) -> GOL - 22-02-5000 - 22-12-5003 | D26: =LEFT(exp_SILP!$R26,5) -> 14:00 | E26: =RIGHT(exp_SILP!$R26,5) -> 16:00 | F26: =IF(exp_SILP!$AG26>=60,exp_SILP!$AG26/60,exp_SILP!$AG26) -> 2 | G26: =VLOOKUP(exp_SILP!$Y26,'DATI CM'!$A$2:$F$28,2,FALSE) -> CSSLTZ84H70A859W | H26: =VLOOKUP(exp_SILP!$Y26,'DATI CM'!$A$2:$F$28,3,FALSE) | I26: =IF(A26>0,"N","N") -> N | J26: =VLOOKUP(exp_SILP!$Y26,'DATI CM'!$A$2:$F$28,4,FALSE) | K26: =VLOOKUP(exp_SILP!$B26,'DATI COMMESSE'!$A$2:$F$25,5,FALSE) -> 39.94 | L26: =IF(exp_SILP!$B26="A4.10 - LEP E - ORIENTAMENTO SPECIALISTICO SKILL GAP ANALYSIS - GRUPPO 3P",0,VLOOKUP(exp_SILP!$Y26,'DATI CM'!$A$2:$F$28,6,FALSE)) | M26: =IFERROR(VLOOKUP(exp_SILP!$B26,'DATI CM'!$H$2:$I$16,2,FALSE)*exp_SILP!$F26,0) -> 0 | N26: =VLOOKUP(exp_SILP!$B26,'DATI COMMESSE'!$A$2:$F$25,4,FALSE) -> GOL | O26: =VLOOKUP(exp_SILP!$B26,'DATI COMMESSE'!$A$2:$F$25,5,FALSE)*exp_SILP!$F26 -> 79.88 | P26: =IF(MID(exp_SILP!$W26,10,2)>"40","F","M") -> F | Q26: 01/06/2023 | R26: 14:00-16:00 | S26: A4.10 - LEP E - ORIENTAMENTO SPECIALISTICO SKILL GAP ANALYSIS | T26: Progetti per accreditati | V26: NGYAABER CHARITY JUNIOR | W26: NGYCRT99M41Z318B | X26: 01/08/1999 | Y26: CASSINA LETIZIA | Z26: Erogato | AA26: INFORCOOP ECIPA PIEMONTE | AB26: Incontro MDLpresentato | AC26: INFORCOOP ECIPA PIEMONTE STRADA CAMPAGNE' 7 - BIELLA | AG26: 120 | AH26: 01/06/2023 | AI26: CSSLTZ84H70A859W | AJ26: =VLOOKUP(exp_SILP!$Y26,'DATI CM'!$A$2:$F$28,2,FALSE) -> CSSLTZ84H70A859W
A27: =IFERROR(VLOOKUP(exp_SILP!$W27,exp_utenti_P!D:D,1,FALSE),"_DA INSERIRE") -> SGRSFN71H05L219A | B27: =IF(AND(exp_SILP!$S27="A.3 ORIENTAMENTO PROFESSIONALE",exp_SILP!$AD27="4.2"),"A.3 ORIENTAMENTO PROFESSIONALE (CARCERE)", IF(AND(exp_SILP!$S27="A.3 ORIENTAMENTO PROFESSIONALE",exp_SILP!$AD27="."),"A.3 ORIENTAMENTO PROFESSIONALE (CARCERE)", IF(AND(exp_SILP!$S27="A.4 CONSULENZA ORIENTATIVA",exp_SILP!$AD27="4.2"),"A.4 CONSULENZA ORIENTATIVA (CARCERE)", IF(AND(exp_SILP!$S27="A.4 CONSULENZA ORIENTATIVA",exp_SILP!$AD27="."),"A.4 CONSULENZA ORIENTATIVA (CARCERE)", IF(AND(exp_SILP!$S27="A.5 - LEP F1 - ACCOMPAGNAMENTO AL LAVORO",exp_SILP!$AD27="4.2"),"A.5 - LEP F1 - ACCOMPAGNAMENTO AL LAVORO (CARCERE)", IF(AND(exp_SILP!$S27="A.5 - LEP F1 - ACCOMPAGNAMENTO AL LAVORO",exp_SILP!$AD27="."),"A.5 - LEP F1 - ACCOMPAGNAMENTO AL LAVORO (CARCERE)", IF(AND(exp_SILP!$S27="A.5.2a - TUTORAGGIO TIROCINI",exp_SILP!$AD27="4.2"),"A.5.2a - TUTORAGGIO TIROCINI (CARCERE)", exp_SILP!$S27))))))) -> A4.10 - LEP E - ORIENTAMENTO SPECIALISTICO SKILL GAP ANALYSIS | C27: =CONCATENATE(VLOOKUP(exp_SILP!$B27,'DATI COMMESSE'!$A$2:$F$25,4,FALSE)," - ", VLOOKUP(exp_SILP!$B27,'DATI COMMESSE'!$A$2:$F$25,2,FALSE)," - ",VLOOKUP(exp_SILP!$B27,'DATI COMMESSE'!$A$2:$F$25,3,FALSE)) -> GOL - 22-02-5000 - 22-12-5003 | D27: =LEFT(exp_SILP!$R27,5) -> 16:00 | E27: =RIGHT(exp_SILP!$R27,5) -> 18:00 | F27: =IF(exp_SILP!$AG27>=60,exp_SILP!$AG27/60,exp_SILP!$AG27) -> 2 | G27: =VLOOKUP(exp_SILP!$Y27,'DATI CM'!$A$2:$F$28,2,FALSE) -> CSSLTZ84H70A859W | H27: =VLOOKUP(exp_SILP!$Y27,'DATI CM'!$A$2:$F$28,3,FALSE) | I27: =IF(A27>0,"N","N") -> N | J27: =VLOOKUP(exp_SILP!$Y27,'DATI CM'!$A$2:$F$28,4,FALSE) | K27: =VLOOKUP(exp_SILP!$B27,'DATI COMMESSE'!$A$2:$F$25,5,FALSE) -> 39.94 | L27: =IF(exp_SILP!$B27="A4.10 - LEP E - ORIENTAMENTO SPECIALISTICO SKILL GAP ANALYSIS - GRUPPO 3P",0,VLOOKUP(exp_SILP!$Y27,'DATI CM'!$A$2:$F$28,6,FALSE)) | M27: =IFERROR(VLOOKUP(exp_SILP!$B27,'DATI CM'!$H$2:$I$16,2,FALSE)*exp_SILP!$F27,0) -> 0 | N27: =VLOOKUP(exp_SILP!$B27,'DATI COMMESSE'!$A$2:$F$25,4,FALSE) -> GOL | O27: =VLOOKUP(exp_SILP!$B27,'DATI COMMESSE'!$A$2:$F$25,5,FALSE)*exp_SILP!$F27 -> 79.88 | P27: =IF(MID(exp_SILP!$W27,10,2)>"40","F","M") -> M | Q27: 01/06/2023 | R27: 16:00-18:00 | S27: A4.10 - LEP E - ORIENTAMENTO SPECIALISTICO SKILL GAP ANALYSIS | T27: Progetti per accreditati | V27: SEGRE STEFANO | W27: SGRSFN71H05L219A | X27: 05/06/1971 | Y27: CASSINA LETIZIA | Z27: Erogato | AA27: INFORCOOP ECIPA PIEMONTE | AB27: Incontro MDLpresentato | AC27: INFORCOOP ECIPA PIEMONTE STRADA CAMPAGNE' 7 - BIELLA | AG27: 120 | AH27: 01/06/2023 | AI27: CSSLTZ84H70A859W | AJ27: =VLOOKUP(exp_SILP!$Y27,'DATI CM'!$A$2:$F$28,2,FALSE) -> CSSLTZ84H70A859W
A28: =IFERROR(VLOOKUP(exp_SILP!$W28,exp_utenti_P!D:D,1,FALSE),"_DA INSERIRE") -> SRRMNC75T49H355I | B28: =IF(AND(exp_SILP!$S28="A.3 ORIENTAMENTO PROFESSIONALE",exp_SILP!$AD28="4.2"),"A.3 ORIENTAMENTO PROFESSIONALE (CARCERE)", IF(AND(exp_SILP!$S28="A.3 ORIENTAMENTO PROFESSIONALE",exp_SILP!$AD28="."),"A.3 ORIENTAMENTO PROFESSIONALE (CARCERE)", IF(AND(exp_SILP!$S28="A.4 CONSULENZA ORIENTATIVA",exp_SILP!$AD28="4.2"),"A.4 CONSULENZA ORIENTATIVA (CARCERE)", IF(AND(exp_SILP!$S28="A.4 CONSULENZA ORIENTATIVA",exp_SILP!$AD28="."),"A.4 CONSULENZA ORIENTATIVA (CARCERE)", IF(AND(exp_SILP!$S28="A.5 - LEP F1 - ACCOMPAGNAMENTO AL LAVORO",exp_SILP!$AD28="4.2"),"A.5 - LEP F1 - ACCOMPAGNAMENTO AL LAVORO (CARCERE)", IF(AND(exp_SILP!$S28="A.5 - LEP F1 - ACCOMPAGNAMENTO AL LAVORO",exp_SILP!$AD28="."),"A.5 - LEP F1 - ACCOMPAGNAMENTO AL LAVORO (CARCERE)", IF(AND(exp_SILP!$S28="A.5.2a - TUTORAGGIO TIROCINI",exp_SILP!$AD28="4.2"),"A.5.2a - TUTORAGGIO TIROCINI (CARCERE)", exp_SILP!$S28))))))) -> A4.10 - LEP E - ORIENTAMENTO SPECIALISTICO SKILL GAP ANALYSIS | C28: =CONCATENATE(VLOOKUP(exp_SILP!$B28,'DATI COMMESSE'!$A$2:$F$25,4,FALSE)," - ", VLOOKUP(exp_SILP!$B28,'DATI COMMESSE'!$A$2:$F$25,2,FALSE)," - ",VLOOKUP(exp_SILP!$B28,'DATI COMMESSE'!$A$2:$F$25,3,FALSE)) -> GOL - 22-02-5000 - 22-12-5003 | D28: =LEFT(exp_SILP!$R28,5) -> 14:00 | E28: =RIGHT(exp_SILP!$R28,5) -> 16:00 | F28: =IF(exp_SILP!$AG28>=60,exp_SILP!$AG28/60,exp_SILP!$AG28) -> 2 | G28: =VLOOKUP(exp_SILP!$Y28,'DATI CM'!$A$2:$F$28,2,FALSE) -> MNRCLD73B46G674U | H28: =VLOOKUP(exp_SILP!$Y28,'DATI CM'!$A$2:$F$28,3,FALSE) -> A011 | I28: =IF(A28>0,"N","N") -> N | J28: =VLOOKUP(exp_SILP!$Y28,'DATI CM'!$A$2:$F$28,4,FALSE) -> TORINO | K28: =VLOOKUP(exp_SILP!$B28,'DATI COMMESSE'!$A$2:$F$25,5,FALSE) -> 39.94 | L28: =IF(exp_SILP!$B28="A4.10 - LEP E - ORIENTAMENTO SPECIALISTICO SKILL GAP ANALYSIS - GRUPPO 3P",0,VLOOKUP(exp_SILP!$Y28,'DATI CM'!$A$2:$F$28,6,FALSE)) -> 25 | M28: =IFERROR(VLOOKUP(exp_SILP!$B28,'DATI CM'!$H$2:$I$16,2,FALSE)*exp_SILP!$F28,0) -> 0 | N28: =VLOOKUP(exp_SILP!$B28,'DATI COMMESSE'!$A$2:$F$25,4,FALSE) -> GOL | O28: =VLOOKUP(exp_SILP!$B28,'DATI COMMESSE'!$A$2:$F$25,5,FALSE)*exp_SILP!$F28 -> 79.88 | P28: =IF(MID(exp_SILP!$W28,10,2)>"40","F","M") -> F | Q28: 01/06/2023 | R28: 14:00-16:00 | S28: A4.10 - LEP E - ORIENTAMENTO SPECIALISTICO SKILL GAP ANALYSIS | T28: Progetti per accreditati | V28: SERRA MONICA | W28: SRRMNC75T49H355I | X28: 09/12/1975 | Y28: MAINERO CLAUDIA | Z28: Erogato | AA28: INFORCOOP ECIPA PIEMONTE | AB28: Incontro MDLpresentato | AC28: INFORCOOP ECIPA PIEMONTE VIA TREVISO 12 - TORINO | AG28: 120 | AH28: 07/06/2023 | AI28: MNRCLD73B46G674U | AJ28: =VLOOKUP(exp_SILP!$Y28,'DATI CM'!$A$2:$F$28,2,FALSE) -> MNRCLD73B46G674U
A29: =IFERROR(VLOOKUP(exp_SILP!$W29,exp_utenti_P!D:D,1,FALSE),"_DA INSERIRE") -> NGNVRD71R65F205Q | B29: =IF(AND(exp_SILP!$S29="A.3 ORIENTAMENTO PROFESSIONALE",exp_SILP!$AD29="4.2"),"A.3 ORIENTAMENTO PROFESSIONALE (CARCERE)", IF(AND(exp_SILP!$S29="A.3 ORIENTAMENTO PROFESSIONALE",exp_SILP!$AD29="."),"A.3 ORIENTAMENTO PROFESSIONALE (CARCERE)", IF(AND(exp_SILP!$S29="A.4 CONSULENZA ORIENTATIVA",exp_SILP!$AD29="4.2"),"A.4 CONSULENZA ORIENTATIVA (CARCERE)", IF(AND(exp_SILP!$S29="A.4 CONSULENZA ORIENTATIVA",exp_SILP!$AD29="."),"A.4 CONSULENZA ORIENTATIVA (CARCERE)", IF(AND(exp_SILP!$S29="A.5 - LEP F1 - ACCOMPAGNAMENTO AL LAVORO",exp_SILP!$AD29="4.2"),"A.5 - LEP F1 - ACCOMPAGNAMENTO AL LAVORO (CARCERE)", IF(AND(exp_SILP!$S29="A.5 - LEP F1 - ACCOMPAGNAMENTO AL LAVORO",exp_SILP!$AD29="."),"A.5 - LEP F1 - ACCOMPAGNAMENTO AL LAVORO (CARCERE)", IF(AND(exp_SILP!$S29="A.5.2a - TUTORAGGIO TIROCINI",exp_SILP!$AD29="4.2"),"A.5.2a - TUTORAGGIO TIROCINI (CARCERE)", exp_SILP!$S29))))))) -> A4.10 - LEP E - ORIENTAMENTO SPECIALISTICO SKILL GAP ANALYSIS | C29: =CONCATENATE(VLOOKUP(exp_SILP!$B29,'DATI COMMESSE'!$A$2:$F$25,4,FALSE)," - ", VLOOKUP(exp_SILP!$B29,'DATI COMMESSE'!$A$2:$F$25,2,FALSE)," - ",VLOOKUP(exp_SILP!$B29,'DATI COMMESSE'!$A$2:$F$25,3,FALSE)) -> GOL - 22-02-5000 - 22-12-5003 | D29: =LEFT(exp_SILP!$R29,5) -> 14:00 | E29: =RIGHT(exp_SILP!$R29,5) -> 15:00 | F29: =IF(exp_SILP!$AG29>=60,exp_SILP!$AG29/60,exp_SILP!$AG29) -> 1 | G29: =VLOOKUP(exp_SILP!$Y29,'DATI CM'!$A$2:$F$28,2,FALSE) -> SPDPRZ67H55L219V | H29: =VLOOKUP(exp_SILP!$Y29,'DATI CM'!$A$2:$F$28,3,FALSE) -> A010 | I29: =IF(A29>0,"N","N") -> N | J29: =VLOOKUP(exp_SILP!$Y29,'DATI CM'!$A$2:$F$28,4,FALSE) -> TORINO | K29: =VLOOKUP(exp_SILP!$B29,'DATI COMMESSE'!$A$2:$F$25,5,FALSE) -> 39.94 | L29: =IF(exp_SILP!$B29="A4.10 - LEP E - ORIENTAMENTO SPECIALISTICO SKILL GAP ANALYSIS - GRUPPO 3P",0,VLOOKUP(exp_SILP!$Y29,'DATI CM'!$A$2:$F$28,6,FALSE)) | M29: =IFERROR(VLOOKUP(exp_SILP!$B29,'DATI CM'!$H$2:$I$16,2,FALSE)*exp_SILP!$F29,0) -> 0 | N29: =VLOOKUP(exp_SILP!$B29,'DATI COMMESSE'!$A$2:$F$25,4,FALSE) -> GOL | O29: =VLOOKUP(exp_SILP!$B29,'DATI COMMESSE'!$A$2:$F$25,5,FALSE)*exp_SILP!$F29 -> 39.94 | P29: =IF(MID(exp_SILP!$W29,10,2)>"40","F","M") -> F | Q29: 01/09/2023 | R29: 14:00-15:00 | S29: A4.10 - LEP E - ORIENTAMENTO SPECIALISTICO SKILL GAP ANALYSIS | T29: Progetti per accreditati | V29: ANGIONE VALERIA ODES | W29: NGNVRD71R65F205Q | X29: 25/10/1971 | Y29: SPADARO PATRIZIA | Z29: Erogato | AA29: INFORCOOP ECIPA PIEMONTE | AB29: Incontro MDL | AC29: INFORCOOP ECIPA PIEMONTE VIA UGO PORZIO GIOVANOLA 7 - NOVARA | AG29: 60 | AH29: 01/09/2023 | AI29: SPDPRZ67H55L219V | AJ29: =VLOOKUP(exp_SILP!$Y29,'DATI CM'!$A$2:$F$28,2,FALSE) -> SPDPRZ67H55L219V
A30: =IFERROR(VLOOKUP(exp_SILP!$W30,exp_utenti_P!D:D,1,FALSE),"_DA INSERIRE") -> DRDCST73R54F952M | B30: =IF(AND(exp_SILP!$S30="A.3 ORIENTAMENTO PROFESSIONALE",exp_SILP!$AD30="4.2"),"A.3 ORIENTAMENTO PROFESSIONALE (CARCERE)", IF(AND(exp_SILP!$S30="A.3 ORIENTAMENTO PROFESSIONALE",exp_SILP!$AD30="."),"A.3 ORIENTAMENTO PROFESSIONALE (CARCERE)", IF(AND(exp_SILP!$S30="A.4 CONSULENZA ORIENTATIVA",exp_SILP!$AD30="4.2"),"A.4 CONSULENZA ORIENTATIVA (CARCERE)", IF(AND(exp_SILP!$S30="A.4 CONSULENZA ORIENTATIVA",exp_SILP!$AD30="."),"A.4 CONSULENZA ORIENTATIVA (CARCERE)", IF(AND(exp_SILP!$S30="A.5 - LEP F1 - ACCOMPAGNAMENTO AL LAVORO",exp_SILP!$AD30="4.2"),"A.5 - LEP F1 - ACCOMPAGNAMENTO AL LAVORO (CARCERE)", IF(AND(exp_SILP!$S30="A.5 - LEP F1 - ACCOMPAGNAMENTO AL LAVORO",exp_SILP!$AD30="."),"A.5 - LEP F1 - ACCOMPAGNAMENTO AL LAVORO (CARCERE)", IF(AND(exp_SILP!$S30="A.5.2a - TUTORAGGIO TIROCINI",exp_SILP!$AD30="4.2"),"A.5.2a - TUTORAGGIO TIROCINI (CARCERE)", exp_SILP!$S30))))))) -> A.5 - LEP F1 - ACCOMPAGNAMENTO AL LAVORO | C30: =CONCATENATE(VLOOKUP(exp_SILP!$B30,'DATI COMMESSE'!$A$2:$F$25,4,FALSE)," - ", VLOOKUP(exp_SILP!$B30,'DATI COMMESSE'!$A$2:$F$25,2,FALSE)," - ",VLOOKUP(exp_SILP!$B30,'DATI COMMESSE'!$A$2:$F$25,3,FALSE)) -> GOL - 22-02-5000 - 22-12-5003 | D30: =LEFT(exp_SILP!$R30,5) -> 13:00 | E30: =RIGHT(exp_SILP!$R30,5) -> 15:00 | F30: =IF(exp_SILP!$AG30>=60,exp_SILP!$AG30/60,exp_SILP!$AG30) -> 2 | G30: =VLOOKUP(exp_SILP!$Y30,'DATI CM'!$A$2:$F$28,2,FALSE) -> RSCDAA66H43F952Q | H30: =VLOOKUP(exp_SILP!$Y30,'DATI CM'!$A$2:$F$28,3,FALSE) -> A011 | I30: =IF(A30>0,"N","N") -> N | J30: =VLOOKUP(exp_SILP!$Y30,'DATI CM'!$A$2:$F$28,4,FALSE) -> NO | K30: =VLOOKUP(exp_SILP!$B30,'DATI COMMESSE'!$A$2:$F$25,5,FALSE) -> 39.94 | L30: =IF(exp_SILP!$B30="A4.10 - LEP E - ORIENTAMENTO SPECIALISTICO SKILL GAP ANALYSIS - GRUPPO 3P",0,VLOOKUP(exp_SILP!$Y30,'DATI CM'!$A$2:$F$28,6,FALSE)) -> 25 | M30: =IFERROR(VLOOKUP(exp_SILP!$B30,'DATI CM'!$H$2:$I$16,2,FALSE)*exp_SILP!$F30,0) -> 0 | N30: =VLOOKUP(exp_SILP!$B30,'DATI COMMESSE'!$A$2:$F$25,4,FALSE) -> GOL | O30: =VLOOKUP(exp_SILP!$B30,'DATI COMMESSE'!$A$2:$F$25,5,FALSE)*exp_SILP!$F30 -> 79.88 | P30: =IF(MID(exp_SILP!$W30,10,2)>"40","F","M") -> F | Q30: 01/12/2023 | R30: 13:00-15:00 | S30: A.5 - LEP F1 - ACCOMPAGNAMENTO AL LAVORO | T30: Progetti per accreditati | V30: DARDANO CRISTINA | W30: DRDCST73R54F952M | X30: 14/10/1973 | Y30: RUSCA ADA | Z30: Erogato | AA30: INFORCOOP ECIPA PIEMONTE | AB30: Incontro MDL | AC30: INFORCOOP ECIPA PIEMONTE VIA UGO PORZIO GIOVANOLA 7 - NOVARA | AG30: 120 | AH30: 19/12/2023 | AI30: RSCDAA66H43F952Q | AJ30: =VLOOKUP(exp_SILP!$Y30,'DATI CM'!$A$2:$F$28,2,FALSE) -> RSCDAA66H43F952Q
A31: =IFERROR(VLOOKUP(exp_SILP!$W31,exp_utenti_P!D:D,1,FALSE),"_DA INSERIRE") -> CRDGLI96M63L219N | B31: =IF(AND(exp_SILP!$S31="A.3 ORIENTAMENTO PROFESSIONALE",exp_SILP!$AD31="4.2"),"A.3 ORIENTAMENTO PROFESSIONALE (CARCERE)", IF(AND(exp_SILP!$S31="A.3 ORIENTAMENTO PROFESSIONALE",exp_SILP!$AD31="."),"A.3 ORIENTAMENTO PROFESSIONALE (CARCERE)", IF(AND(exp_SILP!$S31="A.4 CONSULENZA ORIENTATIVA",exp_SILP!$AD31="4.2"),"A.4 CONSULENZA ORIENTATIVA (CARCERE)", IF(AND(exp_SILP!$S31="A.4 CONSULENZA ORIENTATIVA",exp_SILP!$AD31="."),"A.4 CONSULENZA ORIENTATIVA (CARCERE)", IF(AND(exp_SILP!$S31="A.5 - LEP F1 - ACCOMPAGNAMENTO AL LAVORO",exp_SILP!$AD31="4.2"),"A.5 - LEP F1 - ACCOMPAGNAMENTO AL LAVORO (CARCERE)", IF(AND(exp_SILP!$S31="A.5 - LEP F1 - ACCOMPAGNAMENTO AL LAVORO",exp_SILP!$AD31="."),"A.5 - LEP F1 - ACCOMPAGNAMENTO AL LAVORO (CARCERE)", IF(AND(exp_SILP!$S31="A.5.2a - TUTORAGGIO TIROCINI",exp_SILP!$AD31="4.2"),"A.5.2a - TUTORAGGIO TIROCINI (CARCERE)", exp_SILP!$S31))))))) -> A.5 - LEP F1 - ACCOMPAGNAMENTO AL LAVORO | C31: =CONCATENATE(VLOOKUP(exp_SILP!$B31,'DATI COMMESSE'!$A$2:$F$25,4,FALSE)," - ", VLOOKUP(exp_SILP!$B31,'DATI COMMESSE'!$A$2:$F$25,2,FALSE)," - ",VLOOKUP(exp_SILP!$B31,'DATI COMMESSE'!$A$2:$F$25,3,FALSE)) -> GOL - 22-02-5000 - 22-12-5003 | D31: =LEFT(exp_SILP!$R31,5) -> 10:00 | E31: =RIGHT(exp_SILP!$R31,5) -> 12:00 | F31: =IF(exp_SILP!$AG31>=60,exp_SILP!$AG31/60,exp_SILP!$AG31) -> 2 | G31: =VLOOKUP(exp_SILP!$Y31,'DATI CM'!$A$2:$F$28,2,FALSE) -> FLCSRN79S42L219X | H31: =VLOOKUP(exp_SILP!$Y31,'DATI CM'!$A$2:$F$28,3,FALSE) -> A011 | I31: =IF(A31>0,"N","N") -> N | J31: =VLOOKUP(exp_SILP!$Y31,'DATI CM'!$A$2:$F$28,4,FALSE) -> TORINO | K31: =VLOOKUP(exp_SILP!$B31,'DATI COMMESSE'!$A$2:$F$25,5,FALSE) -> 39.94 | L31: =IF(exp_SILP!$B31="A4.10 - LEP E - ORIENTAMENTO SPECIALISTICO SKILL GAP ANALYSIS - GRUPPO 3P",0,VLOOKUP(exp_SILP!$Y31,'DATI CM'!$A$2:$F$28,6,FALSE)) -> 25 | M31: =IFERROR(VLOOKUP(exp_SILP!$B31,'DATI CM'!$H$2:$I$16,2,FALSE)*exp_SILP!$F31,0) -> 0 | N31: =VLOOKUP(exp_SILP!$B31,'DATI COMMESSE'!$A$2:$F$25,4,FALSE) -> GOL | O31: =VLOOKUP(exp_SILP!$B31,'DATI COMMESSE'!$A$2:$F$25,5,FALSE)*exp_SILP!$F31 -> 79.88 | P31: =IF(MID(exp_SILP!$W31,10,2)>"40","F","M") -> F | Q31: 01/12/2023 | R31: 10:00-12:00 | S31: A.5 - LEP F1 - ACCOMPAGNAMENTO AL LAVORO | T31: Progetti per accreditati | V31: CARDELLA GIULIA | W31: CRDGLI96M63L219N | X31: 23/08/1996 | Y31: FALCONE SERENA | Z31: Erogato | AA31: INFORCOOP ECIPA PIEMONTE | AB31: Incontro MDLpresentato | AC31: INFORCOOP ECIPA PIEMONTE VIA LIVORNO 53/b - TORINO | AG31: 120 | AH31: 01/12/2023 | AI31: FLCSRN79S42L219X | AJ31: =VLOOKUP(exp_SILP!$Y31,'DATI CM'!$A$2:$F$28,2,FALSE) -> FLCSRN79S42L219X
A32: =IFERROR(VLOOKUP(exp_SILP!$W32,exp_utenti_P!D:D,1,FALSE),"_DA INSERIRE") -> DDMLCN64T02F205O | B32: =IF(AND(exp_SILP!$S32="A.3 ORIENTAMENTO PROFESSIONALE",exp_SILP!$AD32="4.2"),"A.3 ORIENTAMENTO PROFESSIONALE (CARCERE)", IF(AND(exp_SILP!$S32="A.3 ORIENTAMENTO PROFESSIONALE",exp_SILP!$AD32="."),"A.3 ORIENTAMENTO PROFESSIONALE (CARCERE)", IF(AND(exp_SILP!$S32="A.4 CONSULENZA ORIENTATIVA",exp_SILP!$AD32="4.2"),"A.4 CONSULENZA ORIENTATIVA (CARCERE)", IF(AND(exp_SILP!$S32="A.4 CONSULENZA ORIENTATIVA",exp_SILP!$AD32="."),"A.4 CONSULENZA ORIENTATIVA (CARCERE)", IF(AND(exp_SILP!$S32="A.5 - LEP F1 - ACCOMPAGNAMENTO AL LAVORO",exp_SILP!$AD32="4.2"),"A.5 - LEP F1 - ACCOMPAGNAMENTO AL LAVORO (CARCERE)", IF(AND(exp_SILP!$S32="A.5 - LEP F1 - ACCOMPAGNAMENTO AL LAVORO",exp_SILP!$AD32="."),"A.5 - LEP F1 - ACCOMPAGNAMENTO AL LAVORO (CARCERE)", IF(AND(exp_SILP!$S32="A.5.2a - TUTORAGGIO TIROCINI",exp_SILP!$AD32="4.2"),"A.5.2a - TUTORAGGIO TIROCINI (CARCERE)", exp_SILP!$S32))))))) -> A.5 - LEP F1 - ACCOMPAGNAMENTO AL LAVORO | C32: =CONCATENATE(VLOOKUP(exp_SILP!$B32,'DATI COMMESSE'!$A$2:$F$25,4,FALSE)," - ", VLOOKUP(exp_SILP!$B32,'DATI COMMESSE'!$A$2:$F$25,2,FALSE)," - ",VLOOKUP(exp_SILP!$B32,'DATI COMMESSE'!$A$2:$F$25,3,FALSE)) -> GOL - 22-02-5000 - 22-12-5003 | D32: =LEFT(exp_SILP!$R32,5) -> 09:00 | E32: =RIGHT(exp_SILP!$R32,5) -> 10:00 | F32: =IF(exp_SILP!$AG32>=60,exp_SILP!$AG32/60,exp_SILP!$AG32) -> 1 | G32: =VLOOKUP(exp_SILP!$Y32,'DATI CM'!$A$2:$F$28,2,FALSE) -> PNFMRT85H50A859E | H32: =VLOOKUP(exp_SILP!$Y32,'DATI CM'!$A$2:$F$28,3,FALSE) -> A011 | I32: =IF(A32>0,"N","N") -> N | J32: =VLOOKUP(exp_SILP!$Y32,'DATI CM'!$A$2:$F$28,4,FALSE) -> BIELLA | K32: =VLOOKUP(exp_SILP!$B32,'DATI COMMESSE'!$A$2:$F$25,5,FALSE) -> 39.94 | L32: =IF(exp_SILP!$B32="A4.10 - LEP E - ORIENTAMENTO SPECIALISTICO SKILL GAP ANALYSIS - GRUPPO 3P",0,VLOOKUP(exp_SILP!$Y32,'DATI CM'!$A$2:$F$28,6,FALSE)) -> 25 | M32: =IFERROR(VLOOKUP(exp_SILP!$B32,'DATI CM'!$H$2:$I$16,2,FALSE)*exp_SILP!$F32,0) -> 0 | N32: =VLOOKUP(exp_SILP!$B32,'DATI COMMESSE'!$A$2:$F$25,4,FALSE) -> GOL | O32: =VLOOKUP(exp_SILP!$B32,'DATI COMMESSE'!$A$2:$F$25,5,FALSE)*exp_SILP!$F32 -> 39.94 | P32: =IF(MID(exp_SILP!$W32,10,2)>"40","F","M") -> M | Q32: 01/12/2023 | R32: 09:00-10:00 | S32: A.5 - LEP F1 - ACCOMPAGNAMENTO AL LAVORO | T32: Progetti per accreditati | V32: DI DOMENICO LUCIANO | W32: DDMLCN64T02F205O | X32: 02/12/1964 | Y32: PIANOFORTE MARTA | Z32: Erogato | AA32: INFORCOOP ECIPA PIEMONTE | AB32: Incontro MDL | AC32: INFORCOOP ECIPA PIEMONTE STRADA CAMPAGNE' 7 - BIELLA | AG32: 60 | AH32: 04/12/2023 | AI32: PNFMRT85H50A859E | AJ32: =VLOOKUP(exp_SILP!$Y32,'DATI CM'!$A$2:$F$28,2,FALSE) -> PNFMRT85H50A859E
A33: =IFERROR(VLOOKUP(exp_SILP!$W33,exp_utenti_P!D:D,1,FALSE),"_DA INSERIRE") -> FLMBBR76L41L219Z | B33: =IF(AND(exp_SILP!$S33="A.3 ORIENTAMENTO PROFESSIONALE",exp_SILP!$AD33="4.2"),"A.3 ORIENTAMENTO PROFESSIONALE (CARCERE)", IF(AND(exp_SILP!$S33="A.3 ORIENTAMENTO PROFESSIONALE",exp_SILP!$AD33="."),"A.3 ORIENTAMENTO PROFESSIONALE (CARCERE)", IF(AND(exp_SILP!$S33="A.4 CONSULENZA ORIENTATIVA",exp_SILP!$AD33="4.2"),"A.4 CONSULENZA ORIENTATIVA (CARCERE)", IF(AND(exp_SILP!$S33="A.4 CONSULENZA ORIENTATIVA",exp_SILP!$AD33="."),"A.4 CONSULENZA ORIENTATIVA (CARCERE)", IF(AND(exp_SILP!$S33="A.5 - LEP F1 - ACCOMPAGNAMENTO AL LAVORO",exp_SILP!$AD33="4.2"),"A.5 - LEP F1 - ACCOMPAGNAMENTO AL LAVORO (CARCERE)", IF(AND(exp_SILP!$S33="A.5 - LEP F1 - ACCOMPAGNAMENTO AL LAVORO",exp_SILP!$AD33="."),"A.5 - LEP F1 - ACCOMPAGNAMENTO AL LAVORO (CARCERE)", IF(AND(exp_SILP!$S33="A.5.2a - TUTORAGGIO TIROCINI",exp_SILP!$AD33="4.2"),"A.5.2a - TUTORAGGIO TIROCINI (CARCERE)", exp_SILP!$S33))))))) -> A.5 - LEP F1 - ACCOMPAGNAMENTO AL LAVORO | C33: =CONCATENATE(VLOOKUP(exp_SILP!$B33,'DATI COMMESSE'!$A$2:$F$25,4,FALSE)," - ", VLOOKUP(exp_SILP!$B33,'DATI COMMESSE'!$A$2:$F$25,2,FALSE)," - ",VLOOKUP(exp_SILP!$B33,'DATI COMMESSE'!$A$2:$F$25,3,FALSE)) -> GOL - 22-02-5000 - 22-12-5003 | D33: =LEFT(exp_SILP!$R33,5) -> 14:00 | E33: =RIGHT(exp_SILP!$R33,5) -> 15:00 | F33: =IF(exp_SILP!$AG33>=60,exp_SILP!$AG33/60,exp_SILP!$AG33) -> 1 | G33: =VLOOKUP(exp_SILP!$Y33,'DATI CM'!$A$2:$F$28,2,FALSE) -> FLCSRN79S42L219X | H33: =VLOOKUP(exp_SILP!$Y33,'DATI CM'!$A$2:$F$28,3,FALSE) -> A011 | I33: =IF(A33>0,"N","N") -> N | J33: =VLOOKUP(exp_SILP!$Y33,'DATI CM'!$A$2:$F$28,4,FALSE) -> TORINO | K33: =VLOOKUP(exp_SILP!$B33,'DATI COMMESSE'!$A$2:$F$25,5,FALSE) -> 39.94 | L33: =IF(exp_SILP!$B33="A4.10 - LEP E - ORIENTAMENTO SPECIALISTICO SKILL GAP ANALYSIS - GRUPPO 3P",0,VLOOKUP(exp_SILP!$Y33,'DATI CM'!$A$2:$F$28,6,FALSE)) -> 25 | M33: =IFERROR(VLOOKUP(exp_SILP!$B33,'DATI CM'!$H$2:$I$16,2,FALSE)*exp_SILP!$F33,0) -> 0 | N33: =VLOOKUP(exp_SILP!$B33,'DATI COMMESSE'!$A$2:$F$25,4,FALSE) -> GOL | O33: =VLOOKUP(exp_SILP!$B33,'DATI COMMESSE'!$A$2:$F$25,5,FALSE)*exp_SILP!$F33 -> 39.94 | P33: =IF(MID(exp_SILP!$W33,10,2)>"40","F","M") -> F | Q33: 01/12/2023 | R33: 14:00-15:00 | S33: A.5 - LEP F1 - ACCOMPAGNAMENTO AL LAVORO | T33: Progetti per accreditati | V33: FLAMANO BARBARA | W33: FLMBBR76L41L219Z | X33: 01/07/1976 | Y33: FALCONE SERENA | Z33: Erogato | AA33: INFORCOOP ECIPA PIEMONTE | AB33: Incontro MDL | AC33: INFORCOOP ECIPA PIEMONTE VIA LIVORNO 53/b - TORINO | AF33: BO | AG33: 60 | AH33: 02/12/2023 | AI33: FLCSRN79S42L219X | AJ33: =VLOOKUP(exp_SILP!$Y33,'DATI CM'!$A$2:$F$28,2,FALSE) -> FLCSRN79S42L219X
A34: =IFERROR(VLOOKUP(exp_SILP!$W34,exp_utenti_P!D:D,1,FALSE),"_DA INSERIRE") -> FLMBBR76L41L219Z | B34: =IF(AND(exp_SILP!$S34="A.3 ORIENTAMENTO PROFESSIONALE",exp_SILP!$AD34="4.2"),"A.3 ORIENTAMENTO PROFESSIONALE (CARCERE)", IF(AND(exp_SILP!$S34="A.3 ORIENTAMENTO PROFESSIONALE",exp_SILP!$AD34="."),"A.3 ORIENTAMENTO PROFESSIONALE (CARCERE)", IF(AND(exp_SILP!$S34="A.4 CONSULENZA ORIENTATIVA",exp_SILP!$AD34="4.2"),"A.4 CONSULENZA ORIENTATIVA (CARCERE)", IF(AND(exp_SILP!$S34="A.4 CONSULENZA ORIENTATIVA",exp_SILP!$AD34="."),"A.4 CONSULENZA ORIENTATIVA (CARCERE)", IF(AND(exp_SILP!$S34="A.5 - LEP F1 - ACCOMPAGNAMENTO AL LAVORO",exp_SILP!$AD34="4.2"),"A.5 - LEP F1 - ACCOMPAGNAMENTO AL LAVORO (CARCERE)", IF(AND(exp_SILP!$S34="A.5 - LEP F1 - ACCOMPAGNAMENTO AL LAVORO",exp_SILP!$AD34="."),"A.5 - LEP F1 - ACCOMPAGNAMENTO AL LAVORO (CARCERE)", IF(AND(exp_SILP!$S34="A.5.2a - TUTORAGGIO TIROCINI",exp_SILP!$AD34="4.2"),"A.5.2a - TUTORAGGIO TIROCINI (CARCERE)", exp_SILP!$S34))))))) -> A.5 - LEP F1 - ACCOMPAGNAMENTO AL LAVORO | C34: =CONCATENATE(VLOOKUP(exp_SILP!$B34,'DATI COMMESSE'!$A$2:$F$25,4,FALSE)," - ", VLOOKUP(exp_SILP!$B34,'DATI COMMESSE'!$A$2:$F$25,2,FALSE)," - ",VLOOKUP(exp_SILP!$B34,'DATI COMMESSE'!$A$2:$F$25,3,FALSE)) -> GOL - 22-02-5000 - 22-12-5003 | D34: =LEFT(exp_SILP!$R34,5) -> 12:00 | E34: =RIGHT(exp_SILP!$R34,5) -> 14:00 | F34: =IF(exp_SILP!$AG34>=60,exp_SILP!$AG34/60,exp_SILP!$AG34) -> 2 | G34: =VLOOKUP(exp_SILP!$Y34,'DATI CM'!$A$2:$F$28,2,FALSE) -> FLCSRN79S42L219X | H34: =VLOOKUP(exp_SILP!$Y34,'DATI CM'!$A$2:$F$28,3,FALSE) -> A011 | I34: =IF(A34>0,"N","N") -> N | J34: =VLOOKUP(exp_SILP!$Y34,'DATI CM'!$A$2:$F$28,4,FALSE) -> TORINO | K34: =VLOOKUP(exp_SILP!$B34,'DATI COMMESSE'!$A$2:$F$25,5,FALSE) -> 39.94 | L34: =IF(exp_SILP!$B34="A4.10 - LEP E - ORIENTAMENTO SPECIALISTICO SKILL GAP ANALYSIS - GRUPPO 3P",0,VLOOKUP(exp_SILP!$Y34,'DATI CM'!$A$2:$F$28,6,FALSE)) -> 25 | M34: =IFERROR(VLOOKUP(exp_SILP!$B34,'DATI CM'!$H$2:$I$16,2,FALSE)*exp_SILP!$F34,0) -> 0 | N34: =VLOOKUP(exp_SILP!$B34,'DATI COMMESSE'!$A$2:$F$25,4,FALSE) -> GOL | O34: =VLOOKUP(exp_SILP!$B34,'DATI COMMESSE'!$A$2:$F$25,5,FALSE)*exp_SILP!$F34 -> 79.88 | P34: =IF(MID(exp_SILP!$W34,10,2)>"40","F","M") -> F | Q34: 01/12/2023 | R34: 12:00-14:00 | S34: A.5 - LEP F1 - ACCOMPAGNAMENTO AL LAVORO | T34: Progetti per accreditati | V34: FLAMANO BARBARA | W34: FLMBBR76L41L219Z | X34: 01/07/1976 | Y34: FALCONE SERENA | Z34: Erogato | AA34: INFORCOOP ECIPA PIEMONTE | AB34: Incontro MDLpresentato | AC34: INFORCOOP ECIPA PIEMONTE VIA LIVORNO 53/b - TORINO | AG34: 120 | AH34: 01/12/2023 | AI34: FLCSRN79S42L219X | AJ34: =VLOOKUP(exp_SILP!$Y34,'DATI CM'!$A$2:$F$28,2,FALSE) -> FLCSRN79S42L219X
A35: =IFERROR(VLOOKUP(exp_SILP!$W35,exp_utenti_P!D:D,1,FALSE),"_DA INSERIRE") -> DLGMRN96M49A859Z | B35: =IF(AND(exp_SILP!$S35="A.3 ORIENTAMENTO PROFESSIONALE",exp_SILP!$AD35="4.2"),"A.3 ORIENTAMENTO PROFESSIONALE (CARCERE)", IF(AND(exp_SILP!$S35="A.3 ORIENTAMENTO PROFESSIONALE",exp_SILP!$AD35="."),"A.3 ORIENTAMENTO PROFESSIONALE (CARCERE)", IF(AND(exp_SILP!$S35="A.4 CONSULENZA ORIENTATIVA",exp_SILP!$AD35="4.2"),"A.4 CONSULENZA ORIENTATIVA (CARCERE)", IF(AND(exp_SILP!$S35="A.4 CONSULENZA ORIENTATIVA",exp_SILP!$AD35="."),"A.4 CONSULENZA ORIENTATIVA (CARCERE)", IF(AND(exp_SILP!$S35="A.5 - LEP F1 - ACCOMPAGNAMENTO AL LAVORO",exp_SILP!$AD35="4.2"),"A.5 - LEP F1 - ACCOMPAGNAMENTO AL LAVORO (CARCERE)", IF(AND(exp_SILP!$S35="A.5 - LEP F1 - ACCOMPAGNAMENTO AL LAVORO",exp_SILP!$AD35="."),"A.5 - LEP F1 - ACCOMPAGNAMENTO AL LAVORO (CARCERE)", IF(AND(exp_SILP!$S35="A.5.2a - TUTORAGGIO TIROCINI",exp_SILP!$AD35="4.2"),"A.5.2a - TUTORAGGIO TIROCINI (CARCERE)", exp_SILP!$S35))))))) -> A4.10 - LEP E - ORIENTAMENTO SPECIALISTICO SKILL GAP ANALYSIS | C35: =CONCATENATE(VLOOKUP(exp_SILP!$B35,'DATI COMMESSE'!$A$2:$F$25,4,FALSE)," - ", VLOOKUP(exp_SILP!$B35,'DATI COMMESSE'!$A$2:$F$25,2,FALSE)," - ",VLOOKUP(exp_SILP!$B35,'DATI COMMESSE'!$A$2:$F$25,3,FALSE)) -> GOL - 22-02-5000 - 22-12-5003 | D35: =LEFT(exp_SILP!$R35,5) -> 10:00 | E35: =RIGHT(exp_SILP!$R35,5) -> 11:00 | F35: =IF(exp_SILP!$AG35>=60,exp_SILP!$AG35/60,exp_SILP!$AG35) -> 1 | G35: =VLOOKUP(exp_SILP!$Y35,'DATI CM'!$A$2:$F$28,2,FALSE) -> PNFMRT85H50A859E | H35: =VLOOKUP(exp_SILP!$Y35,'DATI CM'!$A$2:$F$28,3,FALSE) -> A011 | I35: =IF(A35>0,"N","N") -> N | J35: =VLOOKUP(exp_SILP!$Y35,'DATI CM'!$A$2:$F$28,4,FALSE) -> BIELLA | K35: =VLOOKUP(exp_SILP!$B35,'DATI COMMESSE'!$A$2:$F$25,5,FALSE) -> 39.94 | L35: =IF(exp_SILP!$B35="A4.10 - LEP E - ORIENTAMENTO SPECIALISTICO SKILL GAP ANALYSIS - GRUPPO 3P",0,VLOOKUP(exp_SILP!$Y35,'DATI CM'!$A$2:$F$28,6,FALSE)) -> 25 | M35: =IFERROR(VLOOKUP(exp_SILP!$B35,'DATI CM'!$H$2:$I$16,2,FALSE)*exp_SILP!$F35,0) -> 0 | N35: =VLOOKUP(exp_SILP!$B35,'DATI COMMESSE'!$A$2:$F$25,4,FALSE) -> GOL | O35: =VLOOKUP(exp_SILP!$B35,'DATI COMMESSE'!$A$2:$F$25,5,FALSE)*exp_SILP!$F35 -> 39.94 | P35: =IF(MID(exp_SILP!$W35,10,2)>"40","F","M") -> F | Q35: 01/12/2023 | R35: 10:00-11:00 | S35: A4.10 - LEP E - ORIENTAMENTO SPECIALISTICO SKILL GAP ANALYSIS | T35: Progetti per accreditati | V35: DEL GROSSO MIRIANA | W35: DLGMRN96M49A859Z | X35: 09/08/1996 | Y35: PIANOFORTE MARTA | Z35: Erogato | AA35: INFORCOOP ECIPA PIEMONTE | AB35: Incontro MDL | AC35: INFORCOOP ECIPA PIEMONTE STRADA CAMPAGNE' 7 - BIELLA | AG35: 60 | AH35: 04/12/2023 | AI35: PNFMRT85H50A859E | AJ35: =VLOOKUP(exp_SILP!$Y35,'DATI CM'!$A$2:$F$28,2,FALSE) -> PNFMRT85H50A859E
A36: =IFERROR(VLOOKUP(exp_SILP!$W36,exp_utenti_P!D:D,1,FALSE),"_DA INSERIRE") -> BHALPH96P10Z317H | B36: =IF(AND(exp_SILP!$S36="A.3 ORIENTAMENTO PROFESSIONALE",exp_SILP!$AD36="4.2"),"A.3 ORIENTAMENTO PROFESSIONALE (CARCERE)", IF(AND(exp_SILP!$S36="A.3 ORIENTAMENTO PROFESSIONALE",exp_SILP!$AD36="."),"A.3 ORIENTAMENTO PROFESSIONALE (CARCERE)", IF(AND(exp_SILP!$S36="A.4 CONSULENZA ORIENTATIVA",exp_SILP!$AD36="4.2"),"A.4 CONSULENZA ORIENTATIVA (CARCERE)", IF(AND(exp_SILP!$S36="A.4 CONSULENZA ORIENTATIVA",exp_SILP!$AD36="."),"A.4 CONSULENZA ORIENTATIVA (CARCERE)", IF(AND(exp_SILP!$S36="A.5 - LEP F1 - ACCOMPAGNAMENTO AL LAVORO",exp_SILP!$AD36="4.2"),"A.5 - LEP F1 - ACCOMPAGNAMENTO AL LAVORO (CARCERE)", IF(AND(exp_SILP!$S36="A.5 - LEP F1 - ACCOMPAGNAMENTO AL LAVORO",exp_SILP!$AD36="."),"A.5 - LEP F1 - ACCOMPAGNAMENTO AL LAVORO (CARCERE)", IF(AND(exp_SILP!$S36="A.5.2a - TUTORAGGIO TIROCINI",exp_SILP!$AD36="4.2"),"A.5.2a - TUTORAGGIO TIROCINI (CARCERE)", exp_SILP!$S36))))))) -> A4.10 - LEP E - ORIENTAMENTO SPECIALISTICO SKILL GAP ANALYSIS | C36: =CONCATENATE(VLOOKUP(exp_SILP!$B36,'DATI COMMESSE'!$A$2:$F$25,4,FALSE)," - ", VLOOKUP(exp_SILP!$B36,'DATI COMMESSE'!$A$2:$F$25,2,FALSE)," - ",VLOOKUP(exp_SILP!$B36,'DATI COMMESSE'!$A$2:$F$25,3,FALSE)) -> GOL - 22-02-5000 - 22-12-5003 | D36: =LEFT(exp_SILP!$R36,5) -> 17:00 | E36: =RIGHT(exp_SILP!$R36,5) -> 18:00 | F36: =IF(exp_SILP!$AG36>=60,exp_SILP!$AG36/60,exp_SILP!$AG36) -> 1 | G36: =VLOOKUP(exp_SILP!$Y36,'DATI CM'!$A$2:$F$28,2,FALSE) -> RSCDAA66H43F952Q | H36: =VLOOKUP(exp_SILP!$Y36,'DATI CM'!$A$2:$F$28,3,FALSE) -> A011 | I36: =IF(A36>0,"N","N") -> N | J36: =VLOOKUP(exp_SILP!$Y36,'DATI CM'!$A$2:$F$28,4,FALSE) -> NO | K36: =VLOOKUP(exp_SILP!$B36,'DATI COMMESSE'!$A$2:$F$25,5,FALSE) -> 39.94 | L36: =IF(exp_SILP!$B36="A4.10 - LEP E - ORIENTAMENTO SPECIALISTICO SKILL GAP ANALYSIS - GRUPPO 3P",0,VLOOKUP(exp_SILP!$Y36,'DATI CM'!$A$2:$F$28,6,FALSE)) -> 25 | M36: =IFERROR(VLOOKUP(exp_SILP!$B36,'DATI CM'!$H$2:$I$16,2,FALSE)*exp_SILP!$F36,0) -> 0 | N36: =VLOOKUP(exp_SILP!$B36,'DATI COMMESSE'!$A$2:$F$25,4,FALSE) -> GOL | O36: =VLOOKUP(exp_SILP!$B36,'DATI COMMESSE'!$A$2:$F$25,5,FALSE)*exp_SILP!$F36 -> 39.94 | P36: =IF(MID(exp_SILP!$W36,10,2)>"40","F","M") -> M | Q36: 01/12/2023 | R36: 17:00-18:00 | S36: A4.10 - LEP E - ORIENTAMENTO SPECIALISTICO SKILL GAP ANALYSIS | T36: Progetti per accreditati | V36: BAH ALPHA | W36: BHALPH96P10Z317H | X36: 10/09/1996 | Y36: RUSCA ADA | Z36: Erogato | AA36: INFORCOOP ECIPA PIEMONTE | AB36: Incontro MDL | AC36: INFORCOOP ECIPA PIEMONTE VIA UGO PORZIO GIOVANOLA 7 - NOVARA | AF36: BACK OFFICE | AG36: 60 | AH36: 04/12/2023 | AI36: RSCDAA66H43F952Q | AJ36: =VLOOKUP(exp_SILP!$Y36,'DATI CM'!$A$2:$F$28,2,FALSE) -> RSCDAA66H43F952Q
A37: =IFERROR(VLOOKUP(exp_SILP!$W37,exp_utenti_P!D:D,1,FALSE),"_DA INSERIRE") -> DGLRRT64S29F205I | B37: =IF(AND(exp_SILP!$S37="A.3 ORIENTAMENTO PROFESSIONALE",exp_SILP!$AD37="4.2"),"A.3 ORIENTAMENTO PROFESSIONALE (CARCERE)", IF(AND(exp_SILP!$S37="A.3 ORIENTAMENTO PROFESSIONALE",exp_SILP!$AD37="."),"A.3 ORIENTAMENTO PROFESSIONALE (CARCERE)", IF(AND(exp_SILP!$S37="A.4 CONSULENZA ORIENTATIVA",exp_SILP!$AD37="4.2"),"A.4 CONSULENZA ORIENTATIVA (CARCERE)", IF(AND(exp_SILP!$S37="A.4 CONSULENZA ORIENTATIVA",exp_SILP!$AD37="."),"A.4 CONSULENZA ORIENTATIVA (CARCERE)", IF(AND(exp_SILP!$S37="A.5 - LEP F1 - ACCOMPAGNAMENTO AL LAVORO",exp_SILP!$AD37="4.2"),"A.5 - LEP F1 - ACCOMPAGNAMENTO AL LAVORO (CARCERE)", IF(AND(exp_SILP!$S37="A.5 - LEP F1 - ACCOMPAGNAMENTO AL LAVORO",exp_SILP!$AD37="."),"A.5 - LEP F1 - ACCOMPAGNAMENTO AL LAVORO (CARCERE)", IF(AND(exp_SILP!$S37="A.5.2a - TUTORAGGIO TIROCINI",exp_SILP!$AD37="4.2"),"A.5.2a - TUTORAGGIO TIROCINI (CARCERE)", exp_SILP!$S37))))))) -> A4.10 - LEP E - ORIENTAMENTO SPECIALISTICO SKILL GAP ANALYSIS | C37: =CONCATENATE(VLOOKUP(exp_SILP!$B37,'DATI COMMESSE'!$A$2:$F$25,4,FALSE)," - ", VLOOKUP(exp_SILP!$B37,'DATI COMMESSE'!$A$2:$F$25,2,FALSE)," - ",VLOOKUP(exp_SILP!$B37,'DATI COMMESSE'!$A$2:$F$25,3,FALSE)) -> GOL - 22-02-5000 - 22-12-5003 | D37: =LEFT(exp_SILP!$R37,5) -> 11:00 | E37: =RIGHT(exp_SILP!$R37,5) -> 13:00 | F37: =IF(exp_SILP!$AG37>=60,exp_SILP!$AG37/60,exp_SILP!$AG37) -> 2 | G37: =VLOOKUP(exp_SILP!$Y37,'DATI CM'!$A$2:$F$28,2,FALSE) -> RSCDAA66H43F952Q | H37: =VLOOKUP(exp_SILP!$Y37,'DATI CM'!$A$2:$F$28,3,FALSE) -> A011 | I37: =IF(A37>0,"N","N") -> N | J37: =VLOOKUP(exp_SILP!$Y37,'DATI CM'!$A$2:$F$28,4,FALSE) -> NO | K37: =VLOOKUP(exp_SILP!$B37,'DATI COMMESSE'!$A$2:$F$25,5,FALSE) -> 39.94 | L37: =IF(exp_SILP!$B37="A4.10 - LEP E - ORIENTAMENTO SPECIALISTICO SKILL GAP ANALYSIS - GRUPPO 3P",0,VLOOKUP(exp_SILP!$Y37,'DATI CM'!$A$2:$F$28,6,FALSE)) -> 25 | M37: =IFERROR(VLOOKUP(exp_SILP!$B37,'DATI CM'!$H$2:$I$16,2,FALSE)*exp_SILP!$F37,0) -> 0 | N37: =VLOOKUP(exp_SILP!$B37,'DATI COMMESSE'!$A$2:$F$25,4,FALSE) -> GOL | O37: =VLOOKUP(exp_SILP!$B37,'DATI COMMESSE'!$A$2:$F$25,5,FALSE)*exp_SILP!$F37 -> 79.88 | P37: =IF(MID(exp_SILP!$W37,10,2)>"40","F","M") -> M | Q37: 01/12/2023 | R37: 11:00-13:00 | S37: A4.10 - LEP E - ORIENTAMENTO SPECIALISTICO SKILL GAP ANALYSIS | T37: Progetti per accreditati | V37: DI GIULIO ROBERTO | W37: DGLRRT64S29F205I | X37: 29/11/1964 | Y37: RUSCA ADA | Z37: Erogato | AA37: INFORCOOP ECIPA PIEMONTE | AB37: Incontro MDL | AC37: INFORCOOP ECIPA PIEMONTE VIA UGO PORZIO GIOVANOLA 7 - NOVARA | AG37: 120 | AH37: 01/12/2023 | AI37: RSCDAA66H43F952Q | AJ37: =VLOOKUP(exp_SILP!$Y37,'DATI CM'!$A$2:$F$28,2,FALSE) -> RSCDAA66H43F952Q
A38: =IFERROR(VLOOKUP(exp_SILP!$W38,exp_utenti_P!D:D,1,FALSE),"_DA INSERIRE") -> GMOSSI03D24Z354O | B38: =IF(AND(exp_SILP!$S38="A.3 ORIENTAMENTO PROFESSIONALE",exp_SILP!$AD38="4.2"),"A.3 ORIENTAMENTO PROFESSIONALE (CARCERE)", IF(AND(exp_SILP!$S38="A.3 ORIENTAMENTO PROFESSIONALE",exp_SILP!$AD38="."),"A.3 ORIENTAMENTO PROFESSIONALE (CARCERE)", IF(AND(exp_SILP!$S38="A.4 CONSULENZA ORIENTATIVA",exp_SILP!$AD38="4.2"),"A.4 CONSULENZA ORIENTATIVA (CARCERE)", IF(AND(exp_SILP!$S38="A.4 CONSULENZA ORIENTATIVA",exp_SILP!$AD38="."),"A.4 CONSULENZA ORIENTATIVA (CARCERE)", IF(AND(exp_SILP!$S38="A.5 - LEP F1 - ACCOMPAGNAMENTO AL LAVORO",exp_SILP!$AD38="4.2"),"A.5 - LEP F1 - ACCOMPAGNAMENTO AL LAVORO (CARCERE)", IF(AND(exp_SILP!$S38="A.5 - LEP F1 - ACCOMPAGNAMENTO AL LAVORO",exp_SILP!$AD38="."),"A.5 - LEP F1 - ACCOMPAGNAMENTO AL LAVORO (CARCERE)", IF(AND(exp_SILP!$S38="A.5.2a - TUTORAGGIO TIROCINI",exp_SILP!$AD38="4.2"),"A.5.2a - TUTORAGGIO TIROCINI (CARCERE)", exp_SILP!$S38))))))) -> A4.10 - LEP E - ORIENTAMENTO SPECIALISTICO SKILL GAP ANALYSIS | C38: =CONCATENATE(VLOOKUP(exp_SILP!$B38,'DATI COMMESSE'!$A$2:$F$25,4,FALSE)," - ", VLOOKUP(exp_SILP!$B38,'DATI COMMESSE'!$A$2:$F$25,2,FALSE)," - ",VLOOKUP(exp_SILP!$B38,'DATI COMMESSE'!$A$2:$F$25,3,FALSE)) -> GOL - 22-02-5000 - 22-12-5003 | D38: =LEFT(exp_SILP!$R38,5) -> 09:00 | E38: =RIGHT(exp_SILP!$R38,5) -> 11:00 | F38: =IF(exp_SILP!$AG38>=60,exp_SILP!$AG38/60,exp_SILP!$AG38) -> 2 | G38: =VLOOKUP(exp_SILP!$Y38,'DATI CM'!$A$2:$F$28,2,FALSE) -> RSCDAA66H43F952Q | H38: =VLOOKUP(exp_SILP!$Y38,'DATI CM'!$A$2:$F$28,3,FALSE) -> A011 | I38: =IF(A38>0,"N","N") -> N | J38: =VLOOKUP(exp_SILP!$Y38,'DATI CM'!$A$2:$F$28,4,FALSE) -> NO | K38: =VLOOKUP(exp_SILP!$B38,'DATI COMMESSE'!$A$2:$F$25,5,FALSE) -> 39.94 | L38: =IF(exp_SILP!$B38="A4.10 - LEP E - ORIENTAMENTO SPECIALISTICO SKILL GAP ANALYSIS - GRUPPO 3P",0,VLOOKUP(exp_SILP!$Y38,'DATI CM'!$A$2:$F$28,6,FALSE)) -> 25 | M38: =IFERROR(VLOOKUP(exp_SILP!$B38,'DATI CM'!$H$2:$I$16,2,FALSE)*exp_SILP!$F38,0) -> 0 | N38: =VLOOKUP(exp_SILP!$B38,'DATI COMMESSE'!$A$2:$F$25,4,FALSE) -> GOL | O38: =VLOOKUP(exp_SILP!$B38,'DATI COMMESSE'!$A$2:$F$25,5,FALSE)*exp_SILP!$F38 -> 79.88 | P38: =IF(MID(exp_SILP!$W38,10,2)>"40","F","M") -> M | Q38: 01/12/2023 | R38: 09:00-11:00 | S38: A4.10 - LEP E - ORIENTAMENTO SPECIALISTICO SKILL GAP ANALYSIS | T38: Progetti per accreditati | V38: GOUEM ISSA | W38: GMOSSI03D24Z354O | X38: 24/04/2003 | Y38: RUSCA ADA | Z38: Erogato | AA38: INFORCOOP ECIPA PIEMONTE | AB38: Incontro MDL | AC38: INFORCOOP ECIPA PIEMONTE VIA UGO PORZIO GIOVANOLA 7 - NOVARA | AG38: 120 | AH38: 01/12/2023 | AI38: RSCDAA66H43F952Q | AJ38: =VLOOKUP(exp_SILP!$Y38,'DATI CM'!$A$2:$F$28,2,FALSE) -> RSCDAA66H43F952Q
A39: =IFERROR(VLOOKUP(exp_SILP!$W39,exp_utenti_P!D:D,1,FALSE),"_DA INSERIRE") -> MNSLTF70L47Z352B | B39: =IF(AND(exp_SILP!$S39="A.3 ORIENTAMENTO PROFESSIONALE",exp_SILP!$AD39="4.2"),"A.3 ORIENTAMENTO PROFESSIONALE (CARCERE)", IF(AND(exp_SILP!$S39="A.3 ORIENTAMENTO PROFESSIONALE",exp_SILP!$AD39="."),"A.3 ORIENTAMENTO PROFESSIONALE (CARCERE)", IF(AND(exp_SILP!$S39="A.4 CONSULENZA ORIENTATIVA",exp_SILP!$AD39="4.2"),"A.4 CONSULENZA ORIENTATIVA (CARCERE)", IF(AND(exp_SILP!$S39="A.4 CONSULENZA ORIENTATIVA",exp_SILP!$AD39="."),"A.4 CONSULENZA ORIENTATIVA (CARCERE)", IF(AND(exp_SILP!$S39="A.5 - LEP F1 - ACCOMPAGNAMENTO AL LAVORO",exp_SILP!$AD39="4.2"),"A.5 - LEP F1 - ACCOMPAGNAMENTO AL LAVORO (CARCERE)", IF(AND(exp_SILP!$S39="A.5 - LEP F1 - ACCOMPAGNAMENTO AL LAVORO",exp_SILP!$AD39="."),"A.5 - LEP F1 - ACCOMPAGNAMENTO AL LAVORO (CARCERE)", IF(AND(exp_SILP!$S39="A.5.2a - TUTORAGGIO TIROCINI",exp_SILP!$AD39="4.2"),"A.5.2a - TUTORAGGIO TIROCINI (CARCERE)", exp_SILP!$S39))))))) -> A4.10 - LEP E - ORIENTAMENTO SPECIALISTICO SKILL GAP ANALYSIS | C39: =CONCATENATE(VLOOKUP(exp_SILP!$B39,'DATI COMMESSE'!$A$2:$F$25,4,FALSE)," - ", VLOOKUP(exp_SILP!$B39,'DATI COMMESSE'!$A$2:$F$25,2,FALSE)," - ",VLOOKUP(exp_SILP!$B39,'DATI COMMESSE'!$A$2:$F$25,3,FALSE)) -> GOL - 22-02-5000 - 22-12-5003 | D39: =LEFT(exp_SILP!$R39,5) -> 15:00 | E39: =RIGHT(exp_SILP!$R39,5) -> 17:00 | F39: =IF(exp_SILP!$AG39>=60,exp_SILP!$AG39/60,exp_SILP!$AG39) -> 2 | G39: =VLOOKUP(exp_SILP!$Y39,'DATI CM'!$A$2:$F$28,2,FALSE) -> RSCDAA66H43F952Q | H39: =VLOOKUP(exp_SILP!$Y39,'DATI CM'!$A$2:$F$28,3,FALSE) -> A011 | I39: =IF(A39>0,"N","N") -> N | J39: =VLOOKUP(exp_SILP!$Y39,'DATI CM'!$A$2:$F$28,4,FALSE) -> NO | K39: =VLOOKUP(exp_SILP!$B39,'DATI COMMESSE'!$A$2:$F$25,5,FALSE) -> 39.94 | L39: =IF(exp_SILP!$B39="A4.10 - LEP E - ORIENTAMENTO SPECIALISTICO SKILL GAP ANALYSIS - GRUPPO 3P",0,VLOOKUP(exp_SILP!$Y39,'DATI CM'!$A$2:$F$28,6,FALSE)) -> 25 | M39: =IFERROR(VLOOKUP(exp_SILP!$B39,'DATI CM'!$H$2:$I$16,2,FALSE)*exp_SILP!$F39,0) -> 0 | N39: =VLOOKUP(exp_SILP!$B39,'DATI COMMESSE'!$A$2:$F$25,4,FALSE) -> GOL | O39: =VLOOKUP(exp_SILP!$B39,'DATI COMMESSE'!$A$2:$F$25,5,FALSE)*exp_SILP!$F39 -> 79.88 | P39: =IF(MID(exp_SILP!$W39,10,2)>"40","F","M") -> F | Q39: 01/12/2023 | R39: 15:00-17:00 | S39: A4.10 - LEP E - ORIENTAMENTO SPECIALISTICO SKILL GAP ANALYSIS | T39: Progetti per accreditati | V39: MANSOURI LATIFA | W39: MNSLTF70L47Z352B | X39: 07/07/1970 | Y39: RUSCA ADA | Z39: Erogato | AA39: INFORCOOP ECIPA PIEMONTE | AB39: Incontro MDL | AC39: INFORCOOP ECIPA PIEMONTE VIA UGO PORZIO GIOVANOLA 7 - NOVARA | AG39: 120 | AH39: 01/12/2023 | AI39: RSCDAA66H43F952Q | AJ39: =VLOOKUP(exp_SILP!$Y39,'DATI CM'!$A$2:$F$28,2,FALSE) -> RSCDAA66H43F952Q
A40: =IFERROR(VLOOKUP(exp_SILP!$W40,exp_utenti_P!D:D,1,FALSE),"_DA INSERIRE") -> MSSMRL86T46Z611W | B40: =IF(AND(exp_SILP!$S40="A.3 ORIENTAMENTO PROFESSIONALE",exp_SILP!$AD40="4.2"),"A.3 ORIENTAMENTO PROFESSIONALE (CARCERE)", IF(AND(exp_SILP!$S40="A.3 ORIENTAMENTO PROFESSIONALE",exp_SILP!$AD40="."),"A.3 ORIENTAMENTO PROFESSIONALE (CARCERE)", IF(AND(exp_SILP!$S40="A.4 CONSULENZA ORIENTATIVA",exp_SILP!$AD40="4.2"),"A.4 CONSULENZA ORIENTATIVA (CARCERE)", IF(AND(exp_SILP!$S40="A.4 CONSULENZA ORIENTATIVA",exp_SILP!$AD40="."),"A.4 CONSULENZA ORIENTATIVA (CARCERE)", IF(AND(exp_SILP!$S40="A.5 - LEP F1 - ACCOMPAGNAMENTO AL LAVORO",exp_SILP!$AD40="4.2"),"A.5 - LEP F1 - ACCOMPAGNAMENTO AL LAVORO (CARCERE)", IF(AND(exp_SILP!$S40="A.5 - LEP F1 - ACCOMPAGNAMENTO AL LAVORO",exp_SILP!$AD40="."),"A.5 - LEP F1 - ACCOMPAGNAMENTO AL LAVORO (CARCERE)", IF(AND(exp_SILP!$S40="A.5.2a - TUTORAGGIO TIROCINI",exp_SILP!$AD40="4.2"),"A.5.2a - TUTORAGGIO TIROCINI (CARCERE)", exp_SILP!$S40))))))) -> A4.10 - LEP E - ORIENTAMENTO SPECIALISTICO SKILL GAP ANALYSIS | C40: =CONCATENATE(VLOOKUP(exp_SILP!$B40,'DATI COMMESSE'!$A$2:$F$25,4,FALSE)," - ", VLOOKUP(exp_SILP!$B40,'DATI COMMESSE'!$A$2:$F$25,2,FALSE)," - ",VLOOKUP(exp_SILP!$B40,'DATI COMMESSE'!$A$2:$F$25,3,FALSE)) -> GOL - 22-02-5000 - 22-12-5003 | D40: =LEFT(exp_SILP!$R40,5) -> 18:00 | E40: =RIGHT(exp_SILP!$R40,5) -> 19:00 | F40: =IF(exp_SILP!$AG40>=60,exp_SILP!$AG40/60,exp_SILP!$AG40) -> 1 | G40: =VLOOKUP(exp_SILP!$Y40,'DATI CM'!$A$2:$F$28,2,FALSE) -> FLCSRN79S42L219X | H40: =VLOOKUP(exp_SILP!$Y40,'DATI CM'!$A$2:$F$28,3,FALSE) -> A011 | I40: =IF(A40>0,"N","N") -> N | J40: =VLOOKUP(exp_SILP!$Y40,'DATI CM'!$A$2:$F$28,4,FALSE) -> TORINO | K40: =VLOOKUP(exp_SILP!$B40,'DATI COMMESSE'!$A$2:$F$25,5,FALSE) -> 39.94 | L40: =IF(exp_SILP!$B40="A4.10 - LEP E - ORIENTAMENTO SPECIALISTICO SKILL GAP ANALYSIS - GRUPPO 3P",0,VLOOKUP(exp_SILP!$Y40,'DATI CM'!$A$2:$F$28,6,FALSE)) -> 25 | M40: =IFERROR(VLOOKUP(exp_SILP!$B40,'DATI CM'!$H$2:$I$16,2,FALSE)*exp_SILP!$F40,0) -> 0 | N40: =VLOOKUP(exp_SILP!$B40,'DATI COMMESSE'!$A$2:$F$25,4,FALSE) -> GOL | O40: =VLOOKUP(exp_SILP!$B40,'DATI COMMESSE'!$A$2:$F$25,5,FALSE)*exp_SILP!$F40 -> 39.94 | P40: =IF(MID(exp_SILP!$W40,10,2)>"40","F","M") -> F | Q40: 01/12/2023 | R40: 18:00-19:00 | S40: A4.10 - LEP E - ORIENTAMENTO SPECIALISTICO SKILL GAP ANALYSIS | T40: Progetti per accreditati | V40: MESSINA MARIELA | W40: MSSMRL86T46Z611W | X40: 06/12/1986 | Y40: FALCONE SERENA | Z40: Erogato | AA40: INFORCOOP ECIPA PIEMONTE | AB40: Incontro MDL | AC40: INFORCOOP ECIPA PIEMONTE VIA LIVORNO 53/b - TORINO | AF40: BO | AG40: 60 | AH40: 02/12/2023 | AI40: FLCSRN79S42L219X | AJ40: =VLOOKUP(exp_SILP!$Y40,'DATI CM'!$A$2:$F$28,2,FALSE) -> FLCSRN79S42L219X
A41: =IFERROR(VLOOKUP(exp_SILP!$W41,exp_utenti_P!D:D,1,FALSE),"_DA INSERIRE") -> MSSMRL86T46Z611W | B41: =IF(AND(exp_SILP!$S41="A.3 ORIENTAMENTO PROFESSIONALE",exp_SILP!$AD41="4.2"),"A.3 ORIENTAMENTO PROFESSIONALE (CARCERE)", IF(AND(exp_SILP!$S41="A.3 ORIENTAMENTO PROFESSIONALE",exp_SILP!$AD41="."),"A.3 ORIENTAMENTO PROFESSIONALE (CARCERE)", IF(AND(exp_SILP!$S41="A.4 CONSULENZA ORIENTATIVA",exp_SILP!$AD41="4.2"),"A.4 CONSULENZA ORIENTATIVA (CARCERE)", IF(AND(exp_SILP!$S41="A.4 CONSULENZA ORIENTATIVA",exp_SILP!$AD41="."),"A.4 CONSULENZA ORIENTATIVA (CARCERE)", IF(AND(exp_SILP!$S41="A.5 - LEP F1 - ACCOMPAGNAMENTO AL LAVORO",exp_SILP!$AD41="4.2"),"A.5 - LEP F1 - ACCOMPAGNAMENTO AL LAVORO (CARCERE)", IF(AND(exp_SILP!$S41="A.5 - LEP F1 - ACCOMPAGNAMENTO AL LAVORO",exp_SILP!$AD41="."),"A.5 - LEP F1 - ACCOMPAGNAMENTO AL LAVORO (CARCERE)", IF(AND(exp_SILP!$S41="A.5.2a - TUTORAGGIO TIROCINI",exp_SILP!$AD41="4.2"),"A.5.2a - TUTORAGGIO TIROCINI (CARCERE)", exp_SILP!$S41))))))) -> A4.10 - LEP E - ORIENTAMENTO SPECIALISTICO SKILL GAP ANALYSIS | C41: =CONCATENATE(VLOOKUP(exp_SILP!$B41,'DATI COMMESSE'!$A$2:$F$25,4,FALSE)," - ", VLOOKUP(exp_SILP!$B41,'DATI COMMESSE'!$A$2:$F$25,2,FALSE)," - ",VLOOKUP(exp_SILP!$B41,'DATI COMMESSE'!$A$2:$F$25,3,FALSE)) -> GOL - 22-02-5000 - 22-12-5003 | D41: =LEFT(exp_SILP!$R41,5) -> 15:00 | E41: =RIGHT(exp_SILP!$R41,5) -> 18:00 | F41: =IF(exp_SILP!$AG41>=60,exp_SILP!$AG41/60,exp_SILP!$AG41) -> 3 | G41: =VLOOKUP(exp_SILP!$Y41,'DATI CM'!$A$2:$F$28,2,FALSE) -> FLCSRN79S42L219X | H41: =VLOOKUP(exp_SILP!$Y41,'DATI CM'!$A$2:$F$28,3,FALSE) -> A011 | I41: =IF(A41>0,"N","N") -> N | J41: =VLOOKUP(exp_SILP!$Y41,'DATI CM'!$A$2:$F$28,4,FALSE) -> TORINO | K41: =VLOOKUP(exp_SILP!$B41,'DATI COMMESSE'!$A$2:$F$25,5,FALSE) -> 39.94 | L41: =IF(exp_SILP!$B41="A4.10 - LEP E - ORIENTAMENTO SPECIALISTICO SKILL GAP ANALYSIS - GRUPPO 3P",0,VLOOKUP(exp_SILP!$Y41,'DATI CM'!$A$2:$F$28,6,FALSE)) -> 25 | M41: =IFERROR(VLOOKUP(exp_SILP!$B41,'DATI CM'!$H$2:$I$16,2,FALSE)*exp_SILP!$F41,0) -> 0 | N41: =VLOOKUP(exp_SILP!$B41,'DATI COMMESSE'!$A$2:$F$25,4,FALSE) -> GOL | O41: =VLOOKUP(exp_SILP!$B41,'DATI COMMESSE'!$A$2:$F$25,5,FALSE)*exp_SILP!$F41 -> 119.82 | P41: =IF(MID(exp_SILP!$W41,10,2)>"40","F","M") -> F | Q41: 01/12/2023 | R41: 15:00-18:00 | S41: A4.10 - LEP E - ORIENTAMENTO SPECIALISTICO SKILL GAP ANALYSIS | T41: Progetti per accreditati | V41: MESSINA MARIELA | W41: MSSMRL86T46Z611W | X41: 06/12/1986 | Y41: FALCONE SERENA | Z41: Erogato | AA41: INFORCOOP ECIPA PIEMONTE | AB41: Incontro MDLpresentato | AC41: INFORCOOP ECIPA PIEMONTE VIA LIVORNO 53/b - TORINO | AG41: 180 | AH41: 02/12/2023 | AI41: FLCSRN79S42L219X | AJ41: =VLOOKUP(exp_SILP!$Y41,'DATI CM'!$A$2:$F$28,2,FALSE) -> FLCSRN79S42L219X
A42: =IFERROR(VLOOKUP(exp_SILP!$W42,exp_utenti_P!D:D,1,FALSE),"_DA INSERIRE") -> PPSVNT82B60F335Q | B42: =IF(AND(exp_SILP!$S42="A.3 ORIENTAMENTO PROFESSIONALE",exp_SILP!$AD42="4.2"),"A.3 ORIENTAMENTO PROFESSIONALE (CARCERE)", IF(AND(exp_SILP!$S42="A.3 ORIENTAMENTO PROFESSIONALE",exp_SILP!$AD42="."),"A.3 ORIENTAMENTO PROFESSIONALE (CARCERE)", IF(AND(exp_SILP!$S42="A.4 CONSULENZA ORIENTATIVA",exp_SILP!$AD42="4.2"),"A.4 CONSULENZA ORIENTATIVA (CARCERE)", IF(AND(exp_SILP!$S42="A.4 CONSULENZA ORIENTATIVA",exp_SILP!$AD42="."),"A.4 CONSULENZA ORIENTATIVA (CARCERE)", IF(AND(exp_SILP!$S42="A.5 - LEP F1 - ACCOMPAGNAMENTO AL LAVORO",exp_SILP!$AD42="4.2"),"A.5 - LEP F1 - ACCOMPAGNAMENTO AL LAVORO (CARCERE)", IF(AND(exp_SILP!$S42="A.5 - LEP F1 - ACCOMPAGNAMENTO AL LAVORO",exp_SILP!$AD42="."),"A.5 - LEP F1 - ACCOMPAGNAMENTO AL LAVORO (CARCERE)", IF(AND(exp_SILP!$S42="A.5.2a - TUTORAGGIO TIROCINI",exp_SILP!$AD42="4.2"),"A.5.2a - TUTORAGGIO TIROCINI (CARCERE)", exp_SILP!$S42))))))) -> A4.10 - LEP E - ORIENTAMENTO SPECIALISTICO SKILL GAP ANALYSIS | C42: =CONCATENATE(VLOOKUP(exp_SILP!$B42,'DATI COMMESSE'!$A$2:$F$25,4,FALSE)," - ", VLOOKUP(exp_SILP!$B42,'DATI COMMESSE'!$A$2:$F$25,2,FALSE)," - ",VLOOKUP(exp_SILP!$B42,'DATI COMMESSE'!$A$2:$F$25,3,FALSE)) -> GOL - 22-02-5000 - 22-12-5003 | D42: =LEFT(exp_SILP!$R42,5) -> 09:00 | E42: =RIGHT(exp_SILP!$R42,5) -> 12:00 | F42: =IF(exp_SILP!$AG42>=60,exp_SILP!$AG42/60,exp_SILP!$AG42) -> 3 | G42: =VLOOKUP(exp_SILP!$Y42,'DATI CM'!$A$2:$F$28,2,FALSE) -> CRCMGR68A64L219S | H42: =VLOOKUP(exp_SILP!$Y42,'DATI CM'!$A$2:$F$28,3,FALSE) -> A011 | I42: =IF(A42>0,"N","N") -> N | J42: =VLOOKUP(exp_SILP!$Y42,'DATI CM'!$A$2:$F$28,4,FALSE) -> TORINO | K42: =VLOOKUP(exp_SILP!$B42,'DATI COMMESSE'!$A$2:$F$25,5,FALSE) -> 39.94 | L42: =IF(exp_SILP!$B42="A4.10 - LEP E - ORIENTAMENTO SPECIALISTICO SKILL GAP ANALYSIS - GRUPPO 3P",0,VLOOKUP(exp_SILP!$Y42,'DATI CM'!$A$2:$F$28,6,FALSE)) -> 27 | M42: =IFERROR(VLOOKUP(exp_SILP!$B42,'DATI CM'!$H$2:$I$16,2,FALSE)*exp_SILP!$F42,0) -> 0 | N42: =VLOOKUP(exp_SILP!$B42,'DATI COMMESSE'!$A$2:$F$25,4,FALSE) -> GOL | O42: =VLOOKUP(exp_SILP!$B42,'DATI COMMESSE'!$A$2:$F$25,5,FALSE)*exp_SILP!$F42 -> 119.82 | P42: =IF(MID(exp_SILP!$W42,10,2)>"40","F","M") -> F | Q42: 01/12/2023 | R42: 09:00-12:00 | S42: A4.10 - LEP E - ORIENTAMENTO SPECIALISTICO SKILL GAP ANALYSIS | T42: Progetti per accreditati | V42: OPPES VALENTINA | W42: PPSVNT82B60F335Q | X42: 20/02/1982 | Y42: CROCE MARIA GRAZIA | Z42: Erogato | AA42: INFORCOOP ECIPA PIEMONTE | AB42: Incontro MDL | AC42: INFORCOOP ECIPA PIEMONTE VIA TREVISO 12 - TORINO | AG42: 180 | AH42: 01/12/2023 | AI42: CRCMGR68A64L219S | AJ42: =VLOOKUP(exp_SILP!$Y42,'DATI CM'!$A$2:$F$28,2,FALSE) -> CRCMGR68A64L219S
A43: =IFERROR(VLOOKUP(exp_SILP!$W43,exp_utenti_P!D:D,1,FALSE),"_DA INSERIRE") -> SPZMTN95L65L219U | B43: =IF(AND(exp_SILP!$S43="A.3 ORIENTAMENTO PROFESSIONALE",exp_SILP!$AD43="4.2"),"A.3 ORIENTAMENTO PROFESSIONALE (CARCERE)", IF(AND(exp_SILP!$S43="A.3 ORIENTAMENTO PROFESSIONALE",exp_SILP!$AD43="."),"A.3 ORIENTAMENTO PROFESSIONALE (CARCERE)", IF(AND(exp_SILP!$S43="A.4 CONSULENZA ORIENTATIVA",exp_SILP!$AD43="4.2"),"A.4 CONSULENZA ORIENTATIVA (CARCERE)", IF(AND(exp_SILP!$S43="A.4 CONSULENZA ORIENTATIVA",exp_SILP!$AD43="."),"A.4 CONSULENZA ORIENTATIVA (CARCERE)", IF(AND(exp_SILP!$S43="A.5 - LEP F1 - ACCOMPAGNAMENTO AL LAVORO",exp_SILP!$AD43="4.2"),"A.5 - LEP F1 - ACCOMPAGNAMENTO AL LAVORO (CARCERE)", IF(AND(exp_SILP!$S43="A.5 - LEP F1 - ACCOMPAGNAMENTO AL LAVORO",exp_SILP!$AD43="."),"A.5 - LEP F1 - ACCOMPAGNAMENTO AL LAVORO (CARCERE)", IF(AND(exp_SILP!$S43="A.5.2a - TUTORAGGIO TIROCINI",exp_SILP!$AD43="4.2"),"A.5.2a - TUTORAGGIO TIROCINI (CARCERE)", exp_SILP!$S43))))))) -> A4.10 - LEP E - ORIENTAMENTO SPECIALISTICO SKILL GAP ANALYSIS | C43: =CONCATENATE(VLOOKUP(exp_SILP!$B43,'DATI COMMESSE'!$A$2:$F$25,4,FALSE)," - ", VLOOKUP(exp_SILP!$B43,'DATI COMMESSE'!$A$2:$F$25,2,FALSE)," - ",VLOOKUP(exp_SILP!$B43,'DATI COMMESSE'!$A$2:$F$25,3,FALSE)) -> GOL - 22-02-5000 - 22-12-5003 | D43: =LEFT(exp_SILP!$R43,5) -> 09:00 | E43: =RIGHT(exp_SILP!$R43,5) -> 10:00 | F43: =IF(exp_SILP!$AG43>=60,exp_SILP!$AG43/60,exp_SILP!$AG43) -> 1 | G43: =VLOOKUP(exp_SILP!$Y43,'DATI CM'!$A$2:$F$28,2,FALSE) -> FLCSRN79S42L219X | H43: =VLOOKUP(exp_SILP!$Y43,'DATI CM'!$A$2:$F$28,3,FALSE) -> A011 | I43: =IF(A43>0,"N","N") -> N | J43: =VLOOKUP(exp_SILP!$Y43,'DATI CM'!$A$2:$F$28,4,FALSE) -> TORINO | K43: =VLOOKUP(exp_SILP!$B43,'DATI COMMESSE'!$A$2:$F$25,5,FALSE) -> 39.94 | L43: =IF(exp_SILP!$B43="A4.10 - LEP E - ORIENTAMENTO SPECIALISTICO SKILL GAP ANALYSIS - GRUPPO 3P",0,VLOOKUP(exp_SILP!$Y43,'DATI CM'!$A$2:$F$28,6,FALSE)) -> 25 | M43: =IFERROR(VLOOKUP(exp_SILP!$B43,'DATI CM'!$H$2:$I$16,2,FALSE)*exp_SILP!$F43,0) -> 0 | N43: =VLOOKUP(exp_SILP!$B43,'DATI COMMESSE'!$A$2:$F$25,4,FALSE) -> GOL | O43: =VLOOKUP(exp_SILP!$B43,'DATI COMMESSE'!$A$2:$F$25,5,FALSE)*exp_SILP!$F43 -> 39.94 | P43: =IF(MID(exp_SILP!$W43,10,2)>"40","F","M") -> F | Q43: 01/12/2023 | R43: 09:00-10:00 | S43: A4.10 - LEP E - ORIENTAMENTO SPECIALISTICO SKILL GAP ANALYSIS | T43: Progetti per accreditati | V43: SPEZZANI MARTINA | W43: SPZMTN95L65L219U | X43: 25/07/1995 | Y43: FALCONE SERENA | Z43: Erogato | AA43: INFORCOOP ECIPA PIEMONTE | AB43: Incontro MDLpresentato | AC43: INFORCOOP ECIPA PIEMONTE VIA LIVORNO 53/b - TORINO | AG43: 60 | AH43: 01/12/2023 | AI43: FLCSRN79S42L219X | AJ43: =VLOOKUP(exp_SILP!$Y43,'DATI CM'!$A$2:$F$28,2,FALSE) -> FLCSRN79S42L219X
A44: =IFERROR(VLOOKUP(exp_SILP!$W44,exp_utenti_P!D:D,1,FALSE),"_DA INSERIRE") -> NPLCST73M64L219H | B44: =IF(AND(exp_SILP!$S44="A.3 ORIENTAMENTO PROFESSIONALE",exp_SILP!$AD44="4.2"),"A.3 ORIENTAMENTO PROFESSIONALE (CARCERE)", IF(AND(exp_SILP!$S44="A.3 ORIENTAMENTO PROFESSIONALE",exp_SILP!$AD44="."),"A.3 ORIENTAMENTO PROFESSIONALE (CARCERE)", IF(AND(exp_SILP!$S44="A.4 CONSULENZA ORIENTATIVA",exp_SILP!$AD44="4.2"),"A.4 CONSULENZA ORIENTATIVA (CARCERE)", IF(AND(exp_SILP!$S44="A.4 CONSULENZA ORIENTATIVA",exp_SILP!$AD44="."),"A.4 CONSULENZA ORIENTATIVA (CARCERE)", IF(AND(exp_SILP!$S44="A.5 - LEP F1 - ACCOMPAGNAMENTO AL LAVORO",exp_SILP!$AD44="4.2"),"A.5 - LEP F1 - ACCOMPAGNAMENTO AL LAVORO (CARCERE)", IF(AND(exp_SILP!$S44="A.5 - LEP F1 - ACCOMPAGNAMENTO AL LAVORO",exp_SILP!$AD44="."),"A.5 - LEP F1 - ACCOMPAGNAMENTO AL LAVORO (CARCERE)", IF(AND(exp_SILP!$S44="A.5.2a - TUTORAGGIO TIROCINI",exp_SILP!$AD44="4.2"),"A.5.2a - TUTORAGGIO TIROCINI (CARCERE)", exp_SILP!$S44))))))) -> A4.10 - LEP E - ORIENTAMENTO SPECIALISTICO SKILL GAP ANALYSIS | C44: =CONCATENATE(VLOOKUP(exp_SILP!$B44,'DATI COMMESSE'!$A$2:$F$25,4,FALSE)," - ", VLOOKUP(exp_SILP!$B44,'DATI COMMESSE'!$A$2:$F$25,2,FALSE)," - ",VLOOKUP(exp_SILP!$B44,'DATI COMMESSE'!$A$2:$F$25,3,FALSE)) -> GOL - 22-02-5000 - 22-12-5003 | D44: =LEFT(exp_SILP!$R44,5) -> 09:00 | E44: =RIGHT(exp_SILP!$R44,5) -> 11:00 | F44: =IF(exp_SILP!$AG44>=60,exp_SILP!$AG44/60,exp_SILP!$AG44) -> 2 | G44: =VLOOKUP(exp_SILP!$Y44,'DATI CM'!$A$2:$F$28,2,FALSE) -> FLCSRN79S42L219X | H44: =VLOOKUP(exp_SILP!$Y44,'DATI CM'!$A$2:$F$28,3,FALSE) -> A011 | I44: =IF(A44>0,"N","N") -> N | J44: =VLOOKUP(exp_SILP!$Y44,'DATI CM'!$A$2:$F$28,4,FALSE) -> TORINO | K44: =VLOOKUP(exp_SILP!$B44,'DATI COMMESSE'!$A$2:$F$25,5,FALSE) -> 39.94 | L44: =IF(exp_SILP!$B44="A4.10 - LEP E - ORIENTAMENTO SPECIALISTICO SKILL GAP ANALYSIS - GRUPPO 3P",0,VLOOKUP(exp_SILP!$Y44,'DATI CM'!$A$2:$F$28,6,FALSE)) -> 25 | M44: =IFERROR(VLOOKUP(exp_SILP!$B44,'DATI CM'!$H$2:$I$16,2,FALSE)*exp_SILP!$F44,0) -> 0 | N44: =VLOOKUP(exp_SILP!$B44,'DATI COMMESSE'!$A$2:$F$25,4,FALSE) -> GOL | O44: =VLOOKUP(exp_SILP!$B44,'DATI COMMESSE'!$A$2:$F$25,5,FALSE)*exp_SILP!$F44 -> 79.88 | P44: =IF(MID(exp_SILP!$W44,10,2)>"40","F","M") -> F | Q44: 02/02/2023 | R44: 09:00-11:00 | S44: A4.10 - LEP E - ORIENTAMENTO SPECIALISTICO SKILL GAP ANALYSIS | T44: Progetti per accreditati | V44: NAPOLITANO CRISTINA BARBARA | W44: NPLCST73M64L219H | X44: 24/08/1973 | Y44: FALCONE SERENA | Z44: Erogato | AA44: INFORCOOP ECIPA PIEMONTE | AB44: Incontro MDLpresentato | AC44: INFORCOOP ECIPA PIEMONTE VIA LIVORNO 53/b - TORINO | AG44: 120 | AH44: 02/02/2023 | AI44: FLCSRN79S42L219X | AJ44: =VLOOKUP(exp_SILP!$Y44,'DATI CM'!$A$2:$F$28,2,FALSE) -> FLCSRN79S42L219X
A45: =IFERROR(VLOOKUP(exp_SILP!$W45,exp_utenti_P!D:D,1,FALSE),"_DA INSERIRE") -> TRRLNM97C06Z343R | B45: =IF(AND(exp_SILP!$S45="A.3 ORIENTAMENTO PROFESSIONALE",exp_SILP!$AD45="4.2"),"A.3 ORIENTAMENTO PROFESSIONALE (CARCERE)", IF(AND(exp_SILP!$S45="A.3 ORIENTAMENTO PROFESSIONALE",exp_SILP!$AD45="."),"A.3 ORIENTAMENTO PROFESSIONALE (CARCERE)", IF(AND(exp_SILP!$S45="A.4 CONSULENZA ORIENTATIVA",exp_SILP!$AD45="4.2"),"A.4 CONSULENZA ORIENTATIVA (CARCERE)", IF(AND(exp_SILP!$S45="A.4 CONSULENZA ORIENTATIVA",exp_SILP!$AD45="."),"A.4 CONSULENZA ORIENTATIVA (CARCERE)", IF(AND(exp_SILP!$S45="A.5 - LEP F1 - ACCOMPAGNAMENTO AL LAVORO",exp_SILP!$AD45="4.2"),"A.5 - LEP F1 - ACCOMPAGNAMENTO AL LAVORO (CARCERE)", IF(AND(exp_SILP!$S45="A.5 - LEP F1 - ACCOMPAGNAMENTO AL LAVORO",exp_SILP!$AD45="."),"A.5 - LEP F1 - ACCOMPAGNAMENTO AL LAVORO (CARCERE)", IF(AND(exp_SILP!$S45="A.5.2a - TUTORAGGIO TIROCINI",exp_SILP!$AD45="4.2"),"A.5.2a - TUTORAGGIO TIROCINI (CARCERE)", exp_SILP!$S45))))))) -> A4.10 - LEP E - ORIENTAMENTO SPECIALISTICO SKILL GAP ANALYSIS | C45: =CONCATENATE(VLOOKUP(exp_SILP!$B45,'DATI COMMESSE'!$A$2:$F$25,4,FALSE)," - ", VLOOKUP(exp_SILP!$B45,'DATI COMMESSE'!$A$2:$F$25,2,FALSE)," - ",VLOOKUP(exp_SILP!$B45,'DATI COMMESSE'!$A$2:$F$25,3,FALSE)) -> GOL - 22-02-5000 - 22-12-5003 | D45: =LEFT(exp_SILP!$R45,5) -> 11:00 | E45: =RIGHT(exp_SILP!$R45,5) -> 13:00 | F45: =IF(exp_SILP!$AG45>=60,exp_SILP!$AG45/60,exp_SILP!$AG45) -> 2 | G45: =VLOOKUP(exp_SILP!$Y45,'DATI CM'!$A$2:$F$28,2,FALSE) -> FLCSRN79S42L219X | H45: =VLOOKUP(exp_SILP!$Y45,'DATI CM'!$A$2:$F$28,3,FALSE) -> A011 | I45: =IF(A45>0,"N","N") -> N | J45: =VLOOKUP(exp_SILP!$Y45,'DATI CM'!$A$2:$F$28,4,FALSE) -> TORINO | K45: =VLOOKUP(exp_SILP!$B45,'DATI COMMESSE'!$A$2:$F$25,5,FALSE) -> 39.94 | L45: =IF(exp_SILP!$B45="A4.10 - LEP E - ORIENTAMENTO SPECIALISTICO SKILL GAP ANALYSIS - GRUPPO 3P",0,VLOOKUP(exp_SILP!$Y45,'DATI CM'!$A$2:$F$28,6,FALSE)) -> 25 | M45: =IFERROR(VLOOKUP(exp_SILP!$B45,'DATI CM'!$H$2:$I$16,2,FALSE)*exp_SILP!$F45,0) -> 0 | N45: =VLOOKUP(exp_SILP!$B45,'DATI COMMESSE'!$A$2:$F$25,4,FALSE) -> GOL | O45: =VLOOKUP(exp_SILP!$B45,'DATI COMMESSE'!$A$2:$F$25,5,FALSE)*exp_SILP!$F45 -> 79.88 | P45: =IF(MID(exp_SILP!$W45,10,2)>"40","F","M") -> M | Q45: 02/02/2023 | R45: 11:00-13:00 | S45: A4.10 - LEP E - ORIENTAMENTO SPECIALISTICO SKILL GAP ANALYSIS | T45: Progetti per accreditati | V45: TRAORE LAMINE MAMADOU | W45: TRRLNM97C06Z343R | X45: 06/03/1997 | Y45: FALCONE SERENA | Z45: Erogato | AA45: INFORCOOP ECIPA PIEMONTE | AB45: Incontro MDLpresentato | AC45: INFORCOOP ECIPA PIEMONTE VIA LIVORNO 53/b - TORINO | AG45: 120 | AH45: 02/02/2023 | AI45: FLCSRN79S42L219X | AJ45: =VLOOKUP(exp_SILP!$Y45,'DATI CM'!$A$2:$F$28,2,FALSE) -> FLCSRN79S42L219X
A46: =IFERROR(VLOOKUP(exp_SILP!$W46,exp_utenti_P!D:D,1,FALSE),"_DA INSERIRE") -> MRGCDL78B04L219M | B46: =IF(AND(exp_SILP!$S46="A.3 ORIENTAMENTO PROFESSIONALE",exp_SILP!$AD46="4.2"),"A.3 ORIENTAMENTO PROFESSIONALE (CARCERE)", IF(AND(exp_SILP!$S46="A.3 ORIENTAMENTO PROFESSIONALE",exp_SILP!$AD46="."),"A.3 ORIENTAMENTO PROFESSIONALE (CARCERE)", IF(AND(exp_SILP!$S46="A.4 CONSULENZA ORIENTATIVA",exp_SILP!$AD46="4.2"),"A.4 CONSULENZA ORIENTATIVA (CARCERE)", IF(AND(exp_SILP!$S46="A.4 CONSULENZA ORIENTATIVA",exp_SILP!$AD46="."),"A.4 CONSULENZA ORIENTATIVA (CARCERE)", IF(AND(exp_SILP!$S46="A.5 - LEP F1 - ACCOMPAGNAMENTO AL LAVORO",exp_SILP!$AD46="4.2"),"A.5 - LEP F1 - ACCOMPAGNAMENTO AL LAVORO (CARCERE)", IF(AND(exp_SILP!$S46="A.5 - LEP F1 - ACCOMPAGNAMENTO AL LAVORO",exp_SILP!$AD46="."),"A.5 - LEP F1 - ACCOMPAGNAMENTO AL LAVORO (CARCERE)", IF(AND(exp_SILP!$S46="A.5.2a - TUTORAGGIO TIROCINI",exp_SILP!$AD46="4.2"),"A.5.2a - TUTORAGGIO TIROCINI (CARCERE)", exp_SILP!$S46))))))) -> A4.10 - LEP E - ORIENTAMENTO SPECIALISTICO SKILL GAP ANALYSIS | C46: =CONCATENATE(VLOOKUP(exp_SILP!$B46,'DATI COMMESSE'!$A$2:$F$25,4,FALSE)," - ", VLOOKUP(exp_SILP!$B46,'DATI COMMESSE'!$A$2:$F$25,2,FALSE)," - ",VLOOKUP(exp_SILP!$B46,'DATI COMMESSE'!$A$2:$F$25,3,FALSE)) -> GOL - 22-02-5000 - 22-12-5003 | D46: =LEFT(exp_SILP!$R46,5) -> 16:00 | E46: =RIGHT(exp_SILP!$R46,5) -> 17:00 | F46: =IF(exp_SILP!$AG46>=60,exp_SILP!$AG46/60,exp_SILP!$AG46) -> 1 | G46: =VLOOKUP(exp_SILP!$Y46,'DATI CM'!$A$2:$F$28,2,FALSE) -> SPDPRZ67H55L219V | H46: =VLOOKUP(exp_SILP!$Y46,'DATI CM'!$A$2:$F$28,3,FALSE) -> A010 | I46: =IF(A46>0,"N","N") -> N | J46: =VLOOKUP(exp_SILP!$Y46,'DATI CM'!$A$2:$F$28,4,FALSE) -> TORINO | K46: =VLOOKUP(exp_SILP!$B46,'DATI COMMESSE'!$A$2:$F$25,5,FALSE) -> 39.94 | L46: =IF(exp_SILP!$B46="A4.10 - LEP E - ORIENTAMENTO SPECIALISTICO SKILL GAP ANALYSIS - GRUPPO 3P",0,VLOOKUP(exp_SILP!$Y46,'DATI CM'!$A$2:$F$28,6,FALSE)) | M46: =IFERROR(VLOOKUP(exp_SILP!$B46,'DATI CM'!$H$2:$I$16,2,FALSE)*exp_SILP!$F46,0) -> 0 | N46: =VLOOKUP(exp_SILP!$B46,'DATI COMMESSE'!$A$2:$F$25,4,FALSE) -> GOL | O46: =VLOOKUP(exp_SILP!$B46,'DATI COMMESSE'!$A$2:$F$25,5,FALSE)*exp_SILP!$F46 -> 39.94 | P46: =IF(MID(exp_SILP!$W46,10,2)>"40","F","M") -> M | Q46: 02/02/2023 | R46: 16:00-17:00 | S46: A4.10 - LEP E - ORIENTAMENTO SPECIALISTICO SKILL GAP ANALYSIS | T46: Progetti per accreditati | V46: MORAGLIO CLAUDIO LUCIANO | W46: MRGCDL78B04L219M | X46: 04/02/1978 | Y46: SPADARO PATRIZIA | Z46: Erogato | AA46: INFORCOOP ECIPA PIEMONTE | AB46: Incontro MDL | AC46: INFORCOOP ECIPA PIEMONTE VIA TREVISO 12 - TORINO | AF46: BACK OFFICE | AG46: 60 | AH46: 08/02/2023 | AI46: SPDPRZ67H55L219V | AJ46: =VLOOKUP(exp_SILP!$Y46,'DATI CM'!$A$2:$F$28,2,FALSE) -> SPDPRZ67H55L219V
A47: =IFERROR(VLOOKUP(exp_SILP!$W47,exp_utenti_P!D:D,1,FALSE),"_DA INSERIRE") -> MRGCDL78B04L219M | B47: =IF(AND(exp_SILP!$S47="A.3 ORIENTAMENTO PROFESSIONALE",exp_SILP!$AD47="4.2"),"A.3 ORIENTAMENTO PROFESSIONALE (CARCERE)", IF(AND(exp_SILP!$S47="A.3 ORIENTAMENTO PROFESSIONALE",exp_SILP!$AD47="."),"A.3 ORIENTAMENTO PROFESSIONALE (CARCERE)", IF(AND(exp_SILP!$S47="A.4 CONSULENZA ORIENTATIVA",exp_SILP!$AD47="4.2"),"A.4 CONSULENZA ORIENTATIVA (CARCERE)", IF(AND(exp_SILP!$S47="A.4 CONSULENZA ORIENTATIVA",exp_SILP!$AD47="."),"A.4 CONSULENZA ORIENTATIVA (CARCERE)", IF(AND(exp_SILP!$S47="A.5 - LEP F1 - ACCOMPAGNAMENTO AL LAVORO",exp_SILP!$AD47="4.2"),"A.5 - LEP F1 - ACCOMPAGNAMENTO AL LAVORO (CARCERE)", IF(AND(exp_SILP!$S47="A.5 - LEP F1 - ACCOMPAGNAMENTO AL LAVORO",exp_SILP!$AD47="."),"A.5 - LEP F1 - ACCOMPAGNAMENTO AL LAVORO (CARCERE)", IF(AND(exp_SILP!$S47="A.5.2a - TUTORAGGIO TIROCINI",exp_SILP!$AD47="4.2"),"A.5.2a - TUTORAGGIO TIROCINI (CARCERE)", exp_SILP!$S47))))))) -> A4.10 - LEP E - ORIENTAMENTO SPECIALISTICO SKILL GAP ANALYSIS | C47: =CONCATENATE(VLOOKUP(exp_SILP!$B47,'DATI COMMESSE'!$A$2:$F$25,4,FALSE)," - ", VLOOKUP(exp_SILP!$B47,'DATI COMMESSE'!$A$2:$F$25,2,FALSE)," - ",VLOOKUP(exp_SILP!$B47,'DATI COMMESSE'!$A$2:$F$25,3,FALSE)) -> GOL - 22-02-5000 - 22-12-5003 | D47: =LEFT(exp_SILP!$R47,5) -> 14:00 | E47: =RIGHT(exp_SILP!$R47,5) -> 16:00 | F47: =IF(exp_SILP!$AG47>=60,exp_SILP!$AG47/60,exp_SILP!$AG47) -> 2 | G47: =VLOOKUP(exp_SILP!$Y47,'DATI CM'!$A$2:$F$28,2,FALSE) -> SPDPRZ67H55L219V | H47: =VLOOKUP(exp_SILP!$Y47,'DATI CM'!$A$2:$F$28,3,FALSE) -> A010 | I47: =IF(A47>0,"N","N") -> N | J47: =VLOOKUP(exp_SILP!$Y47,'DATI CM'!$A$2:$F$28,4,FALSE) -> TORINO | K47: =VLOOKUP(exp_SILP!$B47,'DATI COMMESSE'!$A$2:$F$25,5,FALSE) -> 39.94 | L47: =IF(exp_SILP!$B47="A4.10 - LEP E - ORIENTAMENTO SPECIALISTICO SKILL GAP ANALYSIS - GRUPPO 3P",0,VLOOKUP(exp_SILP!$Y47,'DATI CM'!$A$2:$F$28,6,FALSE)) | M47: =IFERROR(VLOOKUP(exp_SILP!$B47,'DATI CM'!$H$2:$I$16,2,FALSE)*exp_SILP!$F47,0) -> 0 | N47: =VLOOKUP(exp_SILP!$B47,'DATI COMMESSE'!$A$2:$F$25,4,FALSE) -> GOL | O47: =VLOOKUP(exp_SILP!$B47,'DATI COMMESSE'!$A$2:$F$25,5,FALSE)*exp_SILP!$F47 -> 79.88 | P47: =IF(MID(exp_SILP!$W47,10,2)>"40","F","M") -> M | Q47: 02/02/2023 | R47: 14:00-16:00 | S47: A4.10 - LEP E - ORIENTAMENTO SPECIALISTICO SKILL GAP ANALYSIS | T47: Progetti per accreditati | V47: MORAGLIO CLAUDIO LUCIANO | W47: MRGCDL78B04L219M | X47: 04/02/1978 | Y47: SPADARO PATRIZIA | Z47: Erogato | AA47: INFORCOOP ECIPA PIEMONTE | AB47: Incontro MDL | AC47: INFORCOOP ECIPA PIEMONTE VIA TREVISO 12 - TORINO | AG47: 120 | AH47: 08/02/2023 | AI47: SPDPRZ67H55L219V | AJ47: =VLOOKUP(exp_SILP!$Y47,'DATI CM'!$A$2:$F$28,2,FALSE) -> SPDPRZ67H55L219V
A48: =IFERROR(VLOOKUP(exp_SILP!$W48,exp_utenti_P!D:D,1,FALSE),"_DA INSERIRE") -> BLHSDO80B42Z330B | B48: =IF(AND(exp_SILP!$S48="A.3 ORIENTAMENTO PROFESSIONALE",exp_SILP!$AD48="4.2"),"A.3 ORIENTAMENTO PROFESSIONALE (CARCERE)", IF(AND(exp_SILP!$S48="A.3 ORIENTAMENTO PROFESSIONALE",exp_SILP!$AD48="."),"A.3 ORIENTAMENTO PROFESSIONALE (CARCERE)", IF(AND(exp_SILP!$S48="A.4 CONSULENZA ORIENTATIVA",exp_SILP!$AD48="4.2"),"A.4 CONSULENZA ORIENTATIVA (CARCERE)", IF(AND(exp_SILP!$S48="A.4 CONSULENZA ORIENTATIVA",exp_SILP!$AD48="."),"A.4 CONSULENZA ORIENTATIVA (CARCERE)", IF(AND(exp_SILP!$S48="A.5 - LEP F1 - ACCOMPAGNAMENTO AL LAVORO",exp_SILP!$AD48="4.2"),"A.5 - LEP F1 - ACCOMPAGNAMENTO AL LAVORO (CARCERE)", IF(AND(exp_SILP!$S48="A.5 - LEP F1 - ACCOMPAGNAMENTO AL LAVORO",exp_SILP!$AD48="."),"A.5 - LEP F1 - ACCOMPAGNAMENTO AL LAVORO (CARCERE)", IF(AND(exp_SILP!$S48="A.5.2a - TUTORAGGIO TIROCINI",exp_SILP!$AD48="4.2"),"A.5.2a - TUTORAGGIO TIROCINI (CARCERE)", exp_SILP!$S48))))))) -> A4.10 - LEP E - ORIENTAMENTO SPECIALISTICO SKILL GAP ANALYSIS | C48: =CONCATENATE(VLOOKUP(exp_SILP!$B48,'DATI COMMESSE'!$A$2:$F$25,4,FALSE)," - ", VLOOKUP(exp_SILP!$B48,'DATI COMMESSE'!$A$2:$F$25,2,FALSE)," - ",VLOOKUP(exp_SILP!$B48,'DATI COMMESSE'!$A$2:$F$25,3,FALSE)) -> GOL - 22-02-5000 - 22-12-5003 | D48: =LEFT(exp_SILP!$R48,5) -> 16:00 | E48: =RIGHT(exp_SILP!$R48,5) -> 17:00 | F48: =IF(exp_SILP!$AG48>=60,exp_SILP!$AG48/60,exp_SILP!$AG48) -> 1 | G48: =VLOOKUP(exp_SILP!$Y48,'DATI CM'!$A$2:$F$28,2,FALSE) -> TRZCST69B41F952V | H48: =VLOOKUP(exp_SILP!$Y48,'DATI CM'!$A$2:$F$28,3,FALSE) | I48: =IF(A48>0,"N","N") -> N | J48: =VLOOKUP(exp_SILP!$Y48,'DATI CM'!$A$2:$F$28,4,FALSE) | K48: =VLOOKUP(exp_SILP!$B48,'DATI COMMESSE'!$A$2:$F$25,5,FALSE) -> 39.94 | L48: =IF(exp_SILP!$B48="A4.10 - LEP E - ORIENTAMENTO SPECIALISTICO SKILL GAP ANALYSIS - GRUPPO 3P",0,VLOOKUP(exp_SILP!$Y48,'DATI CM'!$A$2:$F$28,6,FALSE)) | M48: =IFERROR(VLOOKUP(exp_SILP!$B48,'DATI CM'!$H$2:$I$16,2,FALSE)*exp_SILP!$F48,0) -> 0 | N48: =VLOOKUP(exp_SILP!$B48,'DATI COMMESSE'!$A$2:$F$25,4,FALSE) -> GOL | O48: =VLOOKUP(exp_SILP!$B48,'DATI COMMESSE'!$A$2:$F$25,5,FALSE)*exp_SILP!$F48 -> 39.94 | P48: =IF(MID(exp_SILP!$W48,10,2)>"40","F","M") -> F | Q48: 02/02/2023 | R48: 16:00-17:00 | S48: A4.10 - LEP E - ORIENTAMENTO SPECIALISTICO SKILL GAP ANALYSIS | T48: Progetti per accreditati | V48: BELHADJ SOUAD | W48: BLHSDO80B42Z330B | X48: 02/02/1980 | Y48: TERZERA CRISTINA | Z48: Erogato | AA48: INFORCOOP ECIPA PIEMONTE | AB48: Incontro MDL | AC48: INFORCOOP ECIPA PIEMONTE VIA UGO PORZIO GIOVANOLA 7 - NOVARA | AG48: 60 | AH48: 06/02/2023 | AI48: TRZCST69B41F952V | AJ48: =VLOOKUP(exp_SILP!$Y48,'DATI CM'!$A$2:$F$28,2,FALSE) -> TRZCST69B41F952V
A49: =IFERROR(VLOOKUP(exp_SILP!$W49,exp_utenti_P!D:D,1,FALSE),"_DA INSERIRE") -> RLNGPP59H45H369E | B49: =IF(AND(exp_SILP!$S49="A.3 ORIENTAMENTO PROFESSIONALE",exp_SILP!$AD49="4.2"),"A.3 ORIENTAMENTO PROFESSIONALE (CARCERE)", IF(AND(exp_SILP!$S49="A.3 ORIENTAMENTO PROFESSIONALE",exp_SILP!$AD49="."),"A.3 ORIENTAMENTO PROFESSIONALE (CARCERE)", IF(AND(exp_SILP!$S49="A.4 CONSULENZA ORIENTATIVA",exp_SILP!$AD49="4.2"),"A.4 CONSULENZA ORIENTATIVA (CARCERE)", IF(AND(exp_SILP!$S49="A.4 CONSULENZA ORIENTATIVA",exp_SILP!$AD49="."),"A.4 CONSULENZA ORIENTATIVA (CARCERE)", IF(AND(exp_SILP!$S49="A.5 - LEP F1 - ACCOMPAGNAMENTO AL LAVORO",exp_SILP!$AD49="4.2"),"A.5 - LEP F1 - ACCOMPAGNAMENTO AL LAVORO (CARCERE)", IF(AND(exp_SILP!$S49="A.5 - LEP F1 - ACCOMPAGNAMENTO AL LAVORO",exp_SILP!$AD49="."),"A.5 - LEP F1 - ACCOMPAGNAMENTO AL LAVORO (CARCERE)", IF(AND(exp_SILP!$S49="A.5.2a - TUTORAGGIO TIROCINI",exp_SILP!$AD49="4.2"),"A.5.2a - TUTORAGGIO TIROCINI (CARCERE)", exp_SILP!$S49))))))) -> A4.10 - LEP E - ORIENTAMENTO SPECIALISTICO SKILL GAP ANALYSIS | C49: =CONCATENATE(VLOOKUP(exp_SILP!$B49,'DATI COMMESSE'!$A$2:$F$25,4,FALSE)," - ", VLOOKUP(exp_SILP!$B49,'DATI COMMESSE'!$A$2:$F$25,2,FALSE)," - ",VLOOKUP(exp_SILP!$B49,'DATI COMMESSE'!$A$2:$F$25,3,FALSE)) -> GOL - 22-02-5000 - 22-12-5003 | D49: =LEFT(exp_SILP!$R49,5) -> 17:00 | E49: =RIGHT(exp_SILP!$R49,5) -> 18:00 | F49: =IF(exp_SILP!$AG49>=60,exp_SILP!$AG49/60,exp_SILP!$AG49) -> 1 | G49: =VLOOKUP(exp_SILP!$Y49,'DATI CM'!$A$2:$F$28,2,FALSE) -> TRZCST69B41F952V | H49: =VLOOKUP(exp_SILP!$Y49,'DATI CM'!$A$2:$F$28,3,FALSE) | I49: =IF(A49>0,"N","N") -> N | J49: =VLOOKUP(exp_SILP!$Y49,'DATI CM'!$A$2:$F$28,4,FALSE) | K49: =VLOOKUP(exp_SILP!$B49,'DATI COMMESSE'!$A$2:$F$25,5,FALSE) -> 39.94 | L49: =IF(exp_SILP!$B49="A4.10 - LEP E - ORIENTAMENTO SPECIALISTICO SKILL GAP ANALYSIS - GRUPPO 3P",0,VLOOKUP(exp_SILP!$Y49,'DATI CM'!$A$2:$F$28,6,FALSE)) | M49: =IFERROR(VLOOKUP(exp_SILP!$B49,'DATI CM'!$H$2:$I$16,2,FALSE)*exp_SILP!$F49,0) -> 0 | N49: =VLOOKUP(exp_SILP!$B49,'DATI COMMESSE'!$A$2:$F$25,4,FALSE) -> GOL | O49: =VLOOKUP(exp_SILP!$B49,'DATI COMMESSE'!$A$2:$F$25,5,FALSE)*exp_SILP!$F49 -> 39.94 | P49: =IF(MID(exp_SILP!$W49,10,2)>"40","F","M") -> F | Q49: 02/02/2023 | R49: 17:00-18:00 | S49: A4.10 - LEP E - ORIENTAMENTO SPECIALISTICO SKILL GAP ANALYSIS | T49: Progetti per accreditati | V49: ORLANDIN GIUSEPPINA | W49: RLNGPP59H45H369E | X49: 05/06/1959 | Y49: TERZERA CRISTINA | Z49: Erogato | AA49: INFORCOOP ECIPA PIEMONTE | AB49: Incontro MDL | AC49: INFORCOOP ECIPA PIEMONTE VIA UGO PORZIO GIOVANOLA 7 - NOVARA | AG49: 60 | AH49: 23/02/2023 | AI49: TRZCST69B41F952V | AJ49: =VLOOKUP(exp_SILP!$Y49,'DATI CM'!$A$2:$F$28,2,FALSE) -> TRZCST69B41F952V
A50: =IFERROR(VLOOKUP(exp_SILP!$W50,exp_utenti_P!D:D,1,FALSE),"_DA INSERIRE") -> TRCJLA91D45F952B | B50: =IF(AND(exp_SILP!$S50="A.3 ORIENTAMENTO PROFESSIONALE",exp_SILP!$AD50="4.2"),"A.3 ORIENTAMENTO PROFESSIONALE (CARCERE)", IF(AND(exp_SILP!$S50="A.3 ORIENTAMENTO PROFESSIONALE",exp_SILP!$AD50="."),"A.3 ORIENTAMENTO PROFESSIONALE (CARCERE)", IF(AND(exp_SILP!$S50="A.4 CONSULENZA ORIENTATIVA",exp_SILP!$AD50="4.2"),"A.4 CONSULENZA ORIENTATIVA (CARCERE)", IF(AND(exp_SILP!$S50="A.4 CONSULENZA ORIENTATIVA",exp_SILP!$AD50="."),"A.4 CONSULENZA ORIENTATIVA (CARCERE)", IF(AND(exp_SILP!$S50="A.5 - LEP F1 - ACCOMPAGNAMENTO AL LAVORO",exp_SILP!$AD50="4.2"),"A.5 - LEP F1 - ACCOMPAGNAMENTO AL LAVORO (CARCERE)", IF(AND(exp_SILP!$S50="A.5 - LEP F1 - ACCOMPAGNAMENTO AL LAVORO",exp_SILP!$AD50="."),"A.5 - LEP F1 - ACCOMPAGNAMENTO AL LAVORO (CARCERE)", IF(AND(exp_SILP!$S50="A.5.2a - TUTORAGGIO TIROCINI",exp_SILP!$AD50="4.2"),"A.5.2a - TUTORAGGIO TIROCINI (CARCERE)", exp_SILP!$S50))))))) -> A4.10 - LEP E - ORIENTAMENTO SPECIALISTICO SKILL GAP ANALYSIS | C50: =CONCATENATE(VLOOKUP(exp_SILP!$B50,'DATI COMMESSE'!$A$2:$F$25,4,FALSE)," - ", VLOOKUP(exp_SILP!$B50,'DATI COMMESSE'!$A$2:$F$25,2,FALSE)," - ",VLOOKUP(exp_SILP!$B50,'DATI COMMESSE'!$A$2:$F$25,3,FALSE)) -> GOL - 22-02-5000 - 22-12-5003 | D50: =LEFT(exp_SILP!$R50,5) -> 14:00 | E50: =RIGHT(exp_SILP!$R50,5) -> 16:00 | F50: =IF(exp_SILP!$AG50>=60,exp_SILP!$AG50/60,exp_SILP!$AG50) -> 2 | G50: =VLOOKUP(exp_SILP!$Y50,'DATI CM'!$A$2:$F$28,2,FALSE) -> TRZCST69B41F952V | H50: =VLOOKUP(exp_SILP!$Y50,'DATI CM'!$A$2:$F$28,3,FALSE) | I50: =IF(A50>0,"N","N") -> N | J50: =VLOOKUP(exp_SILP!$Y50,'DATI CM'!$A$2:$F$28,4,FALSE) | K50: =VLOOKUP(exp_SILP!$B50,'DATI COMMESSE'!$A$2:$F$25,5,FALSE) -> 39.94 | L50: =IF(exp_SILP!$B50="A4.10 - LEP E - ORIENTAMENTO SPECIALISTICO SKILL GAP ANALYSIS - GRUPPO 3P",0,VLOOKUP(exp_SILP!$Y50,'DATI CM'!$A$2:$F$28,6,FALSE)) | M50: =IFERROR(VLOOKUP(exp_SILP!$B50,'DATI CM'!$H$2:$I$16,2,FALSE)*exp_SILP!$F50,0) -> 0 | N50: =VLOOKUP(exp_SILP!$B50,'DATI COMMESSE'!$A$2:$F$25,4,FALSE) -> GOL | O50: =VLOOKUP(exp_SILP!$B50,'DATI COMMESSE'!$A$2:$F$25,5,FALSE)*exp_SILP!$F50 -> 79.88 | P50: =IF(MID(exp_SILP!$W50,10,2)>"40","F","M") -> F | Q50: 02/02/2023 | R50: 14:00-16:00 | S50: A4.10 - LEP E - ORIENTAMENTO SPECIALISTICO SKILL GAP ANALYSIS | T50: Progetti per accreditati | V50: TURCO JAEL | W50: TRCJLA91D45F952B | X50: 05/04/1991 | Y50: TERZERA CRISTINA | Z50: Erogato | AA50: INFORCOOP ECIPA PIEMONTE | AB50: Incontro MDL | AC50: INFORCOOP ECIPA PIEMONTE VIA UGO PORZIO GIOVANOLA 7 - NOVARA | AG50: 120 | AH50: 06/02/2023 | AI50: TRZCST69B41F952V | AJ50: =VLOOKUP(exp_SILP!$Y50,'DATI CM'!$A$2:$F$28,2,FALSE) -> TRZCST69B41F952V
A51: =IFERROR(VLOOKUP(exp_SILP!$W51,exp_utenti_P!D:D,1,FALSE),"_DA INSERIRE") -> FLMBBR76L41L219Z | B51: =IF(AND(exp_SILP!$S51="A.3 ORIENTAMENTO PROFESSIONALE",exp_SILP!$AD51="4.2"),"A.3 ORIENTAMENTO PROFESSIONALE (CARCERE)", IF(AND(exp_SILP!$S51="A.3 ORIENTAMENTO PROFESSIONALE",exp_SILP!$AD51="."),"A.3 ORIENTAMENTO PROFESSIONALE (CARCERE)", IF(AND(exp_SILP!$S51="A.4 CONSULENZA ORIENTATIVA",exp_SILP!$AD51="4.2"),"A.4 CONSULENZA ORIENTATIVA (CARCERE)", IF(AND(exp_SILP!$S51="A.4 CONSULENZA ORIENTATIVA",exp_SILP!$AD51="."),"A.4 CONSULENZA ORIENTATIVA (CARCERE)", IF(AND(exp_SILP!$S51="A.5 - LEP F1 - ACCOMPAGNAMENTO AL LAVORO",exp_SILP!$AD51="4.2"),"A.5 - LEP F1 - ACCOMPAGNAMENTO AL LAVORO (CARCERE)", IF(AND(exp_SILP!$S51="A.5 - LEP F1 - ACCOMPAGNAMENTO AL LAVORO",exp_SILP!$AD51="."),"A.5 - LEP F1 - ACCOMPAGNAMENTO AL LAVORO (CARCERE)", IF(AND(exp_SILP!$S51="A.5.2a - TUTORAGGIO TIROCINI",exp_SILP!$AD51="4.2"),"A.5.2a - TUTORAGGIO TIROCINI (CARCERE)", exp_SILP!$S51))))))) -> A4.10 - LEP E - ORIENTAMENTO SPECIALISTICO SKILL GAP ANALYSIS | C51: =CONCATENATE(VLOOKUP(exp_SILP!$B51,'DATI COMMESSE'!$A$2:$F$25,4,FALSE)," - ", VLOOKUP(exp_SILP!$B51,'DATI COMMESSE'!$A$2:$F$25,2,FALSE)," - ",VLOOKUP(exp_SILP!$B51,'DATI COMMESSE'!$A$2:$F$25,3,FALSE)) -> GOL - 22-02-5000 - 22-12-5003 | D51: =LEFT(exp_SILP!$R51,5) -> 14:00 | E51: =RIGHT(exp_SILP!$R51,5) -> 15:00 | F51: =IF(exp_SILP!$AG51>=60,exp_SILP!$AG51/60,exp_SILP!$AG51) -> 1 | G51: =VLOOKUP(exp_SILP!$Y51,'DATI CM'!$A$2:$F$28,2,FALSE) -> FLCSRN79S42L219X | H51: =VLOOKUP(exp_SILP!$Y51,'DATI CM'!$A$2:$F$28,3,FALSE) -> A011 | I51: =IF(A51>0,"N","N") -> N | J51: =VLOOKUP(exp_SILP!$Y51,'DATI CM'!$A$2:$F$28,4,FALSE) -> TORINO | K51: =VLOOKUP(exp_SILP!$B51,'DATI COMMESSE'!$A$2:$F$25,5,FALSE) -> 39.94 | L51: =IF(exp_SILP!$B51="A4.10 - LEP E - ORIENTAMENTO SPECIALISTICO SKILL GAP ANALYSIS - GRUPPO 3P",0,VLOOKUP(exp_SILP!$Y51,'DATI CM'!$A$2:$F$28,6,FALSE)) -> 25 | M51: =IFERROR(VLOOKUP(exp_SILP!$B51,'DATI CM'!$H$2:$I$16,2,FALSE)*exp_SILP!$F51,0) -> 0 | N51: =VLOOKUP(exp_SILP!$B51,'DATI COMMESSE'!$A$2:$F$25,4,FALSE) -> GOL | O51: =VLOOKUP(exp_SILP!$B51,'DATI COMMESSE'!$A$2:$F$25,5,FALSE)*exp_SILP!$F51 -> 39.94 | P51: =IF(MID(exp_SILP!$W51,10,2)>"40","F","M") -> F | Q51: 02/02/2023 | R51: 14:00-15:00 | S51: A4.10 - LEP E - ORIENTAMENTO SPECIALISTICO SKILL GAP ANALYSIS | T51: Progetti per accreditati | V51: FLAMANO BARBARA | W51: FLMBBR76L41L219Z | X51: 01/07/1976 | Y51: FALCONE SERENA | Z51: Erogato | AA51: INFORCOOP ECIPA PIEMONTE | AB51: Incontro MDLpresentato | AC51: INFORCOOP ECIPA PIEMONTE VIA LIVORNO 53/b - TORINO | AG51: 60 | AH51: 09/02/2023 | AI51: FLCSRN79S42L219X | AJ51: =VLOOKUP(exp_SILP!$Y51,'DATI CM'!$A$2:$F$28,2,FALSE) -> FLCSRN79S42L219X
A52: =IFERROR(VLOOKUP(exp_SILP!$W52,exp_utenti_P!D:D,1,FALSE),"_DA INSERIRE") -> FRTLRI79M43L219I | B52: =IF(AND(exp_SILP!$S52="A.3 ORIENTAMENTO PROFESSIONALE",exp_SILP!$AD52="4.2"),"A.3 ORIENTAMENTO PROFESSIONALE (CARCERE)", IF(AND(exp_SILP!$S52="A.3 ORIENTAMENTO PROFESSIONALE",exp_SILP!$AD52="."),"A.3 ORIENTAMENTO PROFESSIONALE (CARCERE)", IF(AND(exp_SILP!$S52="A.4 CONSULENZA ORIENTATIVA",exp_SILP!$AD52="4.2"),"A.4 CONSULENZA ORIENTATIVA (CARCERE)", IF(AND(exp_SILP!$S52="A.4 CONSULENZA ORIENTATIVA",exp_SILP!$AD52="."),"A.4 CONSULENZA ORIENTATIVA (CARCERE)", IF(AND(exp_SILP!$S52="A.5 - LEP F1 - ACCOMPAGNAMENTO AL LAVORO",exp_SILP!$AD52="4.2"),"A.5 - LEP F1 - ACCOMPAGNAMENTO AL LAVORO (CARCERE)", IF(AND(exp_SILP!$S52="A.5 - LEP F1 - ACCOMPAGNAMENTO AL LAVORO",exp_SILP!$AD52="."),"A.5 - LEP F1 - ACCOMPAGNAMENTO AL LAVORO (CARCERE)", IF(AND(exp_SILP!$S52="A.5.2a - TUTORAGGIO TIROCINI",exp_SILP!$AD52="4.2"),"A.5.2a - TUTORAGGIO TIROCINI (CARCERE)", exp_SILP!$S52))))))) -> A4.10 - LEP E - ORIENTAMENTO SPECIALISTICO SKILL GAP ANALYSIS | C52: =CONCATENATE(VLOOKUP(exp_SILP!$B52,'DATI COMMESSE'!$A$2:$F$25,4,FALSE)," - ", VLOOKUP(exp_SILP!$B52,'DATI COMMESSE'!$A$2:$F$25,2,FALSE)," - ",VLOOKUP(exp_SILP!$B52,'DATI COMMESSE'!$A$2:$F$25,3,FALSE)) -> GOL - 22-02-5000 - 22-12-5003 | D52: =LEFT(exp_SILP!$R52,5) -> 15:00 | E52: =RIGHT(exp_SILP!$R52,5) -> 17:00 | F52: =IF(exp_SILP!$AG52>=60,exp_SILP!$AG52/60,exp_SILP!$AG52) -> 2 | G52: =VLOOKUP(exp_SILP!$Y52,'DATI CM'!$A$2:$F$28,2,FALSE) -> FLCSRN79S42L219X | H52: =VLOOKUP(exp_SILP!$Y52,'DATI CM'!$A$2:$F$28,3,FALSE) -> A011 | I52: =IF(A52>0,"N","N") -> N | J52: =VLOOKUP(exp_SILP!$Y52,'DATI CM'!$A$2:$F$28,4,FALSE) -> TORINO | K52: =VLOOKUP(exp_SILP!$B52,'DATI COMMESSE'!$A$2:$F$25,5,FALSE) -> 39.94 | L52: =IF(exp_SILP!$B52="A4.10 - LEP E - ORIENTAMENTO SPECIALISTICO SKILL GAP ANALYSIS - GRUPPO 3P",0,VLOOKUP(exp_SILP!$Y52,'DATI CM'!$A$2:$F$28,6,FALSE)) -> 25 | M52: =IFERROR(VLOOKUP(exp_SILP!$B52,'DATI CM'!$H$2:$I$16,2,FALSE)*exp_SILP!$F52,0) -> 0 | N52: =VLOOKUP(exp_SILP!$B52,'DATI COMMESSE'!$A$2:$F$25,4,FALSE) -> GOL | O52: =VLOOKUP(exp_SILP!$B52,'DATI COMMESSE'!$A$2:$F$25,5,FALSE)*exp_SILP!$F52 -> 79.88 | P52: =IF(MID(exp_SILP!$W52,10,2)>"40","F","M") -> F | Q52: 02/02/2023 | R52: 15:00-17:00 | S52: A4.10 - LEP E - ORIENTAMENTO SPECIALISTICO SKILL GAP ANALYSIS | T52: Progetti per accreditati | V52: FORTINA ILARIA | W52: FRTLRI79M43L219I | X52: 03/08/1979 | Y52: FALCONE SERENA | Z52: Erogato | AA52: INFORCOOP ECIPA PIEMONTE | AB52: Incontro MDLpresentato | AC52: INFORCOOP ECIPA PIEMONTE VIA LIVORNO 53/b - TORINO | AG52: 120 | AH52: 09/02/2023 | AI52: FLCSRN79S42L219X | AJ52: =VLOOKUP(exp_SILP!$Y52,'DATI CM'!$A$2:$F$28,2,FALSE) -> FLCSRN79S42L219X
A53: =IFERROR(VLOOKUP(exp_SILP!$W53,exp_utenti_P!D:D,1,FALSE),"_DA INSERIRE") -> KHNSBH76R46Z330K | B53: =IF(AND(exp_SILP!$S53="A.3 ORIENTAMENTO PROFESSIONALE",exp_SILP!$AD53="4.2"),"A.3 ORIENTAMENTO PROFESSIONALE (CARCERE)", IF(AND(exp_SILP!$S53="A.3 ORIENTAMENTO PROFESSIONALE",exp_SILP!$AD53="."),"A.3 ORIENTAMENTO PROFESSIONALE (CARCERE)", IF(AND(exp_SILP!$S53="A.4 CONSULENZA ORIENTATIVA",exp_SILP!$AD53="4.2"),"A.4 CONSULENZA ORIENTATIVA (CARCERE)", IF(AND(exp_SILP!$S53="A.4 CONSULENZA ORIENTATIVA",exp_SILP!$AD53="."),"A.4 CONSULENZA ORIENTATIVA (CARCERE)", IF(AND(exp_SILP!$S53="A.5 - LEP F1 - ACCOMPAGNAMENTO AL LAVORO",exp_SILP!$AD53="4.2"),"A.5 - LEP F1 - ACCOMPAGNAMENTO AL LAVORO (CARCERE)", IF(AND(exp_SILP!$S53="A.5 - LEP F1 - ACCOMPAGNAMENTO AL LAVORO",exp_SILP!$AD53="."),"A.5 - LEP F1 - ACCOMPAGNAMENTO AL LAVORO (CARCERE)", IF(AND(exp_SILP!$S53="A.5.2a - TUTORAGGIO TIROCINI",exp_SILP!$AD53="4.2"),"A.5.2a - TUTORAGGIO TIROCINI (CARCERE)", exp_SILP!$S53))))))) -> A4.10 - LEP E - ORIENTAMENTO SPECIALISTICO SKILL GAP ANALYSIS | C53: =CONCATENATE(VLOOKUP(exp_SILP!$B53,'DATI COMMESSE'!$A$2:$F$25,4,FALSE)," - ", VLOOKUP(exp_SILP!$B53,'DATI COMMESSE'!$A$2:$F$25,2,FALSE)," - ",VLOOKUP(exp_SILP!$B53,'DATI COMMESSE'!$A$2:$F$25,3,FALSE)) -> GOL - 22-02-5000 - 22-12-5003 | D53: =LEFT(exp_SILP!$R53,5) -> 12:00 | E53: =RIGHT(exp_SILP!$R53,5) -> 13:00 | F53: =IF(exp_SILP!$AG53>=60,exp_SILP!$AG53/60,exp_SILP!$AG53) -> 1 | G53: =VLOOKUP(exp_SILP!$Y53,'DATI CM'!$A$2:$F$28,2,FALSE) -> PNFMRT85H50A859E | H53: =VLOOKUP(exp_SILP!$Y53,'DATI CM'!$A$2:$F$28,3,FALSE) -> A011 | I53: =IF(A53>0,"N","N") -> N | J53: =VLOOKUP(exp_SILP!$Y53,'DATI CM'!$A$2:$F$28,4,FALSE) -> BIELLA | K53: =VLOOKUP(exp_SILP!$B53,'DATI COMMESSE'!$A$2:$F$25,5,FALSE) -> 39.94 | L53: =IF(exp_SILP!$B53="A4.10 - LEP E - ORIENTAMENTO SPECIALISTICO SKILL GAP ANALYSIS - GRUPPO 3P",0,VLOOKUP(exp_SILP!$Y53,'DATI CM'!$A$2:$F$28,6,FALSE)) -> 25 | M53: =IFERROR(VLOOKUP(exp_SILP!$B53,'DATI CM'!$H$2:$I$16,2,FALSE)*exp_SILP!$F53,0) -> 0 | N53: =VLOOKUP(exp_SILP!$B53,'DATI COMMESSE'!$A$2:$F$25,4,FALSE) -> GOL | O53: =VLOOKUP(exp_SILP!$B53,'DATI COMMESSE'!$A$2:$F$25,5,FALSE)*exp_SILP!$F53 -> 39.94 | P53: =IF(MID(exp_SILP!$W53,10,2)>"40","F","M") -> F | Q53: 02/02/2023 | R53: 12:00-13:00 | S53: A4.10 - LEP E - ORIENTAMENTO SPECIALISTICO SKILL GAP ANALYSIS | T53: Progetti per accreditati | V53: KHONCHAF SABAH | W53: KHNSBH76R46Z330K | X53: 06/10/1976 | Y53: PIANOFORTE MARTA | Z53: Erogato | AA53: INFORCOOP ECIPA PIEMONTE | AB53: Incontro MDL | AC53: INFORCOOP ECIPA PIEMONTE STRADA CAMPAGNE' 7 - BIELLA | AG53: 60 | AH53: 02/02/2023 | AI53: PNFMRT85H50A859E | AJ53: =VLOOKUP(exp_SILP!$Y53,'DATI CM'!$A$2:$F$28,2,FALSE) -> PNFMRT85H50A859E
A54: =IFERROR(VLOOKUP(exp_SILP!$W54,exp_utenti_P!D:D,1,FALSE),"_DA INSERIRE") -> MRTLNZ01R29A859B | B54: =IF(AND(exp_SILP!$S54="A.3 ORIENTAMENTO PROFESSIONALE",exp_SILP!$AD54="4.2"),"A.3 ORIENTAMENTO PROFESSIONALE (CARCERE)", IF(AND(exp_SILP!$S54="A.3 ORIENTAMENTO PROFESSIONALE",exp_SILP!$AD54="."),"A.3 ORIENTAMENTO PROFESSIONALE (CARCERE)", IF(AND(exp_SILP!$S54="A.4 CONSULENZA ORIENTATIVA",exp_SILP!$AD54="4.2"),"A.4 CONSULENZA ORIENTATIVA (CARCERE)", IF(AND(exp_SILP!$S54="A.4 CONSULENZA ORIENTATIVA",exp_SILP!$AD54="."),"A.4 CONSULENZA ORIENTATIVA (CARCERE)", IF(AND(exp_SILP!$S54="A.5 - LEP F1 - ACCOMPAGNAMENTO AL LAVORO",exp_SILP!$AD54="4.2"),"A.5 - LEP F1 - ACCOMPAGNAMENTO AL LAVORO (CARCERE)", IF(AND(exp_SILP!$S54="A.5 - LEP F1 - ACCOMPAGNAMENTO AL LAVORO",exp_SILP!$AD54="."),"A.5 - LEP F1 - ACCOMPAGNAMENTO AL LAVORO (CARCERE)", IF(AND(exp_SILP!$S54="A.5.2a - TUTORAGGIO TIROCINI",exp_SILP!$AD54="4.2"),"A.5.2a - TUTORAGGIO TIROCINI (CARCERE)", exp_SILP!$S54))))))) -> A4.10 - LEP E - ORIENTAMENTO SPECIALISTICO SKILL GAP ANALYSIS | C54: =CONCATENATE(VLOOKUP(exp_SILP!$B54,'DATI COMMESSE'!$A$2:$F$25,4,FALSE)," - ", VLOOKUP(exp_SILP!$B54,'DATI COMMESSE'!$A$2:$F$25,2,FALSE)," - ",VLOOKUP(exp_SILP!$B54,'DATI COMMESSE'!$A$2:$F$25,3,FALSE)) -> GOL - 22-02-5000 - 22-12-5003 | D54: =LEFT(exp_SILP!$R54,5) -> 13:00 | E54: =RIGHT(exp_SILP!$R54,5) -> 14:00 | F54: =IF(exp_SILP!$AG54>=60,exp_SILP!$AG54/60,exp_SILP!$AG54) -> 1 | G54: =VLOOKUP(exp_SILP!$Y54,'DATI CM'!$A$2:$F$28,2,FALSE) -> PNFMRT85H50A859E | H54: =VLOOKUP(exp_SILP!$Y54,'DATI CM'!$A$2:$F$28,3,FALSE) -> A011 | I54: =IF(A54>0,"N","N") -> N | J54: =VLOOKUP(exp_SILP!$Y54,'DATI CM'!$A$2:$F$28,4,FALSE) -> BIELLA | K54: =VLOOKUP(exp_SILP!$B54,'DATI COMMESSE'!$A$2:$F$25,5,FALSE) -> 39.94 | L54: =IF(exp_SILP!$B54="A4.10 - LEP E - ORIENTAMENTO SPECIALISTICO SKILL GAP ANALYSIS - GRUPPO 3P",0,VLOOKUP(exp_SILP!$Y54,'DATI CM'!$A$2:$F$28,6,FALSE)) -> 25 | M54: =IFERROR(VLOOKUP(exp_SILP!$B54,'DATI CM'!$H$2:$I$16,2,FALSE)*exp_SILP!$F54,0) -> 0 | N54: =VLOOKUP(exp_SILP!$B54,'DATI COMMESSE'!$A$2:$F$25,4,FALSE) -> GOL | O54: =VLOOKUP(exp_SILP!$B54,'DATI COMMESSE'!$A$2:$F$25,5,FALSE)*exp_SILP!$F54 -> 39.94 | P54: =IF(MID(exp_SILP!$W54,10,2)>"40","F","M") -> M | Q54: 02/02/2023 | R54: 13:00-14:00 | S54: A4.10 - LEP E - ORIENTAMENTO SPECIALISTICO SKILL GAP ANALYSIS | T54: Progetti per accreditati | V54: MORETTO LORENZO | W54: MRTLNZ01R29A859B | X54: 29/10/2001 | Y54: PIANOFORTE MARTA | Z54: Erogato | AA54: INFORCOOP ECIPA PIEMONTE | AB54: Incontro MDL | AC54: INFORCOOP ECIPA PIEMONTE STRADA CAMPAGNE' 7 - BIELLA | AG54: 60 | AH54: 02/02/2023 | AI54: PNFMRT85H50A859E | AJ54: =VLOOKUP(exp_SILP!$Y54,'DATI CM'!$A$2:$F$28,2,FALSE) -> PNFMRT85H50A859E
A55: =IFERROR(VLOOKUP(exp_SILP!$W55,exp_utenti_P!D:D,1,FALSE),"_DA INSERIRE") -> VLPRCC63A01A662P | B55: =IF(AND(exp_SILP!$S55="A.3 ORIENTAMENTO PROFESSIONALE",exp_SILP!$AD55="4.2"),"A.3 ORIENTAMENTO PROFESSIONALE (CARCERE)", IF(AND(exp_SILP!$S55="A.3 ORIENTAMENTO PROFESSIONALE",exp_SILP!$AD55="."),"A.3 ORIENTAMENTO PROFESSIONALE (CARCERE)", IF(AND(exp_SILP!$S55="A.4 CONSULENZA ORIENTATIVA",exp_SILP!$AD55="4.2"),"A.4 CONSULENZA ORIENTATIVA (CARCERE)", IF(AND(exp_SILP!$S55="A.4 CONSULENZA ORIENTATIVA",exp_SILP!$AD55="."),"A.4 CONSULENZA ORIENTATIVA (CARCERE)", IF(AND(exp_SILP!$S55="A.5 - LEP F1 - ACCOMPAGNAMENTO AL LAVORO",exp_SILP!$AD55="4.2"),"A.5 - LEP F1 - ACCOMPAGNAMENTO AL LAVORO (CARCERE)", IF(AND(exp_SILP!$S55="A.5 - LEP F1 - ACCOMPAGNAMENTO AL LAVORO",exp_SILP!$AD55="."),"A.5 - LEP F1 - ACCOMPAGNAMENTO AL LAVORO (CARCERE)", IF(AND(exp_SILP!$S55="A.5.2a - TUTORAGGIO TIROCINI",exp_SILP!$AD55="4.2"),"A.5.2a - TUTORAGGIO TIROCINI (CARCERE)", exp_SILP!$S55))))))) -> A4.10 - LEP E - ORIENTAMENTO SPECIALISTICO SKILL GAP ANALYSIS | C55: =CONCATENATE(VLOOKUP(exp_SILP!$B55,'DATI COMMESSE'!$A$2:$F$25,4,FALSE)," - ", VLOOKUP(exp_SILP!$B55,'DATI COMMESSE'!$A$2:$F$25,2,FALSE)," - ",VLOOKUP(exp_SILP!$B55,'DATI COMMESSE'!$A$2:$F$25,3,FALSE)) -> GOL - 22-02-5000 - 22-12-5003 | D55: =LEFT(exp_SILP!$R55,5) -> 14:00 | E55: =RIGHT(exp_SILP!$R55,5) -> 16:00 | F55: =IF(exp_SILP!$AG55>=60,exp_SILP!$AG55/60,exp_SILP!$AG55) -> 2 | G55: =VLOOKUP(exp_SILP!$Y55,'DATI CM'!$A$2:$F$28,2,FALSE) -> PNFMRT85H50A859E | H55: =VLOOKUP(exp_SILP!$Y55,'DATI CM'!$A$2:$F$28,3,FALSE) -> A011 | I55: =IF(A55>0,"N","N") -> N | J55: =VLOOKUP(exp_SILP!$Y55,'DATI CM'!$A$2:$F$28,4,FALSE) -> BIELLA | K55: =VLOOKUP(exp_SILP!$B55,'DATI COMMESSE'!$A$2:$F$25,5,FALSE) -> 39.94 | L55: =IF(exp_SILP!$B55="A4.10 - LEP E - ORIENTAMENTO SPECIALISTICO SKILL GAP ANALYSIS - GRUPPO 3P",0,VLOOKUP(exp_SILP!$Y55,'DATI CM'!$A$2:$F$28,6,FALSE)) -> 25 | M55: =IFERROR(VLOOKUP(exp_SILP!$B55,'DATI CM'!$H$2:$I$16,2,FALSE)*exp_SILP!$F55,0) -> 0 | N55: =VLOOKUP(exp_SILP!$B55,'DATI COMMESSE'!$A$2:$F$25,4,FALSE) -> GOL | O55: =VLOOKUP(exp_SILP!$B55,'DATI COMMESSE'!$A$2:$F$25,5,FALSE)*exp_SILP!$F55 -> 79.88 | P55: =IF(MID(exp_SILP!$W55,10,2)>"40","F","M") -> M | Q55: 02/02/2023 | R55: 14:00-16:00 | S55: A4.10 - LEP E - ORIENTAMENTO SPECIALISTICO SKILL GAP ANALYSIS | T55: Progetti per accreditati | V55: VOLPICELLA ROCCO | W55: VLPRCC63A01A662P | X55: 01/01/1963 | Y55: PIANOFORTE MARTA | Z55: Erogato | AA55: INFORCOOP ECIPA PIEMONTE | AB55: Incontro MDL | AC55: INFORCOOP ECIPA PIEMONTE STRADA CAMPAGNE' 7 - BIELLA | AG55: 120 | AH55: 06/02/2023 | AI55: PNFMRT85H50A859E | AJ55: =VLOOKUP(exp_SILP!$Y55,'DATI CM'!$A$2:$F$28,2,FALSE) -> PNFMRT85H50A859E
A56: =IFERROR(VLOOKUP(exp_SILP!$W56,exp_utenti_P!D:D,1,FALSE),"_DA INSERIRE") -> STRGRY71L08C627Y | B56: =IF(AND(exp_SILP!$S56="A.3 ORIENTAMENTO PROFESSIONALE",exp_SILP!$AD56="4.2"),"A.3 ORIENTAMENTO PROFESSIONALE (CARCERE)", IF(AND(exp_SILP!$S56="A.3 ORIENTAMENTO PROFESSIONALE",exp_SILP!$AD56="."),"A.3 ORIENTAMENTO PROFESSIONALE (CARCERE)", IF(AND(exp_SILP!$S56="A.4 CONSULENZA ORIENTATIVA",exp_SILP!$AD56="4.2"),"A.4 CONSULENZA ORIENTATIVA (CARCERE)", IF(AND(exp_SILP!$S56="A.4 CONSULENZA ORIENTATIVA",exp_SILP!$AD56="."),"A.4 CONSULENZA ORIENTATIVA (CARCERE)", IF(AND(exp_SILP!$S56="A.5 - LEP F1 - ACCOMPAGNAMENTO AL LAVORO",exp_SILP!$AD56="4.2"),"A.5 - LEP F1 - ACCOMPAGNAMENTO AL LAVORO (CARCERE)", IF(AND(exp_SILP!$S56="A.5 - LEP F1 - ACCOMPAGNAMENTO AL LAVORO",exp_SILP!$AD56="."),"A.5 - LEP F1 - ACCOMPAGNAMENTO AL LAVORO (CARCERE)", IF(AND(exp_SILP!$S56="A.5.2a - TUTORAGGIO TIROCINI",exp_SILP!$AD56="4.2"),"A.5.2a - TUTORAGGIO TIROCINI (CARCERE)", exp_SILP!$S56))))))) -> A4.10 - LEP E - ORIENTAMENTO SPECIALISTICO SKILL GAP ANALYSIS | C56: =CONCATENATE(VLOOKUP(exp_SILP!$B56,'DATI COMMESSE'!$A$2:$F$25,4,FALSE)," - ", VLOOKUP(exp_SILP!$B56,'DATI COMMESSE'!$A$2:$F$25,2,FALSE)," - ",VLOOKUP(exp_SILP!$B56,'DATI COMMESSE'!$A$2:$F$25,3,FALSE)) -> GOL - 22-02-5000 - 22-12-5003 | D56: =LEFT(exp_SILP!$R56,5) -> 08:00 | E56: =RIGHT(exp_SILP!$R56,5) -> 09:00 | F56: =IF(exp_SILP!$AG56>=60,exp_SILP!$AG56/60,exp_SILP!$AG56) -> 1 | G56: =VLOOKUP(exp_SILP!$Y56,'DATI CM'!$A$2:$F$28,2,FALSE) -> FLCSRN79S42L219X | H56: =VLOOKUP(exp_SILP!$Y56,'DATI CM'!$A$2:$F$28,3,FALSE) -> A011 | I56: =IF(A56>0,"N","N") -> N | J56: =VLOOKUP(exp_SILP!$Y56,'DATI CM'!$A$2:$F$28,4,FALSE) -> TORINO | K56: =VLOOKUP(exp_SILP!$B56,'DATI COMMESSE'!$A$2:$F$25,5,FALSE) -> 39.94 | L56: =IF(exp_SILP!$B56="A4.10 - LEP E - ORIENTAMENTO SPECIALISTICO SKILL GAP ANALYSIS - GRUPPO 3P",0,VLOOKUP(exp_SILP!$Y56,'DATI CM'!$A$2:$F$28,6,FALSE)) -> 25 | M56: =IFERROR(VLOOKUP(exp_SILP!$B56,'DATI CM'!$H$2:$I$16,2,FALSE)*exp_SILP!$F56,0) -> 0 | N56: =VLOOKUP(exp_SILP!$B56,'DATI COMMESSE'!$A$2:$F$25,4,FALSE) -> GOL | O56: =VLOOKUP(exp_SILP!$B56,'DATI COMMESSE'!$A$2:$F$25,5,FALSE)*exp_SILP!$F56 -> 39.94 | P56: =IF(MID(exp_SILP!$W56,10,2)>"40","F","M") -> M | Q56: 02/03/2023 | R56: 08:00-09:00 | S56: A4.10 - LEP E - ORIENTAMENTO SPECIALISTICO SKILL GAP ANALYSIS | T56: Progetti per accreditati | V56: STRIANO GERRY | W56: STRGRY71L08C627Y | X56: 08/07/1971 | Y56: FALCONE SERENA | Z56: Erogato | AA56: INFORCOOP ECIPA PIEMONTE | AB56: Incontro MDL | AC56: INFORCOOP ECIPA PIEMONTE VIA LIVORNO 53/b - TORINO | AF56: BACK OFFICE | AG56: 60 | AH56: 03/03/2023 | AI56: FLCSRN79S42L219X | AJ56: =VLOOKUP(exp_SILP!$Y56,'DATI CM'!$A$2:$F$28,2,FALSE) -> FLCSRN79S42L219X
A57: =IFERROR(VLOOKUP(exp_SILP!$W57,exp_utenti_P!D:D,1,FALSE),"_DA INSERIRE") -> BLHSDO80B42Z330B | B57: =IF(AND(exp_SILP!$S57="A.3 ORIENTAMENTO PROFESSIONALE",exp_SILP!$AD57="4.2"),"A.3 ORIENTAMENTO PROFESSIONALE (CARCERE)", IF(AND(exp_SILP!$S57="A.3 ORIENTAMENTO PROFESSIONALE",exp_SILP!$AD57="."),"A.3 ORIENTAMENTO PROFESSIONALE (CARCERE)", IF(AND(exp_SILP!$S57="A.4 CONSULENZA ORIENTATIVA",exp_SILP!$AD57="4.2"),"A.4 CONSULENZA ORIENTATIVA (CARCERE)", IF(AND(exp_SILP!$S57="A.4 CONSULENZA ORIENTATIVA",exp_SILP!$AD57="."),"A.4 CONSULENZA ORIENTATIVA (CARCERE)", IF(AND(exp_SILP!$S57="A.5 - LEP F1 - ACCOMPAGNAMENTO AL LAVORO",exp_SILP!$AD57="4.2"),"A.5 - LEP F1 - ACCOMPAGNAMENTO AL LAVORO (CARCERE)", IF(AND(exp_SILP!$S57="A.5 - LEP F1 - ACCOMPAGNAMENTO AL LAVORO",exp_SILP!$AD57="."),"A.5 - LEP F1 - ACCOMPAGNAMENTO AL LAVORO (CARCERE)", IF(AND(exp_SILP!$S57="A.5.2a - TUTORAGGIO TIROCINI",exp_SILP!$AD57="4.2"),"A.5.2a - TUTORAGGIO TIROCINI (CARCERE)", exp_SILP!$S57))))))) -> A4.10 - LEP E - ORIENTAMENTO SPECIALISTICO SKILL GAP ANALYSIS | C57: =CONCATENATE(VLOOKUP(exp_SILP!$B57,'DATI COMMESSE'!$A$2:$F$25,4,FALSE)," - ", VLOOKUP(exp_SILP!$B57,'DATI COMMESSE'!$A$2:$F$25,2,FALSE)," - ",VLOOKUP(exp_SILP!$B57,'DATI COMMESSE'!$A$2:$F$25,3,FALSE)) -> GOL - 22-02-5000 - 22-12-5003 | D57: =LEFT(exp_SILP!$R57,5) -> 11:00 | E57: =RIGHT(exp_SILP!$R57,5) -> 12:00 | F57: =IF(exp_SILP!$AG57>=60,exp_SILP!$AG57/60,exp_SILP!$AG57) -> 1 | G57: =VLOOKUP(exp_SILP!$Y57,'DATI CM'!$A$2:$F$28,2,FALSE) -> TRZCST69B41F952V | H57: =VLOOKUP(exp_SILP!$Y57,'DATI CM'!$A$2:$F$28,3,FALSE) | I57: =IF(A57>0,"N","N") -> N | J57: =VLOOKUP(exp_SILP!$Y57,'DATI CM'!$A$2:$F$28,4,FALSE) | K57: =VLOOKUP(exp_SILP!$B57,'DATI COMMESSE'!$A$2:$F$25,5,FALSE) -> 39.94 | L57: =IF(exp_SILP!$B57="A4.10 - LEP E - ORIENTAMENTO SPECIALISTICO SKILL GAP ANALYSIS - GRUPPO 3P",0,VLOOKUP(exp_SILP!$Y57,'DATI CM'!$A$2:$F$28,6,FALSE)) | M57: =IFERROR(VLOOKUP(exp_SILP!$B57,'DATI CM'!$H$2:$I$16,2,FALSE)*exp_SILP!$F57,0) -> 0 | N57: =VLOOKUP(exp_SILP!$B57,'DATI COMMESSE'!$A$2:$F$25,4,FALSE) -> GOL | O57: =VLOOKUP(exp_SILP!$B57,'DATI COMMESSE'!$A$2:$F$25,5,FALSE)*exp_SILP!$F57 -> 39.94 | P57: =IF(MID(exp_SILP!$W57,10,2)>"40","F","M") -> F | Q57: 02/03/2023 | R57: 11:00-12:00 | S57: A4.10 - LEP E - ORIENTAMENTO SPECIALISTICO SKILL GAP ANALYSIS | T57: Progetti per accreditati | V57: BELHADJ SOUAD | W57: BLHSDO80B42Z330B | X57: 02/02/1980 | Y57: TERZERA CRISTINA | Z57: Erogato | AA57: INFORCOOP ECIPA PIEMONTE | AB57: Incontro MDL | AC57: INFORCOOP ECIPA PIEMONTE VIA UGO PORZIO GIOVANOLA 7 - NOVARA | AG57: 60 | AH57: 02/03/2023 | AI57: TRZCST69B41F952V | AJ57: =VLOOKUP(exp_SILP!$Y57,'DATI CM'!$A$2:$F$28,2,FALSE) -> TRZCST69B41F952V
A58: =IFERROR(VLOOKUP(exp_SILP!$W58,exp_utenti_P!D:D,1,FALSE),"_DA INSERIRE") -> CHRLKY97A01Z335E | B58: =IF(AND(exp_SILP!$S58="A.3 ORIENTAMENTO PROFESSIONALE",exp_SILP!$AD58="4.2"),"A.3 ORIENTAMENTO PROFESSIONALE (CARCERE)", IF(AND(exp_SILP!$S58="A.3 ORIENTAMENTO PROFESSIONALE",exp_SILP!$AD58="."),"A.3 ORIENTAMENTO PROFESSIONALE (CARCERE)", IF(AND(exp_SILP!$S58="A.4 CONSULENZA ORIENTATIVA",exp_SILP!$AD58="4.2"),"A.4 CONSULENZA ORIENTATIVA (CARCERE)", IF(AND(exp_SILP!$S58="A.4 CONSULENZA ORIENTATIVA",exp_SILP!$AD58="."),"A.4 CONSULENZA ORIENTATIVA (CARCERE)", IF(AND(exp_SILP!$S58="A.5 - LEP F1 - ACCOMPAGNAMENTO AL LAVORO",exp_SILP!$AD58="4.2"),"A.5 - LEP F1 - ACCOMPAGNAMENTO AL LAVORO (CARCERE)", IF(AND(exp_SILP!$S58="A.5 - LEP F1 - ACCOMPAGNAMENTO AL LAVORO",exp_SILP!$AD58="."),"A.5 - LEP F1 - ACCOMPAGNAMENTO AL LAVORO (CARCERE)", IF(AND(exp_SILP!$S58="A.5.2a - TUTORAGGIO TIROCINI",exp_SILP!$AD58="4.2"),"A.5.2a - TUTORAGGIO TIROCINI (CARCERE)", exp_SILP!$S58))))))) -> A4.10 - LEP E - ORIENTAMENTO SPECIALISTICO SKILL GAP ANALYSIS | C58: =CONCATENATE(VLOOKUP(exp_SILP!$B58,'DATI COMMESSE'!$A$2:$F$25,4,FALSE)," - ", VLOOKUP(exp_SILP!$B58,'DATI COMMESSE'!$A$2:$F$25,2,FALSE)," - ",VLOOKUP(exp_SILP!$B58,'DATI COMMESSE'!$A$2:$F$25,3,FALSE)) -> GOL - 22-02-5000 - 22-12-5003 | D58: =LEFT(exp_SILP!$R58,5) -> 10:00 | E58: =RIGHT(exp_SILP!$R58,5) -> 11:00 | F58: =IF(exp_SILP!$AG58>=60,exp_SILP!$AG58/60,exp_SILP!$AG58) -> 1 | G58: =VLOOKUP(exp_SILP!$Y58,'DATI CM'!$A$2:$F$28,2,FALSE) -> TRZCST69B41F952V | H58: =VLOOKUP(exp_SILP!$Y58,'DATI CM'!$A$2:$F$28,3,FALSE) | I58: =IF(A58>0,"N","N") -> N | J58: =VLOOKUP(exp_SILP!$Y58,'DATI CM'!$A$2:$F$28,4,FALSE) | K58: =VLOOKUP(exp_SILP!$B58,'DATI COMMESSE'!$A$2:$F$25,5,FALSE) -> 39.94 | L58: =IF(exp_SILP!$B58="A4.10 - LEP E - ORIENTAMENTO SPECIALISTICO SKILL GAP ANALYSIS - GRUPPO 3P",0,VLOOKUP(exp_SILP!$Y58,'DATI CM'!$A$2:$F$28,6,FALSE)) | M58: =IFERROR(VLOOKUP(exp_SILP!$B58,'DATI CM'!$H$2:$I$16,2,FALSE)*exp_SILP!$F58,0) -> 0 | N58: =VLOOKUP(exp_SILP!$B58,'DATI COMMESSE'!$A$2:$F$25,4,FALSE) -> GOL | O58: =VLOOKUP(exp_SILP!$B58,'DATI COMMESSE'!$A$2:$F$25,5,FALSE)*exp_SILP!$F58 -> 39.94 | P58: =IF(MID(exp_SILP!$W58,10,2)>"40","F","M") -> M | Q58: 02/03/2023 | R58: 10:00-11:00 | S58: A4.10 - LEP E - ORIENTAMENTO SPECIALISTICO SKILL GAP ANALYSIS | T58: Progetti per accreditati | V58: CHARLES LUCKY | W58: CHRLKY97A01Z335E | X58: 01/01/1997 | Y58: TERZERA CRISTINA | Z58: Erogato | AA58: INFORCOOP ECIPA PIEMONTE | AB58: Incontro MDL | AC58: INFORCOOP ECIPA PIEMONTE VIA UGO PORZIO GIOVANOLA 7 - NOVARA | AG58: 60 | AH58: 02/03/2023 | AI58: TRZCST69B41F952V | AJ58: =VLOOKUP(exp_SILP!$Y58,'DATI CM'!$A$2:$F$28,2,FALSE) -> TRZCST69B41F952V
A59: =IFERROR(VLOOKUP(exp_SILP!$W59,exp_utenti_P!D:D,1,FALSE),"_DA INSERIRE") -> RLNGPP59H45H369E | B59: =IF(AND(exp_SILP!$S59="A.3 ORIENTAMENTO PROFESSIONALE",exp_SILP!$AD59="4.2"),"A.3 ORIENTAMENTO PROFESSIONALE (CARCERE)", IF(AND(exp_SILP!$S59="A.3 ORIENTAMENTO PROFESSIONALE",exp_SILP!$AD59="."),"A.3 ORIENTAMENTO PROFESSIONALE (CARCERE)", IF(AND(exp_SILP!$S59="A.4 CONSULENZA ORIENTATIVA",exp_SILP!$AD59="4.2"),"A.4 CONSULENZA ORIENTATIVA (CARCERE)", IF(AND(exp_SILP!$S59="A.4 CONSULENZA ORIENTATIVA",exp_SILP!$AD59="."),"A.4 CONSULENZA ORIENTATIVA (CARCERE)", IF(AND(exp_SILP!$S59="A.5 - LEP F1 - ACCOMPAGNAMENTO AL LAVORO",exp_SILP!$AD59="4.2"),"A.5 - LEP F1 - ACCOMPAGNAMENTO AL LAVORO (CARCERE)", IF(AND(exp_SILP!$S59="A.5 - LEP F1 - ACCOMPAGNAMENTO AL LAVORO",exp_SILP!$AD59="."),"A.5 - LEP F1 - ACCOMPAGNAMENTO AL LAVORO (CARCERE)", IF(AND(exp_SILP!$S59="A.5.2a - TUTORAGGIO TIROCINI",exp_SILP!$AD59="4.2"),"A.5.2a - TUTORAGGIO TIROCINI (CARCERE)", exp_SILP!$S59))))))) -> A4.10 - LEP E - ORIENTAMENTO SPECIALISTICO SKILL GAP ANALYSIS | C59: =CONCATENATE(VLOOKUP(exp_SILP!$B59,'DATI COMMESSE'!$A$2:$F$25,4,FALSE)," - ", VLOOKUP(exp_SILP!$B59,'DATI COMMESSE'!$A$2:$F$25,2,FALSE)," - ",VLOOKUP(exp_SILP!$B59,'DATI COMMESSE'!$A$2:$F$25,3,FALSE)) -> GOL - 22-02-5000 - 22-12-5003 | D59: =LEFT(exp_SILP!$R59,5) -> 14:00 | E59: =RIGHT(exp_SILP!$R59,5) -> 16:00 | F59: =IF(exp_SILP!$AG59>=60,exp_SILP!$AG59/60,exp_SILP!$AG59) -> 2 | G59: =VLOOKUP(exp_SILP!$Y59,'DATI CM'!$A$2:$F$28,2,FALSE) -> TRZCST69B41F952V | H59: =VLOOKUP(exp_SILP!$Y59,'DATI CM'!$A$2:$F$28,3,FALSE) | I59: =IF(A59>0,"N","N") -> N | J59: =VLOOKUP(exp_SILP!$Y59,'DATI CM'!$A$2:$F$28,4,FALSE) | K59: =VLOOKUP(exp_SILP!$B59,'DATI COMMESSE'!$A$2:$F$25,5,FALSE) -> 39.94 | L59: =IF(exp_SILP!$B59="A4.10 - LEP E - ORIENTAMENTO SPECIALISTICO SKILL GAP ANALYSIS - GRUPPO 3P",0,VLOOKUP(exp_SILP!$Y59,'DATI CM'!$A$2:$F$28,6,FALSE)) | M59: =IFERROR(VLOOKUP(exp_SILP!$B59,'DATI CM'!$H$2:$I$16,2,FALSE)*exp_SILP!$F59,0) -> 0 | N59: =VLOOKUP(exp_SILP!$B59,'DATI COMMESSE'!$A$2:$F$25,4,FALSE) -> GOL | O59: =VLOOKUP(exp_SILP!$B59,'DATI COMMESSE'!$A$2:$F$25,5,FALSE)*exp_SILP!$F59 -> 79.88 | P59: =IF(MID(exp_SILP!$W59,10,2)>"40","F","M") -> F | Q59: 02/03/2023 | R59: 14:00-16:00 | S59: A4.10 - LEP E - ORIENTAMENTO SPECIALISTICO SKILL GAP ANALYSIS | T59: Progetti per accreditati | V59: ORLANDIN GIUSEPPINA | W59: RLNGPP59H45H369E | X59: 05/06/1959 | Y59: TERZERA CRISTINA | Z59: Erogato | AA59: INFORCOOP ECIPA PIEMONTE | AB59: Incontro MDL | AC59: INFORCOOP ECIPA PIEMONTE VIA UGO PORZIO GIOVANOLA 7 - NOVARA | AG59: 120 | AH59: 02/03/2023 | AI59: TRZCST69B41F952V | AJ59: =VLOOKUP(exp_SILP!$Y59,'DATI CM'!$A$2:$F$28,2,FALSE) -> TRZCST69B41F952V
A60: =IFERROR(VLOOKUP(exp_SILP!$W60,exp_utenti_P!D:D,1,FALSE),"_DA INSERIRE") -> RLNGPP59H45H369E | B60: =IF(AND(exp_SILP!$S60="A.3 ORIENTAMENTO PROFESSIONALE",exp_SILP!$AD60="4.2"),"A.3 ORIENTAMENTO PROFESSIONALE (CARCERE)", IF(AND(exp_SILP!$S60="A.3 ORIENTAMENTO PROFESSIONALE",exp_SILP!$AD60="."),"A.3 ORIENTAMENTO PROFESSIONALE (CARCERE)", IF(AND(exp_SILP!$S60="A.4 CONSULENZA ORIENTATIVA",exp_SILP!$AD60="4.2"),"A.4 CONSULENZA ORIENTATIVA (CARCERE)", IF(AND(exp_SILP!$S60="A.4 CONSULENZA ORIENTATIVA",exp_SILP!$AD60="."),"A.4 CONSULENZA ORIENTATIVA (CARCERE)", IF(AND(exp_SILP!$S60="A.5 - LEP F1 - ACCOMPAGNAMENTO AL LAVORO",exp_SILP!$AD60="4.2"),"A.5 - LEP F1 - ACCOMPAGNAMENTO AL LAVORO (CARCERE)", IF(AND(exp_SILP!$S60="A.5 - LEP F1 - ACCOMPAGNAMENTO AL LAVORO",exp_SILP!$AD60="."),"A.5 - LEP F1 - ACCOMPAGNAMENTO AL LAVORO (CARCERE)", IF(AND(exp_SILP!$S60="A.5.2a - TUTORAGGIO TIROCINI",exp_SILP!$AD60="4.2"),"A.5.2a - TUTORAGGIO TIROCINI (CARCERE)", exp_SILP!$S60))))))) -> A4.10 - LEP E - ORIENTAMENTO SPECIALISTICO SKILL GAP ANALYSIS | C60: =CONCATENATE(VLOOKUP(exp_SILP!$B60,'DATI COMMESSE'!$A$2:$F$25,4,FALSE)," - ", VLOOKUP(exp_SILP!$B60,'DATI COMMESSE'!$A$2:$F$25,2,FALSE)," - ",VLOOKUP(exp_SILP!$B60,'DATI COMMESSE'!$A$2:$F$25,3,FALSE)) -> GOL - 22-02-5000 - 22-12-5003 | D60: =LEFT(exp_SILP!$R60,5) -> 12:00 | E60: =RIGHT(exp_SILP!$R60,5) -> 13:00 | F60: =IF(exp_SILP!$AG60>=60,exp_SILP!$AG60/60,exp_SILP!$AG60) -> 1 | G60: =VLOOKUP(exp_SILP!$Y60,'DATI CM'!$A$2:$F$28,2,FALSE) -> TRZCST69B41F952V | H60: =VLOOKUP(exp_SILP!$Y60,'DATI CM'!$A$2:$F$28,3,FALSE) | I60: =IF(A60>0,"N","N") -> N | J60: =VLOOKUP(exp_SILP!$Y60,'DATI CM'!$A$2:$F$28,4,FALSE) | K60: =VLOOKUP(exp_SILP!$B60,'DATI COMMESSE'!$A$2:$F$25,5,FALSE) -> 39.94 | L60: =IF(exp_SILP!$B60="A4.10 - LEP E - ORIENTAMENTO SPECIALISTICO SKILL GAP ANALYSIS - GRUPPO 3P",0,VLOOKUP(exp_SILP!$Y60,'DATI CM'!$A$2:$F$28,6,FALSE)) | M60: =IFERROR(VLOOKUP(exp_SILP!$B60,'DATI CM'!$H$2:$I$16,2,FALSE)*exp_SILP!$F60,0) -> 0 | N60: =VLOOKUP(exp_SILP!$B60,'DATI COMMESSE'!$A$2:$F$25,4,FALSE) -> GOL | O60: =VLOOKUP(exp_SILP!$B60,'DATI COMMESSE'!$A$2:$F$25,5,FALSE)*exp_SILP!$F60 -> 39.94 | P60: =IF(MID(exp_SILP!$W60,10,2)>"40","F","M") -> F | Q60: 02/03/2023 | R60: 12:00-13:00 | S60: A4.10 - LEP E - ORIENTAMENTO SPECIALISTICO SKILL GAP ANALYSIS | T60: Progetti per accreditati | V60: ORLANDIN GIUSEPPINA | W60: RLNGPP59H45H369E | X60: 05/06/1959 | Y60: TERZERA CRISTINA | Z60: Erogato | AA60: INFORCOOP ECIPA PIEMONTE | AB60: Incontro MDL | AC60: INFORCOOP ECIPA PIEMONTE VIA UGO PORZIO GIOVANOLA 7 - NOVARA | AF60: BACK OFFICE | AG60: 60 | AH60: 02/03/2023 | AI60: TRZCST69B41F952V | AJ60: =VLOOKUP(exp_SILP!$Y60,'DATI CM'!$A$2:$F$28,2,FALSE) -> TRZCST69B41F952V
A61: =IFERROR(VLOOKUP(exp_SILP!$W61,exp_utenti_P!D:D,1,FALSE),"_DA INSERIRE") -> FRNGPP76S12A859E | B61: =IF(AND(exp_SILP!$S61="A.3 ORIENTAMENTO PROFESSIONALE",exp_SILP!$AD61="4.2"),"A.3 ORIENTAMENTO PROFESSIONALE (CARCERE)", IF(AND(exp_SILP!$S61="A.3 ORIENTAMENTO PROFESSIONALE",exp_SILP!$AD61="."),"A.3 ORIENTAMENTO PROFESSIONALE (CARCERE)", IF(AND(exp_SILP!$S61="A.4 CONSULENZA ORIENTATIVA",exp_SILP!$AD61="4.2"),"A.4 CONSULENZA ORIENTATIVA (CARCERE)", IF(AND(exp_SILP!$S61="A.4 CONSULENZA ORIENTATIVA",exp_SILP!$AD61="."),"A.4 CONSULENZA ORIENTATIVA (CARCERE)", IF(AND(exp_SILP!$S61="A.5 - LEP F1 - ACCOMPAGNAMENTO AL LAVORO",exp_SILP!$AD61="4.2"),"A.5 - LEP F1 - ACCOMPAGNAMENTO AL LAVORO (CARCERE)", IF(AND(exp_SILP!$S61="A.5 - LEP F1 - ACCOMPAGNAMENTO AL LAVORO",exp_SILP!$AD61="."),"A.5 - LEP F1 - ACCOMPAGNAMENTO AL LAVORO (CARCERE)", IF(AND(exp_SILP!$S61="A.5.2a - TUTORAGGIO TIROCINI",exp_SILP!$AD61="4.2"),"A.5.2a - TUTORAGGIO TIROCINI (CARCERE)", exp_SILP!$S61))))))) -> A4.10 - LEP E - ORIENTAMENTO SPECIALISTICO SKILL GAP ANALYSIS | C61: =CONCATENATE(VLOOKUP(exp_SILP!$B61,'DATI COMMESSE'!$A$2:$F$25,4,FALSE)," - ", VLOOKUP(exp_SILP!$B61,'DATI COMMESSE'!$A$2:$F$25,2,FALSE)," - ",VLOOKUP(exp_SILP!$B61,'DATI COMMESSE'!$A$2:$F$25,3,FALSE)) -> GOL - 22-02-5000 - 22-12-5003 | D61: =LEFT(exp_SILP!$R61,5) -> 13:00 | E61: =RIGHT(exp_SILP!$R61,5) -> 14:00 | F61: =IF(exp_SILP!$AG61>=60,exp_SILP!$AG61/60,exp_SILP!$AG61) -> 1 | G61: =VLOOKUP(exp_SILP!$Y61,'DATI CM'!$A$2:$F$28,2,FALSE) -> PNFMRT85H50A859E | H61: =VLOOKUP(exp_SILP!$Y61,'DATI CM'!$A$2:$F$28,3,FALSE) -> A011 | I61: =IF(A61>0,"N","N") -> N | J61: =VLOOKUP(exp_SILP!$Y61,'DATI CM'!$A$2:$F$28,4,FALSE) -> BIELLA | K61: =VLOOKUP(exp_SILP!$B61,'DATI COMMESSE'!$A$2:$F$25,5,FALSE) -> 39.94 | L61: =IF(exp_SILP!$B61="A4.10 - LEP E - ORIENTAMENTO SPECIALISTICO SKILL GAP ANALYSIS - GRUPPO 3P",0,VLOOKUP(exp_SILP!$Y61,'DATI CM'!$A$2:$F$28,6,FALSE)) -> 25 | M61: =IFERROR(VLOOKUP(exp_SILP!$B61,'DATI CM'!$H$2:$I$16,2,FALSE)*exp_SILP!$F61,0) -> 0 | N61: =VLOOKUP(exp_SILP!$B61,'DATI COMMESSE'!$A$2:$F$25,4,FALSE) -> GOL | O61: =VLOOKUP(exp_SILP!$B61,'DATI COMMESSE'!$A$2:$F$25,5,FALSE)*exp_SILP!$F61 -> 39.94 | P61: =IF(MID(exp_SILP!$W61,10,2)>"40","F","M") -> M | Q61: 02/03/2023 | R61: 13:00-14:00 | S61: A4.10 - LEP E - ORIENTAMENTO SPECIALISTICO SKILL GAP ANALYSIS | T61: Progetti per accreditati | V61: FIORENZA GIUSEPPE | W61: FRNGPP76S12A859E | X61: 12/11/1976 | Y61: PIANOFORTE MARTA | Z61: Erogato | AA61: INFORCOOP ECIPA PIEMONTE | AB61: Incontro MDL | AC61: INFORCOOP ECIPA PIEMONTE STRADA CAMPAGNE' 7 - BIELLA | AG61: 60 | AH61: 10/03/2023 | AI61: PNFMRT85H50A859E | AJ61: =VLOOKUP(exp_SILP!$Y61,'DATI CM'!$A$2:$F$28,2,FALSE) -> PNFMRT85H50A859E
A62: =IFERROR(VLOOKUP(exp_SILP!$W62,exp_utenti_P!D:D,1,FALSE),"_DA INSERIRE") -> FYAMKH88P51Z343H | B62: =IF(AND(exp_SILP!$S62="A.3 ORIENTAMENTO PROFESSIONALE",exp_SILP!$AD62="4.2"),"A.3 ORIENTAMENTO PROFESSIONALE (CARCERE)", IF(AND(exp_SILP!$S62="A.3 ORIENTAMENTO PROFESSIONALE",exp_SILP!$AD62="."),"A.3 ORIENTAMENTO PROFESSIONALE (CARCERE)", IF(AND(exp_SILP!$S62="A.4 CONSULENZA ORIENTATIVA",exp_SILP!$AD62="4.2"),"A.4 CONSULENZA ORIENTATIVA (CARCERE)", IF(AND(exp_SILP!$S62="A.4 CONSULENZA ORIENTATIVA",exp_SILP!$AD62="."),"A.4 CONSULENZA ORIENTATIVA (CARCERE)", IF(AND(exp_SILP!$S62="A.5 - LEP F1 - ACCOMPAGNAMENTO AL LAVORO",exp_SILP!$AD62="4.2"),"A.5 - LEP F1 - ACCOMPAGNAMENTO AL LAVORO (CARCERE)", IF(AND(exp_SILP!$S62="A.5 - LEP F1 - ACCOMPAGNAMENTO AL LAVORO",exp_SILP!$AD62="."),"A.5 - LEP F1 - ACCOMPAGNAMENTO AL LAVORO (CARCERE)", IF(AND(exp_SILP!$S62="A.5.2a - TUTORAGGIO TIROCINI",exp_SILP!$AD62="4.2"),"A.5.2a - TUTORAGGIO TIROCINI (CARCERE)", exp_SILP!$S62))))))) -> A4.10 - LEP E - ORIENTAMENTO SPECIALISTICO SKILL GAP ANALYSIS - GRUPPO 3P | C62: =CONCATENATE(VLOOKUP(exp_SILP!$B62,'DATI COMMESSE'!$A$2:$F$25,4,FALSE)," - ", VLOOKUP(exp_SILP!$B62,'DATI COMMESSE'!$A$2:$F$25,2,FALSE)," - ",VLOOKUP(exp_SILP!$B62,'DATI COMMESSE'!$A$2:$F$25,3,FALSE)) -> GOL - 22-02-5000 - 22-12-5003 | D62: =LEFT(exp_SILP!$R62,5) -> 08:00 | E62: =RIGHT(exp_SILP!$R62,5) -> 10:00 | F62: =IF(exp_SILP!$AG62>=60,exp_SILP!$AG62/60,exp_SILP!$AG62) -> 2 | G62: =VLOOKUP(exp_SILP!$Y62,'DATI CM'!$A$2:$F$28,2,FALSE) -> PNFMRT85H50A859E | H62: =VLOOKUP(exp_SILP!$Y62,'DATI CM'!$A$2:$F$28,3,FALSE) -> A011 | I62: =IF(A62>0,"N","N") -> N | J62: =VLOOKUP(exp_SILP!$Y62,'DATI CM'!$A$2:$F$28,4,FALSE) -> BIELLA | K62: =VLOOKUP(exp_SILP!$B62,'DATI COMMESSE'!$A$2:$F$25,5,FALSE) -> 82.27 | L62: =IF(exp_SILP!$B62="A4.10 - LEP E - ORIENTAMENTO SPECIALISTICO SKILL GAP ANALYSIS - GRUPPO 3P",0,VLOOKUP(exp_SILP!$Y62,'DATI CM'!$A$2:$F$28,6,FALSE)) -> 0 | M62: =IFERROR(VLOOKUP(exp_SILP!$B62,'DATI CM'!$H$2:$I$16,2,FALSE)*exp_SILP!$F62,0) -> 70 | N62: =VLOOKUP(exp_SILP!$B62,'DATI COMMESSE'!$A$2:$F$25,4,FALSE) -> GOL | O62: =VLOOKUP(exp_SILP!$B62,'DATI COMMESSE'!$A$2:$F$25,5,FALSE)*exp_SILP!$F62 -> 164.54 | P62: =IF(MID(exp_SILP!$W62,10,2)>"40","F","M") -> F | Q62: 02/05/2023 | R62: 08:00-10:00 | S62: A4.10 - LEP E - ORIENTAMENTO SPECIALISTICO SKILL GAP ANALYSIS - GRUPPO 3P | T62: Progetti per accreditati | V62: FAYE MAME KHADY | W62: FYAMKH88P51Z343H | X62: 11/09/1988 | Y62: PIANOFORTE MARTA | Z62: Erogato | AA62: INFORCOOP ECIPA PIEMONTE | AB62: Incontro MDL | AC62: INFORCOOP ECIPA PIEMONTE STRADA CAMPAGNE' 7 - BIELLA | AG62: 120 | AH62: 10/05/2023 | AI62: PNFMRT85H50A859E | AJ62: =VLOOKUP(exp_SILP!$Y62,'DATI CM'!$A$2:$F$28,2,FALSE) -> PNFMRT85H50A859E
A63: =IFERROR(VLOOKUP(exp_SILP!$W63,exp_utenti_P!D:D,1,FALSE),"_DA INSERIRE") -> DTMGFT95E68Z335I | B63: =IF(AND(exp_SILP!$S63="A.3 ORIENTAMENTO PROFESSIONALE",exp_SILP!$AD63="4.2"),"A.3 ORIENTAMENTO PROFESSIONALE (CARCERE)", IF(AND(exp_SILP!$S63="A.3 ORIENTAMENTO PROFESSIONALE",exp_SILP!$AD63="."),"A.3 ORIENTAMENTO PROFESSIONALE (CARCERE)", IF(AND(exp_SILP!$S63="A.4 CONSULENZA ORIENTATIVA",exp_SILP!$AD63="4.2"),"A.4 CONSULENZA ORIENTATIVA (CARCERE)", IF(AND(exp_SILP!$S63="A.4 CONSULENZA ORIENTATIVA",exp_SILP!$AD63="."),"A.4 CONSULENZA ORIENTATIVA (CARCERE)", IF(AND(exp_SILP!$S63="A.5 - LEP F1 - ACCOMPAGNAMENTO AL LAVORO",exp_SILP!$AD63="4.2"),"A.5 - LEP F1 - ACCOMPAGNAMENTO AL LAVORO (CARCERE)", IF(AND(exp_SILP!$S63="A.5 - LEP F1 - ACCOMPAGNAMENTO AL LAVORO",exp_SILP!$AD63="."),"A.5 - LEP F1 - ACCOMPAGNAMENTO AL LAVORO (CARCERE)", IF(AND(exp_SILP!$S63="A.5.2a - TUTORAGGIO TIROCINI",exp_SILP!$AD63="4.2"),"A.5.2a - TUTORAGGIO TIROCINI (CARCERE)", exp_SILP!$S63))))))) -> A4.10 - LEP E - ORIENTAMENTO SPECIALISTICO SKILL GAP ANALYSIS - GRUPPO 3P | C63: =CONCATENATE(VLOOKUP(exp_SILP!$B63,'DATI COMMESSE'!$A$2:$F$25,4,FALSE)," - ", VLOOKUP(exp_SILP!$B63,'DATI COMMESSE'!$A$2:$F$25,2,FALSE)," - ",VLOOKUP(exp_SILP!$B63,'DATI COMMESSE'!$A$2:$F$25,3,FALSE)) -> GOL - 22-02-5000 - 22-12-5003 | D63: =LEFT(exp_SILP!$R63,5) -> 10:00 | E63: =RIGHT(exp_SILP!$R63,5) -> 12:00 | F63: =IF(exp_SILP!$AG63>=60,exp_SILP!$AG63/60,exp_SILP!$AG63) -> 2 | G63: =VLOOKUP(exp_SILP!$Y63,'DATI CM'!$A$2:$F$28,2,FALSE) -> PNFMRT85H50A859E | H63: =VLOOKUP(exp_SILP!$Y63,'DATI CM'!$A$2:$F$28,3,FALSE) -> A011 | I63: =IF(A63>0,"N","N") -> N | J63: =VLOOKUP(exp_SILP!$Y63,'DATI CM'!$A$2:$F$28,4,FALSE) -> BIELLA | K63: =VLOOKUP(exp_SILP!$B63,'DATI COMMESSE'!$A$2:$F$25,5,FALSE) -> 82.27 | L63: =IF(exp_SILP!$B63="A4.10 - LEP E - ORIENTAMENTO SPECIALISTICO SKILL GAP ANALYSIS - GRUPPO 3P",0,VLOOKUP(exp_SILP!$Y63,'DATI CM'!$A$2:$F$28,6,FALSE)) -> 0 | M63: =IFERROR(VLOOKUP(exp_SILP!$B63,'DATI CM'!$H$2:$I$16,2,FALSE)*exp_SILP!$F63,0) -> 70 | N63: =VLOOKUP(exp_SILP!$B63,'DATI COMMESSE'!$A$2:$F$25,4,FALSE) -> GOL | O63: =VLOOKUP(exp_SILP!$B63,'DATI COMMESSE'!$A$2:$F$25,5,FALSE)*exp_SILP!$F63 -> 164.54 | P63: =IF(MID(exp_SILP!$W63,10,2)>"40","F","M") -> F | Q63: 02/05/2023 | R63: 10:00-12:00 | S63: A4.10 - LEP E - ORIENTAMENTO SPECIALISTICO SKILL GAP ANALYSIS - GRUPPO 3P | T63: Progetti per accreditati | V63: EDET MFON GIFT | W63: DTMGFT95E68Z335I | X63: 28/05/1995 | Y63: PIANOFORTE MARTA | Z63: Erogato | AA63: INFORCOOP ECIPA PIEMONTE | AB63: Incontro MDL | AC63: INFORCOOP ECIPA PIEMONTE STRADA CAMPAGNE' 7 - BIELLA | AG63: 120 | AH63: 10/05/2023 | AI63: PNFMRT85H50A859E | AJ63: =VLOOKUP(exp_SILP!$Y63,'DATI CM'!$A$2:$F$28,2,FALSE) -> PNFMRT85H50A859E
A64: =IFERROR(VLOOKUP(exp_SILP!$W64,exp_utenti_P!D:D,1,FALSE),"_DA INSERIRE") -> GGLDNC78R61H224I | B64: =IF(AND(exp_SILP!$S64="A.3 ORIENTAMENTO PROFESSIONALE",exp_SILP!$AD64="4.2"),"A.3 ORIENTAMENTO PROFESSIONALE (CARCERE)", IF(AND(exp_SILP!$S64="A.3 ORIENTAMENTO PROFESSIONALE",exp_SILP!$AD64="."),"A.3 ORIENTAMENTO PROFESSIONALE (CARCERE)", IF(AND(exp_SILP!$S64="A.4 CONSULENZA ORIENTATIVA",exp_SILP!$AD64="4.2"),"A.4 CONSULENZA ORIENTATIVA (CARCERE)", IF(AND(exp_SILP!$S64="A.4 CONSULENZA ORIENTATIVA",exp_SILP!$AD64="."),"A.4 CONSULENZA ORIENTATIVA (CARCERE)", IF(AND(exp_SILP!$S64="A.5 - LEP F1 - ACCOMPAGNAMENTO AL LAVORO",exp_SILP!$AD64="4.2"),"A.5 - LEP F1 - ACCOMPAGNAMENTO AL LAVORO (CARCERE)", IF(AND(exp_SILP!$S64="A.5 - LEP F1 - ACCOMPAGNAMENTO AL LAVORO",exp_SILP!$AD64="."),"A.5 - LEP F1 - ACCOMPAGNAMENTO AL LAVORO (CARCERE)", IF(AND(exp_SILP!$S64="A.5.2a - TUTORAGGIO TIROCINI",exp_SILP!$AD64="4.2"),"A.5.2a - TUTORAGGIO TIROCINI (CARCERE)", exp_SILP!$S64))))))) -> A.4 CONSULENZA ORIENTATIVA (1-C) | C64: =CONCATENATE(VLOOKUP(exp_SILP!$B64,'DATI COMMESSE'!$A$2:$F$25,4,FALSE)," - ", VLOOKUP(exp_SILP!$B64,'DATI COMMESSE'!$A$2:$F$25,2,FALSE)," - ",VLOOKUP(exp_SILP!$B64,'DATI COMMESSE'!$A$2:$F$25,3,FALSE)) -> FRD - 22-02-5000 - 22-12-5002 | D64: =LEFT(exp_SILP!$R64,5) -> 14:00 | E64: =RIGHT(exp_SILP!$R64,5) -> 17:00 | F64: =IF(exp_SILP!$AG64>=60,exp_SILP!$AG64/60,exp_SILP!$AG64) -> 3 | G64: =VLOOKUP(exp_SILP!$Y64,'DATI CM'!$A$2:$F$28,2,FALSE) -> TRZCST69B41F952V | H64: =VLOOKUP(exp_SILP!$Y64,'DATI CM'!$A$2:$F$28,3,FALSE) | I64: =IF(A64>0,"N","N") -> N | J64: =VLOOKUP(exp_SILP!$Y64,'DATI CM'!$A$2:$F$28,4,FALSE) | K64: =VLOOKUP(exp_SILP!$B64,'DATI COMMESSE'!$A$2:$F$25,5,FALSE) -> 35.5 | L64: =IF(exp_SILP!$B64="A4.10 - LEP E - ORIENTAMENTO SPECIALISTICO SKILL GAP ANALYSIS - GRUPPO 3P",0,VLOOKUP(exp_SILP!$Y64,'DATI CM'!$A$2:$F$28,6,FALSE)) | M64: =IFERROR(VLOOKUP(exp_SILP!$B64,'DATI CM'!$H$2:$I$16,2,FALSE)*exp_SILP!$F64,0) -> 0 | N64: =VLOOKUP(exp_SILP!$B64,'DATI COMMESSE'!$A$2:$F$25,4,FALSE) -> FRD | O64: =VLOOKUP(exp_SILP!$B64,'DATI COMMESSE'!$A$2:$F$25,5,FALSE)*exp_SILP!$F64 -> 106.5 | P64: =IF(MID(exp_SILP!$W64,10,2)>"40","F","M") -> F | Q64: 02/05/2023 | R64: 14:00-17:00 | S64: A.4 CONSULENZA ORIENTATIVA (1-C) | T64: Progetti per accreditati | V64: GAGLIARDI DOMENICA | W64: GGLDNC78R61H224I | X64: 21/10/1978 | Y64: TERZERA CRISTINA | Z64: Erogato | AA64: INFORCOOP ECIPA PIEMONTE | AB64: Incontro MDL | AC64: INFORCOOP ECIPA PIEMONTE VIA UGO PORZIO GIOVANOLA 7 - NOVARA | AG64: 180 | AH64: 02/05/2023 | AI64: TRZCST69B41F952V | AJ64: =VLOOKUP(exp_SILP!$Y64,'DATI CM'!$A$2:$F$28,2,FALSE) -> TRZCST69B41F952V
A65: =IFERROR(VLOOKUP(exp_SILP!$W65,exp_utenti_P!D:D,1,FALSE),"_DA INSERIRE") -> NGRGGT68H67Z129D | B65: =IF(AND(exp_SILP!$S65="A.3 ORIENTAMENTO PROFESSIONALE",exp_SILP!$AD65="4.2"),"A.3 ORIENTAMENTO PROFESSIONALE (CARCERE)", IF(AND(exp_SILP!$S65="A.3 ORIENTAMENTO PROFESSIONALE",exp_SILP!$AD65="."),"A.3 ORIENTAMENTO PROFESSIONALE (CARCERE)", IF(AND(exp_SILP!$S65="A.4 CONSULENZA ORIENTATIVA",exp_SILP!$AD65="4.2"),"A.4 CONSULENZA ORIENTATIVA (CARCERE)", IF(AND(exp_SILP!$S65="A.4 CONSULENZA ORIENTATIVA",exp_SILP!$AD65="."),"A.4 CONSULENZA ORIENTATIVA (CARCERE)", IF(AND(exp_SILP!$S65="A.5 - LEP F1 - ACCOMPAGNAMENTO AL LAVORO",exp_SILP!$AD65="4.2"),"A.5 - LEP F1 - ACCOMPAGNAMENTO AL LAVORO (CARCERE)", IF(AND(exp_SILP!$S65="A.5 - LEP F1 - ACCOMPAGNAMENTO AL LAVORO",exp_SILP!$AD65="."),"A.5 - LEP F1 - ACCOMPAGNAMENTO AL LAVORO (CARCERE)", IF(AND(exp_SILP!$S65="A.5.2a - TUTORAGGIO TIROCINI",exp_SILP!$AD65="4.2"),"A.5.2a - TUTORAGGIO TIROCINI (CARCERE)", exp_SILP!$S65))))))) -> A.5 - LEP F1 - ACCOMPAGNAMENTO AL LAVORO | C65: =CONCATENATE(VLOOKUP(exp_SILP!$B65,'DATI COMMESSE'!$A$2:$F$25,4,FALSE)," - ", VLOOKUP(exp_SILP!$B65,'DATI COMMESSE'!$A$2:$F$25,2,FALSE)," - ",VLOOKUP(exp_SILP!$B65,'DATI COMMESSE'!$A$2:$F$25,3,FALSE)) -> GOL - 22-02-5000 - 22-12-5003 | D65: =LEFT(exp_SILP!$R65,5) -> 09:00 | E65: =RIGHT(exp_SILP!$R65,5) -> 11:00 | F65: =IF(exp_SILP!$AG65>=60,exp_SILP!$AG65/60,exp_SILP!$AG65) -> 2 | G65: =VLOOKUP(exp_SILP!$Y65,'DATI CM'!$A$2:$F$28,2,FALSE) -> MNRCLD73B46G674U | H65: =VLOOKUP(exp_SILP!$Y65,'DATI CM'!$A$2:$F$28,3,FALSE) -> A011 | I65: =IF(A65>0,"N","N") -> N | J65: =VLOOKUP(exp_SILP!$Y65,'DATI CM'!$A$2:$F$28,4,FALSE) -> TORINO | K65: =VLOOKUP(exp_SILP!$B65,'DATI COMMESSE'!$A$2:$F$25,5,FALSE) -> 39.94 | L65: =IF(exp_SILP!$B65="A4.10 - LEP E - ORIENTAMENTO SPECIALISTICO SKILL GAP ANALYSIS - GRUPPO 3P",0,VLOOKUP(exp_SILP!$Y65,'DATI CM'!$A$2:$F$28,6,FALSE)) -> 25 | M65: =IFERROR(VLOOKUP(exp_SILP!$B65,'DATI CM'!$H$2:$I$16,2,FALSE)*exp_SILP!$F65,0) -> 0 | N65: =VLOOKUP(exp_SILP!$B65,'DATI COMMESSE'!$A$2:$F$25,4,FALSE) -> GOL | O65: =VLOOKUP(exp_SILP!$B65,'DATI COMMESSE'!$A$2:$F$25,5,FALSE)*exp_SILP!$F65 -> 79.88 | P65: =IF(MID(exp_SILP!$W65,10,2)>"40","F","M") -> F | Q65: 02/05/2023 | R65: 09:00-11:00 | S65: A.5 - LEP F1 - ACCOMPAGNAMENTO AL LAVORO | T65: Progetti per accreditati | V65: NEGRU GEORGETA | W65: NGRGGT68H67Z129D | X65: 27/06/1968 | Y65: MAINERO CLAUDIA | Z65: Erogato | AA65: INFORCOOP ECIPA PIEMONTE | AB65: Incontro MDL | AC65: INFORCOOP ECIPA PIEMONTE VIA TREVISO 12 - TORINO | AF65: B.O. | AG65: 120 | AH65: 02/05/2023 | AI65: MNRCLD73B46G674U | AJ65: =VLOOKUP(exp_SILP!$Y65,'DATI CM'!$A$2:$F$28,2,FALSE) -> MNRCLD73B46G674U
A66: =IFERROR(VLOOKUP(exp_SILP!$W66,exp_utenti_P!D:D,1,FALSE),"_DA INSERIRE") -> DMAGPP68A02C352O | B66: =IF(AND(exp_SILP!$S66="A.3 ORIENTAMENTO PROFESSIONALE",exp_SILP!$AD66="4.2"),"A.3 ORIENTAMENTO PROFESSIONALE (CARCERE)", IF(AND(exp_SILP!$S66="A.3 ORIENTAMENTO PROFESSIONALE",exp_SILP!$AD66="."),"A.3 ORIENTAMENTO PROFESSIONALE (CARCERE)", IF(AND(exp_SILP!$S66="A.4 CONSULENZA ORIENTATIVA",exp_SILP!$AD66="4.2"),"A.4 CONSULENZA ORIENTATIVA (CARCERE)", IF(AND(exp_SILP!$S66="A.4 CONSULENZA ORIENTATIVA",exp_SILP!$AD66="."),"A.4 CONSULENZA ORIENTATIVA (CARCERE)", IF(AND(exp_SILP!$S66="A.5 - LEP F1 - ACCOMPAGNAMENTO AL LAVORO",exp_SILP!$AD66="4.2"),"A.5 - LEP F1 - ACCOMPAGNAMENTO AL LAVORO (CARCERE)", IF(AND(exp_SILP!$S66="A.5 - LEP F1 - ACCOMPAGNAMENTO AL LAVORO",exp_SILP!$AD66="."),"A.5 - LEP F1 - ACCOMPAGNAMENTO AL LAVORO (CARCERE)", IF(AND(exp_SILP!$S66="A.5.2a - TUTORAGGIO TIROCINI",exp_SILP!$AD66="4.2"),"A.5.2a - TUTORAGGIO TIROCINI (CARCERE)", exp_SILP!$S66))))))) -> A.5 - LEP F1 - ACCOMPAGNAMENTO AL LAVORO | C66: =CONCATENATE(VLOOKUP(exp_SILP!$B66,'DATI COMMESSE'!$A$2:$F$25,4,FALSE)," - ", VLOOKUP(exp_SILP!$B66,'DATI COMMESSE'!$A$2:$F$25,2,FALSE)," - ",VLOOKUP(exp_SILP!$B66,'DATI COMMESSE'!$A$2:$F$25,3,FALSE)) -> GOL - 22-02-5000 - 22-12-5003 | D66: =LEFT(exp_SILP!$R66,5) -> 10:00 | E66: =RIGHT(exp_SILP!$R66,5) -> 13:00 | F66: =IF(exp_SILP!$AG66>=60,exp_SILP!$AG66/60,exp_SILP!$AG66) -> 3 | G66: =VLOOKUP(exp_SILP!$Y66,'DATI CM'!$A$2:$F$28,2,FALSE) -> TRZCST69B41F952V | H66: =VLOOKUP(exp_SILP!$Y66,'DATI CM'!$A$2:$F$28,3,FALSE) | I66: =IF(A66>0,"N","N") -> N | J66: =VLOOKUP(exp_SILP!$Y66,'DATI CM'!$A$2:$F$28,4,FALSE) | K66: =VLOOKUP(exp_SILP!$B66,'DATI COMMESSE'!$A$2:$F$25,5,FALSE) -> 39.94 | L66: =IF(exp_SILP!$B66="A4.10 - LEP E - ORIENTAMENTO SPECIALISTICO SKILL GAP ANALYSIS - GRUPPO 3P",0,VLOOKUP(exp_SILP!$Y66,'DATI CM'!$A$2:$F$28,6,FALSE)) | M66: =IFERROR(VLOOKUP(exp_SILP!$B66,'DATI CM'!$H$2:$I$16,2,FALSE)*exp_SILP!$F66,0) -> 0 | N66: =VLOOKUP(exp_SILP!$B66,'DATI COMMESSE'!$A$2:$F$25,4,FALSE) -> GOL | O66: =VLOOKUP(exp_SILP!$B66,'DATI COMMESSE'!$A$2:$F$25,5,FALSE)*exp_SILP!$F66 -> 119.82 | P66: =IF(MID(exp_SILP!$W66,10,2)>"40","F","M") -> M | Q66: 02/05/2023 | R66: 10:00-13:00 | S66: A.5 - LEP F1 - ACCOMPAGNAMENTO AL LAVORO | T66: Progetti per accreditati | V66: ADAMO GIUSEPPE | W66: DMAGPP68A02C352O | X66: 02/01/1968 | Y66: TERZERA CRISTINA | Z66: Erogato | AA66: INFORCOOP ECIPA PIEMONTE | AB66: Incontro MDL | AC66: INFORCOOP ECIPA PIEMONTE VIA UGO PORZIO GIOVANOLA 7 - NOVARA | AG66: 180 | AH66: 02/05/2023 | AI66: TRZCST69B41F952V | AJ66: =VLOOKUP(exp_SILP!$Y66,'DATI CM'!$A$2:$F$28,2,FALSE) -> TRZCST69B41F952V
A67: =IFERROR(VLOOKUP(exp_SILP!$W67,exp_utenti_P!D:D,1,FALSE),"_DA INSERIRE") -> CCISFI61C23Z129N | B67: =IF(AND(exp_SILP!$S67="A.3 ORIENTAMENTO PROFESSIONALE",exp_SILP!$AD67="4.2"),"A.3 ORIENTAMENTO PROFESSIONALE (CARCERE)", IF(AND(exp_SILP!$S67="A.3 ORIENTAMENTO PROFESSIONALE",exp_SILP!$AD67="."),"A.3 ORIENTAMENTO PROFESSIONALE (CARCERE)", IF(AND(exp_SILP!$S67="A.4 CONSULENZA ORIENTATIVA",exp_SILP!$AD67="4.2"),"A.4 CONSULENZA ORIENTATIVA (CARCERE)", IF(AND(exp_SILP!$S67="A.4 CONSULENZA ORIENTATIVA",exp_SILP!$AD67="."),"A.4 CONSULENZA ORIENTATIVA (CARCERE)", IF(AND(exp_SILP!$S67="A.5 - LEP F1 - ACCOMPAGNAMENTO AL LAVORO",exp_SILP!$AD67="4.2"),"A.5 - LEP F1 - ACCOMPAGNAMENTO AL LAVORO (CARCERE)", IF(AND(exp_SILP!$S67="A.5 - LEP F1 - ACCOMPAGNAMENTO AL LAVORO",exp_SILP!$AD67="."),"A.5 - LEP F1 - ACCOMPAGNAMENTO AL LAVORO (CARCERE)", IF(AND(exp_SILP!$S67="A.5.2a - TUTORAGGIO TIROCINI",exp_SILP!$AD67="4.2"),"A.5.2a - TUTORAGGIO TIROCINI (CARCERE)", exp_SILP!$S67))))))) -> A.5 - LEP F1 - ACCOMPAGNAMENTO AL LAVORO | C67: =CONCATENATE(VLOOKUP(exp_SILP!$B67,'DATI COMMESSE'!$A$2:$F$25,4,FALSE)," - ", VLOOKUP(exp_SILP!$B67,'DATI COMMESSE'!$A$2:$F$25,2,FALSE)," - ",VLOOKUP(exp_SILP!$B67,'DATI COMMESSE'!$A$2:$F$25,3,FALSE)) -> GOL - 22-02-5000 - 22-12-5003 | D67: =LEFT(exp_SILP!$R67,5) -> 14:00 | E67: =RIGHT(exp_SILP!$R67,5) -> 15:00 | F67: =IF(exp_SILP!$AG67>=60,exp_SILP!$AG67/60,exp_SILP!$AG67) -> 1 | G67: =VLOOKUP(exp_SILP!$Y67,'DATI CM'!$A$2:$F$28,2,FALSE) -> PNFMRT85H50A859E | H67: =VLOOKUP(exp_SILP!$Y67,'DATI CM'!$A$2:$F$28,3,FALSE) -> A011 | I67: =IF(A67>0,"N","N") -> N | J67: =VLOOKUP(exp_SILP!$Y67,'DATI CM'!$A$2:$F$28,4,FALSE) -> BIELLA | K67: =VLOOKUP(exp_SILP!$B67,'DATI COMMESSE'!$A$2:$F$25,5,FALSE) -> 39.94 | L67: =IF(exp_SILP!$B67="A4.10 - LEP E - ORIENTAMENTO SPECIALISTICO SKILL GAP ANALYSIS - GRUPPO 3P",0,VLOOKUP(exp_SILP!$Y67,'DATI CM'!$A$2:$F$28,6,FALSE)) -> 25 | M67: =IFERROR(VLOOKUP(exp_SILP!$B67,'DATI CM'!$H$2:$I$16,2,FALSE)*exp_SILP!$F67,0) -> 0 | N67: =VLOOKUP(exp_SILP!$B67,'DATI COMMESSE'!$A$2:$F$25,4,FALSE) -> GOL | O67: =VLOOKUP(exp_SILP!$B67,'DATI COMMESSE'!$A$2:$F$25,5,FALSE)*exp_SILP!$F67 -> 39.94 | P67: =IF(MID(exp_SILP!$W67,10,2)>"40","F","M") -> M | Q67: 02/05/2023 | R67: 14:00-15:00 | S67: A.5 - LEP F1 - ACCOMPAGNAMENTO AL LAVORO | T67: Progetti per accreditati | V67: CIOCOIU IOSIF | W67: CCISFI61C23Z129N | X67: 23/03/1961 | Y67: PIANOFORTE MARTA | Z67: Erogato | AA67: INFORCOOP ECIPA PIEMONTE | AB67: Incontro MDL | AC67: INFORCOOP ECIPA PIEMONTE STRADA CAMPAGNE' 7 - BIELLA | AG67: 60 | AH67: 03/08/2023 | AI67: PNFMRT85H50A859E | AJ67: =VLOOKUP(exp_SILP!$Y67,'DATI CM'!$A$2:$F$28,2,FALSE) -> PNFMRT85H50A859E
A68: =IFERROR(VLOOKUP(exp_SILP!$W68,exp_utenti_P!D:D,1,FALSE),"_DA INSERIRE") -> MRZGPP65M28E047L | B68: =IF(AND(exp_SILP!$S68="A.3 ORIENTAMENTO PROFESSIONALE",exp_SILP!$AD68="4.2"),"A.3 ORIENTAMENTO PROFESSIONALE (CARCERE)", IF(AND(exp_SILP!$S68="A.3 ORIENTAMENTO PROFESSIONALE",exp_SILP!$AD68="."),"A.3 ORIENTAMENTO PROFESSIONALE (CARCERE)", IF(AND(exp_SILP!$S68="A.4 CONSULENZA ORIENTATIVA",exp_SILP!$AD68="4.2"),"A.4 CONSULENZA ORIENTATIVA (CARCERE)", IF(AND(exp_SILP!$S68="A.4 CONSULENZA ORIENTATIVA",exp_SILP!$AD68="."),"A.4 CONSULENZA ORIENTATIVA (CARCERE)", IF(AND(exp_SILP!$S68="A.5 - LEP F1 - ACCOMPAGNAMENTO AL LAVORO",exp_SILP!$AD68="4.2"),"A.5 - LEP F1 - ACCOMPAGNAMENTO AL LAVORO (CARCERE)", IF(AND(exp_SILP!$S68="A.5 - LEP F1 - ACCOMPAGNAMENTO AL LAVORO",exp_SILP!$AD68="."),"A.5 - LEP F1 - ACCOMPAGNAMENTO AL LAVORO (CARCERE)", IF(AND(exp_SILP!$S68="A.5.2a - TUTORAGGIO TIROCINI",exp_SILP!$AD68="4.2"),"A.5.2a - TUTORAGGIO TIROCINI (CARCERE)", exp_SILP!$S68))))))) -> A.5.1 ATTIVAZIONE E RICERCA OPPORTUNITA' (1-C) | C68: =CONCATENATE(VLOOKUP(exp_SILP!$B68,'DATI COMMESSE'!$A$2:$F$25,4,FALSE)," - ", VLOOKUP(exp_SILP!$B68,'DATI COMMESSE'!$A$2:$F$25,2,FALSE)," - ",VLOOKUP(exp_SILP!$B68,'DATI COMMESSE'!$A$2:$F$25,3,FALSE)) -> FRD - 22-02-5000 - 22-12-5002 | D68: =LEFT(exp_SILP!$R68,5) -> 14:00 | E68: =RIGHT(exp_SILP!$R68,5) -> 16:00 | F68: =IF(exp_SILP!$AG68>=60,exp_SILP!$AG68/60,exp_SILP!$AG68) -> 2 | G68: =VLOOKUP(exp_SILP!$Y68,'DATI CM'!$A$2:$F$28,2,FALSE) -> MNRCLD73B46G674U | H68: =VLOOKUP(exp_SILP!$Y68,'DATI CM'!$A$2:$F$28,3,FALSE) -> A011 | I68: =IF(A68>0,"N","N") -> N | J68: =VLOOKUP(exp_SILP!$Y68,'DATI CM'!$A$2:$F$28,4,FALSE) -> TORINO | K68: =VLOOKUP(exp_SILP!$B68,'DATI COMMESSE'!$A$2:$F$25,5,FALSE) -> 35.5 | L68: =IF(exp_SILP!$B68="A4.10 - LEP E - ORIENTAMENTO SPECIALISTICO SKILL GAP ANALYSIS - GRUPPO 3P",0,VLOOKUP(exp_SILP!$Y68,'DATI CM'!$A$2:$F$28,6,FALSE)) -> 25 | M68: =IFERROR(VLOOKUP(exp_SILP!$B68,'DATI CM'!$H$2:$I$16,2,FALSE)*exp_SILP!$F68,0) -> 0 | N68: =VLOOKUP(exp_SILP!$B68,'DATI COMMESSE'!$A$2:$F$25,4,FALSE) -> FRD | O68: =VLOOKUP(exp_SILP!$B68,'DATI COMMESSE'!$A$2:$F$25,5,FALSE)*exp_SILP!$F68 -> 71 | P68: =IF(MID(exp_SILP!$W68,10,2)>"40","F","M") -> M | Q68: 02/05/2023 | R68: 14:00-16:00 | S68: A.5.1 ATTIVAZIONE E RICERCA OPPORTUNITA' (1-C) | T68: Progetti per accreditati | V68: MARZELLA GIUSEPPE | W68: MRZGPP65M28E047L | X68: 28/08/1965 | Y68: MAINERO CLAUDIA | Z68: Erogato | AA68: INFORCOOP ECIPA PIEMONTE | AB68: Incontro MDLpresentato | AC68: INFORCOOP ECIPA PIEMONTE VIA TREVISO 12 - TORINO | AG68: 120 | AH68: 02/05/2023 | AI68: MNRCLD73B46G674U | AJ68: =VLOOKUP(exp_SILP!$Y68,'DATI CM'!$A$2:$F$28,2,FALSE) -> MNRCLD73B46G674U
A69: =IFERROR(VLOOKUP(exp_SILP!$W69,exp_utenti_P!D:D,1,FALSE),"_DA INSERIRE") -> LLJRHN57E55Z100A | B69: =IF(AND(exp_SILP!$S69="A.3 ORIENTAMENTO PROFESSIONALE",exp_SILP!$AD69="4.2"),"A.3 ORIENTAMENTO PROFESSIONALE (CARCERE)", IF(AND(exp_SILP!$S69="A.3 ORIENTAMENTO PROFESSIONALE",exp_SILP!$AD69="."),"A.3 ORIENTAMENTO PROFESSIONALE (CARCERE)", IF(AND(exp_SILP!$S69="A.4 CONSULENZA ORIENTATIVA",exp_SILP!$AD69="4.2"),"A.4 CONSULENZA ORIENTATIVA (CARCERE)", IF(AND(exp_SILP!$S69="A.4 CONSULENZA ORIENTATIVA",exp_SILP!$AD69="."),"A.4 CONSULENZA ORIENTATIVA (CARCERE)", IF(AND(exp_SILP!$S69="A.5 - LEP F1 - ACCOMPAGNAMENTO AL LAVORO",exp_SILP!$AD69="4.2"),"A.5 - LEP F1 - ACCOMPAGNAMENTO AL LAVORO (CARCERE)", IF(AND(exp_SILP!$S69="A.5 - LEP F1 - ACCOMPAGNAMENTO AL LAVORO",exp_SILP!$AD69="."),"A.5 - LEP F1 - ACCOMPAGNAMENTO AL LAVORO (CARCERE)", IF(AND(exp_SILP!$S69="A.5.2a - TUTORAGGIO TIROCINI",exp_SILP!$AD69="4.2"),"A.5.2a - TUTORAGGIO TIROCINI (CARCERE)", exp_SILP!$S69))))))) -> A4.10 - LEP E - ORIENTAMENTO SPECIALISTICO SKILL GAP ANALYSIS | C69: =CONCATENATE(VLOOKUP(exp_SILP!$B69,'DATI COMMESSE'!$A$2:$F$25,4,FALSE)," - ", VLOOKUP(exp_SILP!$B69,'DATI COMMESSE'!$A$2:$F$25,2,FALSE)," - ",VLOOKUP(exp_SILP!$B69,'DATI COMMESSE'!$A$2:$F$25,3,FALSE)) -> GOL - 22-02-5000 - 22-12-5003 | D69: =LEFT(exp_SILP!$R69,5) -> 11:00 | E69: =RIGHT(exp_SILP!$R69,5) -> 13:00 | F69: =IF(exp_SILP!$AG69>=60,exp_SILP!$AG69/60,exp_SILP!$AG69) -> 2 | G69: =VLOOKUP(exp_SILP!$Y69,'DATI CM'!$A$2:$F$28,2,FALSE) -> MNRCLD73B46G674U | H69: =VLOOKUP(exp_SILP!$Y69,'DATI CM'!$A$2:$F$28,3,FALSE) -> A011 | I69: =IF(A69>0,"N","N") -> N | J69: =VLOOKUP(exp_SILP!$Y69,'DATI CM'!$A$2:$F$28,4,FALSE) -> TORINO | K69: =VLOOKUP(exp_SILP!$B69,'DATI COMMESSE'!$A$2:$F$25,5,FALSE) -> 39.94 | L69: =IF(exp_SILP!$B69="A4.10 - LEP E - ORIENTAMENTO SPECIALISTICO SKILL GAP ANALYSIS - GRUPPO 3P",0,VLOOKUP(exp_SILP!$Y69,'DATI CM'!$A$2:$F$28,6,FALSE)) -> 25 | M69: =IFERROR(VLOOKUP(exp_SILP!$B69,'DATI CM'!$H$2:$I$16,2,FALSE)*exp_SILP!$F69,0) -> 0 | N69: =VLOOKUP(exp_SILP!$B69,'DATI COMMESSE'!$A$2:$F$25,4,FALSE) -> GOL | O69: =VLOOKUP(exp_SILP!$B69,'DATI COMMESSE'!$A$2:$F$25,5,FALSE)*exp_SILP!$F69 -> 79.88 | P69: =IF(MID(exp_SILP!$W69,10,2)>"40","F","M") -> F | Q69: 02/05/2023 | R69: 11:00-13:00 | S69: A4.10 - LEP E - ORIENTAMENTO SPECIALISTICO SKILL GAP ANALYSIS | T69: Progetti per accreditati | V69: LALAJ REXHINA | W69: LLJRHN57E55Z100A | X69: 15/05/1957 | Y69: MAINERO CLAUDIA | Z69: Erogato | AA69: INFORCOOP ECIPA PIEMONTE | AB69: Incontro MDLpresentato | AC69: INFORCOOP ECIPA PIEMONTE VIA TREVISO 12 - TORINO | AG69: 120 | AH69: 02/05/2023 | AI69: MNRCLD73B46G674U | AJ69: =VLOOKUP(exp_SILP!$Y69,'DATI CM'!$A$2:$F$28,2,FALSE) -> MNRCLD73B46G674U
A70: =IFERROR(VLOOKUP(exp_SILP!$W70,exp_utenti_P!D:D,1,FALSE),"_DA INSERIRE") -> SCHNRC64D55A859N | B70: =IF(AND(exp_SILP!$S70="A.3 ORIENTAMENTO PROFESSIONALE",exp_SILP!$AD70="4.2"),"A.3 ORIENTAMENTO PROFESSIONALE (CARCERE)", IF(AND(exp_SILP!$S70="A.3 ORIENTAMENTO PROFESSIONALE",exp_SILP!$AD70="."),"A.3 ORIENTAMENTO PROFESSIONALE (CARCERE)", IF(AND(exp_SILP!$S70="A.4 CONSULENZA ORIENTATIVA",exp_SILP!$AD70="4.2"),"A.4 CONSULENZA ORIENTATIVA (CARCERE)", IF(AND(exp_SILP!$S70="A.4 CONSULENZA ORIENTATIVA",exp_SILP!$AD70="."),"A.4 CONSULENZA ORIENTATIVA (CARCERE)", IF(AND(exp_SILP!$S70="A.5 - LEP F1 - ACCOMPAGNAMENTO AL LAVORO",exp_SILP!$AD70="4.2"),"A.5 - LEP F1 - ACCOMPAGNAMENTO AL LAVORO (CARCERE)", IF(AND(exp_SILP!$S70="A.5 - LEP F1 - ACCOMPAGNAMENTO AL LAVORO",exp_SILP!$AD70="."),"A.5 - LEP F1 - ACCOMPAGNAMENTO AL LAVORO (CARCERE)", IF(AND(exp_SILP!$S70="A.5.2a - TUTORAGGIO TIROCINI",exp_SILP!$AD70="4.2"),"A.5.2a - TUTORAGGIO TIROCINI (CARCERE)", exp_SILP!$S70))))))) -> A4.10 - LEP E - ORIENTAMENTO SPECIALISTICO SKILL GAP ANALYSIS | C70: =CONCATENATE(VLOOKUP(exp_SILP!$B70,'DATI COMMESSE'!$A$2:$F$25,4,FALSE)," - ", VLOOKUP(exp_SILP!$B70,'DATI COMMESSE'!$A$2:$F$25,2,FALSE)," - ",VLOOKUP(exp_SILP!$B70,'DATI COMMESSE'!$A$2:$F$25,3,FALSE)) -> GOL - 22-02-5000 - 22-12-5003 | D70: =LEFT(exp_SILP!$R70,5) -> 15:00 | E70: =RIGHT(exp_SILP!$R70,5) -> 16:00 | F70: =IF(exp_SILP!$AG70>=60,exp_SILP!$AG70/60,exp_SILP!$AG70) -> 1 | G70: =VLOOKUP(exp_SILP!$Y70,'DATI CM'!$A$2:$F$28,2,FALSE) -> PNFMRT85H50A859E | H70: =VLOOKUP(exp_SILP!$Y70,'DATI CM'!$A$2:$F$28,3,FALSE) -> A011 | I70: =IF(A70>0,"N","N") -> N | J70: =VLOOKUP(exp_SILP!$Y70,'DATI CM'!$A$2:$F$28,4,FALSE) -> BIELLA | K70: =VLOOKUP(exp_SILP!$B70,'DATI COMMESSE'!$A$2:$F$25,5,FALSE) -> 39.94 | L70: =IF(exp_SILP!$B70="A4.10 - LEP E - ORIENTAMENTO SPECIALISTICO SKILL GAP ANALYSIS - GRUPPO 3P",0,VLOOKUP(exp_SILP!$Y70,'DATI CM'!$A$2:$F$28,6,FALSE)) -> 25 | M70: =IFERROR(VLOOKUP(exp_SILP!$B70,'DATI CM'!$H$2:$I$16,2,FALSE)*exp_SILP!$F70,0) -> 0 | N70: =VLOOKUP(exp_SILP!$B70,'DATI COMMESSE'!$A$2:$F$25,4,FALSE) -> GOL | O70: =VLOOKUP(exp_SILP!$B70,'DATI COMMESSE'!$A$2:$F$25,5,FALSE)*exp_SILP!$F70 -> 39.94 | P70: =IF(MID(exp_SILP!$W70,10,2)>"40","F","M") -> F | Q70: 02/05/2023 | R70: 15:00-16:00 | S70: A4.10 - LEP E - ORIENTAMENTO SPECIALISTICO SKILL GAP ANALYSIS | T70: Progetti per accreditati | V70: SCHINTONE ENRICA | W70: SCHNRC64D55A859N | X70: 15/04/1964 | Y70: PIANOFORTE MARTA | Z70: Erogato | AA70: INFORCOOP ECIPA PIEMONTE | AB70: Incontro MDL | AC70: INFORCOOP ECIPA PIEMONTE STRADA CAMPAGNE' 7 - BIELLA | AG70: 60 | AH70: 17/05/2023 | AI70: PNFMRT85H50A859E | AJ70: =VLOOKUP(exp_SILP!$Y70,'DATI CM'!$A$2:$F$28,2,FALSE) -> PNFMRT85H50A859E
A71: =IFERROR(VLOOKUP(exp_SILP!$W71,exp_utenti_P!D:D,1,FALSE),"_DA INSERIRE") -> HLPVNT92E61L219L | B71: =IF(AND(exp_SILP!$S71="A.3 ORIENTAMENTO PROFESSIONALE",exp_SILP!$AD71="4.2"),"A.3 ORIENTAMENTO PROFESSIONALE (CARCERE)", IF(AND(exp_SILP!$S71="A.3 ORIENTAMENTO PROFESSIONALE",exp_SILP!$AD71="."),"A.3 ORIENTAMENTO PROFESSIONALE (CARCERE)", IF(AND(exp_SILP!$S71="A.4 CONSULENZA ORIENTATIVA",exp_SILP!$AD71="4.2"),"A.4 CONSULENZA ORIENTATIVA (CARCERE)", IF(AND(exp_SILP!$S71="A.4 CONSULENZA ORIENTATIVA",exp_SILP!$AD71="."),"A.4 CONSULENZA ORIENTATIVA (CARCERE)", IF(AND(exp_SILP!$S71="A.5 - LEP F1 - ACCOMPAGNAMENTO AL LAVORO",exp_SILP!$AD71="4.2"),"A.5 - LEP F1 - ACCOMPAGNAMENTO AL LAVORO (CARCERE)", IF(AND(exp_SILP!$S71="A.5 - LEP F1 - ACCOMPAGNAMENTO AL LAVORO",exp_SILP!$AD71="."),"A.5 - LEP F1 - ACCOMPAGNAMENTO AL LAVORO (CARCERE)", IF(AND(exp_SILP!$S71="A.5.2a - TUTORAGGIO TIROCINI",exp_SILP!$AD71="4.2"),"A.5.2a - TUTORAGGIO TIROCINI (CARCERE)", exp_SILP!$S71))))))) -> A4.10 - LEP E - ORIENTAMENTO SPECIALISTICO SKILL GAP ANALYSIS | C71: =CONCATENATE(VLOOKUP(exp_SILP!$B71,'DATI COMMESSE'!$A$2:$F$25,4,FALSE)," - ", VLOOKUP(exp_SILP!$B71,'DATI COMMESSE'!$A$2:$F$25,2,FALSE)," - ",VLOOKUP(exp_SILP!$B71,'DATI COMMESSE'!$A$2:$F$25,3,FALSE)) -> GOL - 22-02-5000 - 22-12-5003 | D71: =LEFT(exp_SILP!$R71,5) -> 16:00 | E71: =RIGHT(exp_SILP!$R71,5) -> 18:00 | F71: =IF(exp_SILP!$AG71>=60,exp_SILP!$AG71/60,exp_SILP!$AG71) -> 2 | G71: =VLOOKUP(exp_SILP!$Y71,'DATI CM'!$A$2:$F$28,2,FALSE) -> MNRCLD73B46G674U | H71: =VLOOKUP(exp_SILP!$Y71,'DATI CM'!$A$2:$F$28,3,FALSE) -> A011 | I71: =IF(A71>0,"N","N") -> N | J71: =VLOOKUP(exp_SILP!$Y71,'DATI CM'!$A$2:$F$28,4,FALSE) -> TORINO | K71: =VLOOKUP(exp_SILP!$B71,'DATI COMMESSE'!$A$2:$F$25,5,FALSE) -> 39.94 | L71: =IF(exp_SILP!$B71="A4.10 - LEP E - ORIENTAMENTO SPECIALISTICO SKILL GAP ANALYSIS - GRUPPO 3P",0,VLOOKUP(exp_SILP!$Y71,'DATI CM'!$A$2:$F$28,6,FALSE)) -> 25 | M71: =IFERROR(VLOOKUP(exp_SILP!$B71,'DATI CM'!$H$2:$I$16,2,FALSE)*exp_SILP!$F71,0) -> 0 | N71: =VLOOKUP(exp_SILP!$B71,'DATI COMMESSE'!$A$2:$F$25,4,FALSE) -> GOL | O71: =VLOOKUP(exp_SILP!$B71,'DATI COMMESSE'!$A$2:$F$25,5,FALSE)*exp_SILP!$F71 -> 79.88 | P71: =IF(MID(exp_SILP!$W71,10,2)>"40","F","M") -> F | Q71: 02/05/2023 | R71: 16:00-18:00 | S71: A4.10 - LEP E - ORIENTAMENTO SPECIALISTICO SKILL GAP ANALYSIS | T71: Progetti per accreditati | V71: HALEPLIYAN VALENTINA | W71: HLPVNT92E61L219L | X71: 21/05/1992 | Y71: MAINERO CLAUDIA | Z71: Erogato | AA71: INFORCOOP ECIPA PIEMONTE | AB71: Incontro MDLpresentato | AC71: INFORCOOP ECIPA PIEMONTE VIA TREVISO 12 - TORINO | AG71: 120 | AH71: 03/05/2023 | AI71: MNRCLD73B46G674U | AJ71: =VLOOKUP(exp_SILP!$Y71,'DATI CM'!$A$2:$F$28,2,FALSE) -> MNRCLD73B46G674U
A72: =IFERROR(VLOOKUP(exp_SILP!$W72,exp_utenti_P!D:D,1,FALSE),"_DA INSERIRE") -> PRCHLN84C69G713F | B72: =IF(AND(exp_SILP!$S72="A.3 ORIENTAMENTO PROFESSIONALE",exp_SILP!$AD72="4.2"),"A.3 ORIENTAMENTO PROFESSIONALE (CARCERE)", IF(AND(exp_SILP!$S72="A.3 ORIENTAMENTO PROFESSIONALE",exp_SILP!$AD72="."),"A.3 ORIENTAMENTO PROFESSIONALE (CARCERE)", IF(AND(exp_SILP!$S72="A.4 CONSULENZA ORIENTATIVA",exp_SILP!$AD72="4.2"),"A.4 CONSULENZA ORIENTATIVA (CARCERE)", IF(AND(exp_SILP!$S72="A.4 CONSULENZA ORIENTATIVA",exp_SILP!$AD72="."),"A.4 CONSULENZA ORIENTATIVA (CARCERE)", IF(AND(exp_SILP!$S72="A.5 - LEP F1 - ACCOMPAGNAMENTO AL LAVORO",exp_SILP!$AD72="4.2"),"A.5 - LEP F1 - ACCOMPAGNAMENTO AL LAVORO (CARCERE)", IF(AND(exp_SILP!$S72="A.5 - LEP F1 - ACCOMPAGNAMENTO AL LAVORO",exp_SILP!$AD72="."),"A.5 - LEP F1 - ACCOMPAGNAMENTO AL LAVORO (CARCERE)", IF(AND(exp_SILP!$S72="A.5.2a - TUTORAGGIO TIROCINI",exp_SILP!$AD72="4.2"),"A.5.2a - TUTORAGGIO TIROCINI (CARCERE)", exp_SILP!$S72))))))) -> A4.10 - LEP E - ORIENTAMENTO SPECIALISTICO SKILL GAP ANALYSIS | C72: =CONCATENATE(VLOOKUP(exp_SILP!$B72,'DATI COMMESSE'!$A$2:$F$25,4,FALSE)," - ", VLOOKUP(exp_SILP!$B72,'DATI COMMESSE'!$A$2:$F$25,2,FALSE)," - ",VLOOKUP(exp_SILP!$B72,'DATI COMMESSE'!$A$2:$F$25,3,FALSE)) -> GOL - 22-02-5000 - 22-12-5003 | D72: =LEFT(exp_SILP!$R72,5) -> 12:00 | E72: =RIGHT(exp_SILP!$R72,5) -> 13:00 | F72: =IF(exp_SILP!$AG72>=60,exp_SILP!$AG72/60,exp_SILP!$AG72) -> 1 | G72: =VLOOKUP(exp_SILP!$Y72,'DATI CM'!$A$2:$F$28,2,FALSE) -> PNFMRT85H50A859E | H72: =VLOOKUP(exp_SILP!$Y72,'DATI CM'!$A$2:$F$28,3,FALSE) -> A011 | I72: =IF(A72>0,"N","N") -> N | J72: =VLOOKUP(exp_SILP!$Y72,'DATI CM'!$A$2:$F$28,4,FALSE) -> BIELLA | K72: =VLOOKUP(exp_SILP!$B72,'DATI COMMESSE'!$A$2:$F$25,5,FALSE) -> 39.94 | L72: =IF(exp_SILP!$B72="A4.10 - LEP E - ORIENTAMENTO SPECIALISTICO SKILL GAP ANALYSIS - GRUPPO 3P",0,VLOOKUP(exp_SILP!$Y72,'DATI CM'!$A$2:$F$28,6,FALSE)) -> 25 | M72: =IFERROR(VLOOKUP(exp_SILP!$B72,'DATI CM'!$H$2:$I$16,2,FALSE)*exp_SILP!$F72,0) -> 0 | N72: =VLOOKUP(exp_SILP!$B72,'DATI COMMESSE'!$A$2:$F$25,4,FALSE) -> GOL | O72: =VLOOKUP(exp_SILP!$B72,'DATI COMMESSE'!$A$2:$F$25,5,FALSE)*exp_SILP!$F72 -> 39.94 | P72: =IF(MID(exp_SILP!$W72,10,2)>"40","F","M") -> F | Q72: 02/05/2023 | R72: 12:00-13:00 | S72: A4.10 - LEP E - ORIENTAMENTO SPECIALISTICO SKILL GAP ANALYSIS | T72: Progetti per accreditati | V72: PIERUCCI HELENIA | W72: PRCHLN84C69G713F | X72: 29/03/1984 | Y72: PIANOFORTE MARTA | Z72: Erogato | AA72: INFORCOOP ECIPA PIEMONTE | AB72: Incontro MDL | AC72: INFORCOOP ECIPA PIEMONTE STRADA CAMPAGNE' 7 - BIELLA | AG72: 60 | AH72: 21/06/2023 | AI72: PNFMRT85H50A859E | AJ72: =VLOOKUP(exp_SILP!$Y72,'DATI CM'!$A$2:$F$28,2,FALSE) -> PNFMRT85H50A859E
A73: =IFERROR(VLOOKUP(exp_SILP!$W73,exp_utenti_P!D:D,1,FALSE),"_DA INSERIRE") -> FYAMKH88P51Z343H | B73: =IF(AND(exp_SILP!$S73="A.3 ORIENTAMENTO PROFESSIONALE",exp_SILP!$AD73="4.2"),"A.3 ORIENTAMENTO PROFESSIONALE (CARCERE)", IF(AND(exp_SILP!$S73="A.3 ORIENTAMENTO PROFESSIONALE",exp_SILP!$AD73="."),"A.3 ORIENTAMENTO PROFESSIONALE (CARCERE)", IF(AND(exp_SILP!$S73="A.4 CONSULENZA ORIENTATIVA",exp_SILP!$AD73="4.2"),"A.4 CONSULENZA ORIENTATIVA (CARCERE)", IF(AND(exp_SILP!$S73="A.4 CONSULENZA ORIENTATIVA",exp_SILP!$AD73="."),"A.4 CONSULENZA ORIENTATIVA (CARCERE)", IF(AND(exp_SILP!$S73="A.5 - LEP F1 - ACCOMPAGNAMENTO AL LAVORO",exp_SILP!$AD73="4.2"),"A.5 - LEP F1 - ACCOMPAGNAMENTO AL LAVORO (CARCERE)", IF(AND(exp_SILP!$S73="A.5 - LEP F1 - ACCOMPAGNAMENTO AL LAVORO",exp_SILP!$AD73="."),"A.5 - LEP F1 - ACCOMPAGNAMENTO AL LAVORO (CARCERE)", IF(AND(exp_SILP!$S73="A.5.2a - TUTORAGGIO TIROCINI",exp_SILP!$AD73="4.2"),"A.5.2a - TUTORAGGIO TIROCINI (CARCERE)", exp_SILP!$S73))))))) -> A.5 - LEP F1 - ACCOMPAGNAMENTO AL LAVORO | C73: =CONCATENATE(VLOOKUP(exp_SILP!$B73,'DATI COMMESSE'!$A$2:$F$25,4,FALSE)," - ", VLOOKUP(exp_SILP!$B73,'DATI COMMESSE'!$A$2:$F$25,2,FALSE)," - ",VLOOKUP(exp_SILP!$B73,'DATI COMMESSE'!$A$2:$F$25,3,FALSE)) -> GOL - 22-02-5000 - 22-12-5003 | D73: =LEFT(exp_SILP!$R73,5) -> 13:00 | E73: =RIGHT(exp_SILP!$R73,5) -> 14:00 | F73: =IF(exp_SILP!$AG73>=60,exp_SILP!$AG73/60,exp_SILP!$AG73) -> 1 | G73: =VLOOKUP(exp_SILP!$Y73,'DATI CM'!$A$2:$F$28,2,FALSE) -> PNFMRT85H50A859E | H73: =VLOOKUP(exp_SILP!$Y73,'DATI CM'!$A$2:$F$28,3,FALSE) -> A011 | I73: =IF(A73>0,"N","N") -> N | J73: =VLOOKUP(exp_SILP!$Y73,'DATI CM'!$A$2:$F$28,4,FALSE) -> BIELLA | K73: =VLOOKUP(exp_SILP!$B73,'DATI COMMESSE'!$A$2:$F$25,5,FALSE) -> 39.94 | L73: =IF(exp_SILP!$B73="A4.10 - LEP E - ORIENTAMENTO SPECIALISTICO SKILL GAP ANALYSIS - GRUPPO 3P",0,VLOOKUP(exp_SILP!$Y73,'DATI CM'!$A$2:$F$28,6,FALSE)) -> 25 | M73: =IFERROR(VLOOKUP(exp_SILP!$B73,'DATI CM'!$H$2:$I$16,2,FALSE)*exp_SILP!$F73,0) -> 0 | N73: =VLOOKUP(exp_SILP!$B73,'DATI COMMESSE'!$A$2:$F$25,4,FALSE) -> GOL | O73: =VLOOKUP(exp_SILP!$B73,'DATI COMMESSE'!$A$2:$F$25,5,FALSE)*exp_SILP!$F73 -> 39.94 | P73: =IF(MID(exp_SILP!$W73,10,2)>"40","F","M") -> F | Q73: 02/08/2023 | R73: 13:00-14:00 | S73: A.5 - LEP F1 - ACCOMPAGNAMENTO AL LAVORO | T73: Progetti per accreditati | V73: FAYE MAME KHADY | W73: FYAMKH88P51Z343H | X73: 11/09/1988 | Y73: PIANOFORTE MARTA | Z73: Erogato | AA73: INFORCOOP ECIPA PIEMONTE | AB73: Incontro MDL | AC73: INFORCOOP ECIPA PIEMONTE STRADA CAMPAGNE' 7 - BIELLA | AG73: 60 | AH73: 03/08/2023 | AI73: PNFMRT85H50A859E | AJ73: =VLOOKUP(exp_SILP!$Y73,'DATI CM'!$A$2:$F$28,2,FALSE) -> PNFMRT85H50A859E
A74: =IFERROR(VLOOKUP(exp_SILP!$W74,exp_utenti_P!D:D,1,FALSE),"_DA INSERIRE") -> GNNSFN88D13H355K | B74: =IF(AND(exp_SILP!$S74="A.3 ORIENTAMENTO PROFESSIONALE",exp_SILP!$AD74="4.2"),"A.3 ORIENTAMENTO PROFESSIONALE (CARCERE)", IF(AND(exp_SILP!$S74="A.3 ORIENTAMENTO PROFESSIONALE",exp_SILP!$AD74="."),"A.3 ORIENTAMENTO PROFESSIONALE (CARCERE)", IF(AND(exp_SILP!$S74="A.4 CONSULENZA ORIENTATIVA",exp_SILP!$AD74="4.2"),"A.4 CONSULENZA ORIENTATIVA (CARCERE)", IF(AND(exp_SILP!$S74="A.4 CONSULENZA ORIENTATIVA",exp_SILP!$AD74="."),"A.4 CONSULENZA ORIENTATIVA (CARCERE)", IF(AND(exp_SILP!$S74="A.5 - LEP F1 - ACCOMPAGNAMENTO AL LAVORO",exp_SILP!$AD74="4.2"),"A.5 - LEP F1 - ACCOMPAGNAMENTO AL LAVORO (CARCERE)", IF(AND(exp_SILP!$S74="A.5 - LEP F1 - ACCOMPAGNAMENTO AL LAVORO",exp_SILP!$AD74="."),"A.5 - LEP F1 - ACCOMPAGNAMENTO AL LAVORO (CARCERE)", IF(AND(exp_SILP!$S74="A.5.2a - TUTORAGGIO TIROCINI",exp_SILP!$AD74="4.2"),"A.5.2a - TUTORAGGIO TIROCINI (CARCERE)", exp_SILP!$S74))))))) -> A.5 - LEP F1 - ACCOMPAGNAMENTO AL LAVORO | C74: =CONCATENATE(VLOOKUP(exp_SILP!$B74,'DATI COMMESSE'!$A$2:$F$25,4,FALSE)," - ", VLOOKUP(exp_SILP!$B74,'DATI COMMESSE'!$A$2:$F$25,2,FALSE)," - ",VLOOKUP(exp_SILP!$B74,'DATI COMMESSE'!$A$2:$F$25,3,FALSE)) -> GOL - 22-02-5000 - 22-12-5003 | D74: =LEFT(exp_SILP!$R74,5) -> 16:00 | E74: =RIGHT(exp_SILP!$R74,5) -> 18:00 | F74: =IF(exp_SILP!$AG74>=60,exp_SILP!$AG74/60,exp_SILP!$AG74) -> 2 | G74: =VLOOKUP(exp_SILP!$Y74,'DATI CM'!$A$2:$F$28,2,FALSE) -> FLCSRN79S42L219X | H74: =VLOOKUP(exp_SILP!$Y74,'DATI CM'!$A$2:$F$28,3,FALSE) -> A011 | I74: =IF(A74>0,"N","N") -> N | J74: =VLOOKUP(exp_SILP!$Y74,'DATI CM'!$A$2:$F$28,4,FALSE) -> TORINO | K74: =VLOOKUP(exp_SILP!$B74,'DATI COMMESSE'!$A$2:$F$25,5,FALSE) -> 39.94 | L74: =IF(exp_SILP!$B74="A4.10 - LEP E - ORIENTAMENTO SPECIALISTICO SKILL GAP ANALYSIS - GRUPPO 3P",0,VLOOKUP(exp_SILP!$Y74,'DATI CM'!$A$2:$F$28,6,FALSE)) -> 25 | M74: =IFERROR(VLOOKUP(exp_SILP!$B74,'DATI CM'!$H$2:$I$16,2,FALSE)*exp_SILP!$F74,0) -> 0 | N74: =VLOOKUP(exp_SILP!$B74,'DATI COMMESSE'!$A$2:$F$25,4,FALSE) -> GOL | O74: =VLOOKUP(exp_SILP!$B74,'DATI COMMESSE'!$A$2:$F$25,5,FALSE)*exp_SILP!$F74 -> 79.88 | P74: =IF(MID(exp_SILP!$W74,10,2)>"40","F","M") -> M | Q74: 02/08/2023 | R74: 16:00-18:00 | S74: A.5 - LEP F1 - ACCOMPAGNAMENTO AL LAVORO | T74: Progetti per accreditati | V74: GIANNELLA STEFANO | W74: GNNSFN88D13H355K | X74: 13/04/1988 | Y74: FALCONE SERENA | Z74: Erogato | AA74: INFORCOOP ECIPA PIEMONTE | AB74: Incontro MDLpresentato | AC74: INFORCOOP ECIPA PIEMONTE VIA LIVORNO 53/b - TORINO | AG74: 120 | AH74: 02/08/2023 | AI74: FLCSRN79S42L219X | AJ74: =VLOOKUP(exp_SILP!$Y74,'DATI CM'!$A$2:$F$28,2,FALSE) -> FLCSRN79S42L219X
